Workbook
Name n_1: {"","одинz","дваz","триz","четыреz","пятьz","шестьz","семьz","восемьz","девятьz"}
Name n_1: {"","одинz","дваz","триz","четыреz","пятьz","шестьz","семьz","восемьz","девятьz"}
Name n_1: {"","одинz","дваz","триz","четыреz","пятьz","шестьz","семьz","восемьz","девятьz"}
Name n_1: {"","одинz","дваz","триz","четыреz","пятьz","шестьz","семьz","восемьz","девятьz"}
Name n_1: {"","одинz","дваz","триz","четыреz","пятьz","шестьz","семьz","восемьz","девятьz"}
Name n_1: {"","одинz","дваz","триz","четыреz","пятьz","шестьz","семьz","восемьz","девятьz"}
Name n_2: {"десятьz","одиннадцатьz","двенадцатьz","тринадцатьz","четырнадцатьz","пятнадцатьz","шестнадцатьz","семнадцатьz","восемнадцатьz","девятнадцатьz"}
Name n_2: {"десятьz","одиннадцатьz","двенадцатьz","тринадцатьz","четырнадцатьz","пятнадцатьz","шестнадцатьz","семнадцатьz","восемнадцатьz","девятнадцатьz"}
Name n_2: {"десятьz","одиннадцатьz","двенадцатьz","тринадцатьz","четырнадцатьz","пятнадцатьz","шестнадцатьz","семнадцатьz","восемнадцатьz","девятнадцатьz"}
Name n_2: {"десятьz","одиннадцатьz","двенадцатьz","тринадцатьz","четырнадцатьz","пятнадцатьz","шестнадцатьz","семнадцатьz","восемнадцатьz","девятнадцатьz"}
Name n_2: {"десятьz","одиннадцатьz","двенадцатьz","тринадцатьz","четырнадцатьz","пятнадцатьz","шестнадцатьz","семнадцатьz","восемнадцатьz","девятнадцатьz"}
Name n_2: {"десятьz","одиннадцатьz","двенадцатьz","тринадцатьz","четырнадцатьz","пятнадцатьz","шестнадцатьz","семнадцатьz","восемнадцатьz","девятнадцатьz"}
Name n_3: {"";1;"двадцатьz";"тридцатьz";"сорокz";"пятьдесятz";"шестьдесятz";"семьдесятz";"восемьдесятz";"девяностоz"}
Name n_3: {"";1;"двадцатьz";"тридцатьz";"сорокz";"пятьдесятz";"шестьдесятz";"семьдесятz";"восемьдесятz";"девяностоz"}
Name n_3: {"";1;"двадцатьz";"тридцатьz";"сорокz";"пятьдесятz";"шестьдесятz";"семьдесятz";"восемьдесятz";"девяностоz"}
Name n_3: {"";1;"двадцатьz";"тридцатьz";"сорокz";"пятьдесятz";"шестьдесятz";"семьдесятz";"восемьдесятz";"девяностоz"}
Name n_3: {"";1;"двадцатьz";"тридцатьz";"сорокz";"пятьдесятz";"шестьдесятz";"семьдесятz";"восемьдесятz";"девяностоz"}
Name n_3: {"";1;"двадцатьz";"тридцатьz";"сорокz";"пятьдесятz";"шестьдесятz";"семьдесятz";"восемьдесятz";"девяностоz"}
Name n_4: {"","стоz","двестиz","тристаz","четырестаz","пятьсотz","шестьсотz","семьсотz","восемьсотz","девятьсотz"}
Name n_4: {"","стоz","двестиz","тристаz","четырестаz","пятьсотz","шестьсотz","семьсотz","восемьсотz","девятьсотz"}
Name n_4: {"","стоz","двестиz","тристаz","четырестаz","пятьсотz","шестьсотz","семьсотz","восемьсотz","девятьсотz"}
Name n_4: {"","стоz","двестиz","тристаz","четырестаz","пятьсотz","шестьсотz","семьсотz","восемьсотz","девятьсотz"}
Name n_4: {"","стоz","двестиz","тристаz","четырестаz","пятьсотz","шестьсотz","семьсотz","восемьсотz","девятьсотz"}
Name n_4: {"","стоz","двестиz","тристаz","четырестаz","пятьсотz","шестьсотz","семьсотz","восемьсотz","девятьсотz"}
Name n_5: {"","однаz","двеz","триz","четыреz","пятьz","шестьz","семьz","восемьz","девятьz"}
Name n_5: {"","однаz","двеz","триz","четыреz","пятьz","шестьz","семьz","восемьz","девятьz"}
Name n_5: {"","однаz","двеz","триz","четыреz","пятьz","шестьz","семьz","восемьz","девятьz"}
Name n_5: {"","однаz","двеz","триz","четыреz","пятьz","шестьz","семьz","восемьz","девятьz"}
Name n_5: {"","однаz","двеz","триz","четыреz","пятьz","шестьz","семьz","восемьz","девятьz"}
Name n_5: {"","однаz","двеz","триz","четыреz","пятьz","шестьz","семьz","восемьz","девятьz"}
Name n0: "000000000000"&MID(1/2,2,1)&"00"
Name n0x: IF('Акт невозврата Вышки'!n_3=1,'Акт невозврата Вышки'!n_2,'Акт невозврата Вышки'!n_3&'Акт невозврата Вышки'!n_1)
Name n0x: IF('Акт невозврата Леса'!n_3=1,'Акт невозврата Леса'!n_2,'Акт невозврата Леса'!n_3&'Акт невозврата Леса'!n_1)
Name n0x: IF(ДляДоговора!n_3=1,ДляДоговора!n_2,ДляДоговора!n_3&ДляДоговора!n_1)
Name n0x: IF(n_3=1,n_2,n_3&n_1)
Name n0x: IF(n_3=1,n_2,n_3&n_1)
Name n0x: IF(n_3=1,n_2,n_3&n_1)
Name n1x: IF('Акт невозврата Вышки'!n_3=1,'Акт невозврата Вышки'!n_2,'Акт невозврата Вышки'!n_3&'Акт невозврата Вышки'!n_5)
Name n1x: IF('Акт невозврата Леса'!n_3=1,'Акт невозврата Леса'!n_2,'Акт невозврата Леса'!n_3&'Акт невозврата Леса'!n_5)
Name n1x: IF(ДляДоговора!n_3=1,ДляДоговора!n_2,ДляДоговора!n_3&ДляДоговора!n_5)
Name n1x: IF(n_3=1,n_2,n_3&n_5)
Name n1x: IF(n_3=1,n_2,n_3&n_5)
Name n1x: IF(n_3=1,n_2,n_3&n_5)
Name Договоры: '[1]Расчет лесов'!#REF!
Name Договоры: '[1]Расчет лесов'!#REF!
Name Договоры: '[1]Расчет лесов'!#REF!
Name Договоры: 'Расчет лесов'!#REF!
Name Договоры: 'Расчет лесов'!#REF!
Name мил: {0,"овz";1,"z";2,"аz";5,"овz"}
Name мил: {0,"овz";1,"z";2,"аz";5,"овz"}
Name мил: {0,"овz";1,"z";2,"аz";5,"овz"}
Name мил: {0,"овz";1,"z";2,"аz";5,"овz"}
Name мил: {0,"овz";1,"z";2,"аz";5,"овz"}
Name мил: {0,"овz";1,"z";2,"аz";5,"овz"}
Name тыс: {0,"тысячz";1,"тысячаz";2,"тысячиz";5,"тысячz"}
Name тыс: {0,"тысячz";1,"тысячаz";2,"тысячиz";5,"тысячz"}
Name тыс: {0,"тысячz";1,"тысячаz";2,"тысячиz";5,"тысячz"}
Name тыс: {0,"тысячz";1,"тысячаz";2,"тысячиz";5,"тысячz"}
Name тыс: {0,"тысячz";1,"тысячаz";2,"тысячиz";5,"тысячz"}
Name тыс: {0,"тысячz";1,"тысячаz";2,"тысячиz";5,"тысячz"}

Sheet Расчет лесов
A1: УПСК Аренда строительных лесов | B1: Параметры цен | I1: Параметры здания/стены | N1: Город= | O1: Екатеринбург | P1: к= | Q1: =IF(O1="Екатеринбург",AG22,IF(O1="Челябинск",AG23,IF(O1="Новосибирск",AG25,IF(O1="Пермь",AG24)))) -> 1 | Y1: Договор | Z1: НДС | AA1: Длина | AB1: Высота | AF1: Кол-во метров/ срок аренды | AG1: до 3х дней | AH1: До недели | AI1: До 2-х недель | AJ1: До месяца | AK1: До 45дн | AL1: До 2-х месяцев | AM1: Св 2 месяцев
B2: цена за м2 | C2: =IF(AND(C4<=7,L12<=50),AH2,IF(AND(C4<=14,L12<=50),AI2,IF(AND(C4<=30,L12<=50),AJ2,IF(AND(C4<=45,L12<=50),AK2,IF(AND(C4<=60,L12<=50),AL2,IF(AND(C4>60,L12<=50),AM2, IF(AND(C4<=7,L12<=100),AH3, IF(AND(C4<=14,L12<=100),AI3, IF(AND(C4<=30,L12<=100),AJ3,IF(AND(C4<=45,L12<=100),AK3, IF(AND(C4<=60,L12<=100),AL3, IF(AND(C4>60,L12<=100),AM3, IF(AND(C4<=7,L12<=300),AH4, IF(AND(C4<=14,L12<=300),AI4, IF(AND(C4<=30,L12<=300),AJ4,IF(AND(C4<=45,L12<=300),AK4, IF(AND(C4<=60,L12<=300),AL4, IF(AND(C4>60,L12<=300),AM4, IF(AND(C4<=7,L12<=500),AH5, IF(AND(C4<=14,L12<=500),AI5, IF(AND(C4<=30,L12<=500),AJ5,IF(AND(C4<=45,L12<=500),AK5, IF(AND(C4<=60,L12<=500),AL5, IF(AND(C4>60,L12<=500),AM5, IF(AND(C4<=7,L12<=1000),AH6, IF(AND(C4<=14,L12<=1000),AI6, IF(AND(C4<=30,L12<=1000),AJ6,IF(AND(C4<=45,L12<=1000),AK6, IF(AND(C4<=60,L12<=1000),AL6, IF(AND(C4>60,L12<=1000),AM6, IF(AND(C4<=7,L12>1000),AH7, IF(AND(C4<=14,L12>1000),AI7, IF(AND(C4<=30,L12>1000),AJ7, IF(AND(C4<=45,L12>1000),AK7, IF(AND(C4<=60,L12>1000),AL7, IF(AND(C4>60,L12>1000),AM7, "нету" ))))))))))))))))))))))))))))))))))))*Q1+Q21 -> 3.2 | D2: руб | J2: длинна | K2: высота | L2: ПЛОЩАДЬ | M2: проверка | N2: Доставка= | O2: 0 | Q2: Сезон дисконт | S2: 1.2 | T2: для юр | V2: =IF(B8=B9,1.7,1) -> 1.7 | Y2: Физ | Z2: без НДС | AA2: 0 | AB2: 0 | AE2: 1 | AF2: До 50м2 | AG2: 10 | AH2: 8 | AI2: 4.5 | AJ2: 3.2 | AK2: 2.5 | AL2: 2 | AM2: 1.6
B3: ст-ть аренды | C3: =ROUNDUP((C2*L12*S2*V2+L21*S2+Q22),-1) -> 210 | D3: в сутки | I3: Сторона1 | J3: 3 | K3: 8 | L3: =J3*K3 -> 24 | M3: =L3/3 -> 8 | N3: Погрузка= | O3: =AJ25*150 -> 300 | Q3: нал | R3: безнал | Y3: Юр | Z3: с НДС 20% | AA3: 3 | AB3: 2 | AE3: 2 | AF3: До 100м2 | AG3: 8 | AH3: 5 | AI3: 3.7 | AJ3: 2.7 | AK3: 2 | AL3: 1.65 | AM3: 1.4
B4: кол-во суток | C4: 30 | J4: =J3/3 -> 1 | K4: =K3/2 -> 4 | M4: =J4*K4 -> 4 | N4: Расстояние | O4: 50 | P4: км | Q4: =O4*2*O5 -> 1800 | R4: =Q4*1.18 -> 2124 | Y4: своё знач. | AA4: 6 | AB4: 4 | AE4: 3 | AF4: До 300м2 | AG4: 5 | AH4: 4 | AI4: 2.8 | AJ4: 2.1 | AK4: 1.7 | AL4: 1.45 | AM4: 1.25
B5: 1м2 стоит | C5: =ROUNDUP(D16/L12, 0) -> 1269 | D5: руб | I5: Сторона2 | J5: 0 | K5: 0 | L5: =J5*K5 -> 0 | M5: =L5/3 -> 0 | N5: Цена за км | O5: 18 | Z5: =IF(O9="без НДС",0,1) -> 1 | AA5: 9 | AB5: 6 | AE5: 4 | AF5: До 500м2 | AH5: 3 | AI5: 2 | AJ5: 1.65 | AK5: 1.5 | AL5: 1.3 | AM5: 1.1
J6: =J5/3 -> 0 | K6: =K5/2 -> 0 | M6: =J6*K6 -> 0 | N6: Договор | O6: своё знач. | P6: = | Q6: 10 | AA6: 12 | AB6: 8 | AE6: 5 | AF6: До 1000м2 | AH6: 2.5 | AI6: 1.7 | AJ6: 1.4 | AK6: 1.25 | AL6: 1.1 | AM6: 1
A7: Наименование | B7: Количество | C7: Стоимость | D7: Сумма, руб. | E7: % | I7: Сторона3 | J7: 0 | K7: 0 | L7: =J7*K7 -> 0 | M7: =L7/3 -> 0 | N7: Залог | O7: =Q6 -> 10 | P7: % | Y7: =IF(J3<=18,0,IF(J3<=39,0,0)) -> 0 | AA7: 15 | AB7: 10 | AE7: 6 | AF7: Св 1000м2 | AH7: 2 | AI7: 1.5 | AJ7: 1.25 | AK7: 1.1 | AL7: 1 | AM7: 0.9
A8: 1 Рама проходная ЛСПР-200 | B8: =(J16-J17)+(K16-K17)+(L16-L17)+(M16-M17)+(N16-N17) -> 4 | C8: =AI32 -> 1400 | D8: =B8*C8 -> 5600 | E8: =D8*100/$D$16 -> 18.396846 | F8: =$C$3/100*E8 -> 38.633377 | G8: =IF(B8=0,0,F8/B8) -> 9.6583443 | J8: =J7/3 -> 0 | K8: =K7/2 -> 0 | M8: =J8*K8 -> 0 | N8: Вес | O8: =AI24 -> 375.6 | P8: кг | Q8: Машин | R8: =O8/1400 -> 0.26828571 | AA8: 18 | AB8: 12
A9: 2 Рама с лестницей ЛСПР-200 | B9: =J17+K17+L17+M17+N17 -> 4 | C9: =AI33 -> 1670 | D9: =B9*C9 -> 6680 | E9: =D9*100/$D$16 -> 21.944809 | F9: =$C$3/100*E9 -> 46.0841 | G9: =IF(B9=0,0,F9/B9) -> 11.521025 | I9: Сторона4 | J9: 0 | K9: 0 | L9: =J9*K9 -> 0 | M9: =L9/3 -> 0 | N9: Объем | O9: =AJ24 -> 1.6848 | P9: м3 | Y9: =B8+B9 -> 8 | AA9: 21 | AB9: 14 | AE9: Подмости | AF9: шт (3м*1м) | AH9: 18 | AI9: 13 | AJ9: 10 | AK9: 8 | AL9: 7 | AM9: 5
A10: 3 Диагональная связь (3,3 м) ЛСПР-200 | B10: =J19+K19+L19+M19+N19 -> 4 | C10: =AI34 -> 630 | D10: =B10*C10 -> 2520 | E10: =D10*100/$D$16 -> 8.2785808 | F10: =$C$3/100*E10 -> 17.38502 | G10: =IF(B10=0,0,F10/B10) -> 4.3462549 | J10: =J9/3 -> 0 | K10: =K9/2 -> 0 | M10: =J10*K10 -> 0 | AA10: 24 | AB10: 16
A11: 4 Горизонтальная связь | B11: =J18+K18+L18+M18+N18 -> 4 | C11: =AI35 -> 320 | D11: =B11*C11 -> 1280 | E11: =D11*100/$D$16 -> 4.2049934 | F11: =$C$3/100*E11 -> 8.8304862 | G11: =IF(B11=0,0,F11/B11) -> 2.2076216 | N11: Диагонали | O11: В каждую | AA11: 27 | AB11: 18
A12: 5 Мостки (настил) деревянные | B12: =J21*3 -> 12 | C12: =AI36 -> 450 | D12: =B12*C12 -> 5400 | E12: =D12*100/$D$16 -> 17.739816 | F12: =$C$3/100*E12 -> 37.253614 | G12: =IF(B12=0,0,F12/B12) -> 3.1044678 | I12: Итого площадь | L12: =L3+L5+L7+L9 -> 24 | M12: м2 | AA12: 30 | AB12: 20
A13: 6 Ригель для настила | B13: =J21*2 -> 8 | C13: =AI37 -> 1120 | D13: =B13*C13 -> 8960 | E13: =D13*100/$D$16 -> 29.434954 | F13: =$C$3/100*E13 -> 61.813403 | G13: =IF(B13=0,0,F13/B13) -> 7.7266754 | N13: Минималка у транпортной комп | Q13: =O4*2*15+2*520 -> 2540 | R13: =Q13*1.2 -> 3048 | AA13: 33 | AB13: 22 | AG13: 4 | AH13: 7 | AI13: 14 | AJ13: 30 | AK13: 45 | AL13: 60 | AM13: 60
A14: 7 Кронштейн | B14: 0 | C14: 200 | D14: =B14*C14 -> 0 | I14: Количество элементов | AA14: 36 | AB14: 24
A15: 8 Башмак | B15: 0 | C15: 150 | D15: =B15*C15 -> 0 | J15: С1 | K15: С2 | L15: С3 | M15: С4 | N15: Доп связи | AA15: 39 | AB15: 26
A16: Общая рыночная стоимость арендуемого оборудования | D16: =SUM(D8:D15) -> 30440 | I16: всего рам | J16: =(J4+1)*K4 -> 8 | K16: =(J6+1)*K6 -> 0 | L16: =(J8+1)*K8 -> 0 | M16: =(J10+1)*K10 -> 0 | N16: 0 | AA16: 42 | AB16: 28 | AI16: вес | AJ16: объем | AL16: Диагонали
A17: =CONCATENATE("Стоимость залога за оборудование составляет ", O7, "% от общей рыночной стоимости") -> Стоимость залога за оборудование составляет 10% от общей рыночной стоимости | D17: =ROUNDUP(D16/100*O7,-2)+Q23 -> 3100 | I17: с лестницей | J17: =K4*1+K4*Y7 -> 4 | K17: =K6*1+K6*Y7 -> 0 | L17: =K8*1+K8*Y7 -> 0 | M17: =K10*1+K10*Y7 -> 0 | N17: 0 | AA17: 45 | AB17: 30 | AH17: 9.7 | AI17: =10*B8 -> 40 | AJ17: =0.1*B8 -> 0.4 | AL17: В каждую
A18: Стоимость доставки оборудования до объекта Арендатора* | D18: =O2 -> 0 | I18: секций/гор. | J18: =CEILING(J4*K4*AL22,1) -> 4 | K18: =CEILING(J6*K6*AL22,1) -> 0 | L18: =CEILING(J8*K8*AL22,1) -> 0 | M18: =CEILING(J10*K10*AL22,1) -> 0 | N18: 0 | AA18: 48 | AB18: 32 | AH18: 11.7 | AI18: =11.7*B9 -> 46.8 | AJ18: =0.1*B9 -> 0.4 | AL18: В шахматном
A19: Стоимость вывоза оборудования с объекта Арендатора | D19: =O2 -> 0 | I19: диаг связи | J19: =CEILING(J4*K4/AL21,1) -> 4 | K19: =CEILING(J6*K6/AL21,1) -> 0 | L19: =CEILING(J8*K8/AL21,1) -> 0 | M19: =CEILING(J10*K10/AL21,1) -> 0 | N19: 0 | AA19: 51 | AB19: 34 | AH19: 5.6 | AI19: =5.6*B10 -> 22.4 | AJ19: =0.0019*B10 -> 0.0076
A20: Монтаж и демонтаж оборудования | D20: 0 | I20: Настил | J20: кол-во | K20: цена/д | L20: Итого | O20: Надбавка/(дисконт) | S20: желаемая цена | AA20: 54 | AB20: 36 | AH20: 2.6 | AI20: =2.6*B11 -> 10.4 | AJ20: =0.0041*B11 -> 0.0164
A21: Погрузка и выгрузка оборудования | D21: 0 | J21: 4 | K21: =IF(AND(C4<=7),AH9,IF(AND(C4<=14),AI9,IF(AND(C4<=30),AJ9,IF(AND(C4<=45),AK9,IF(AND(C4<=60),AL9, IF(AND(C4>60),AM9, "нету"))))))+Q24 -> 10 | L21: =J21*K21 -> 40 | O21: цена за 1м2 | Q21: 0 | R21: руб. | AA21: 57 | AB21: 38 | AF21: Город | AI21: =15*B12 -> 180 | AJ21: =0.068*B12 -> 0.816 | AL21: =IF(O11="В каждую",1,2) -> 1
A22: =CONCATENATE("Стоимость аренды всего оборудования за ", C4," суток согласно п. 3.1 договора") -> Стоимость аренды всего оборудования за 30 суток согласно п. 3.1 договора | D22: =((C3)*C4)+Q27 -> 6300 | I22: нужно | J22: =M4+M6+M8+M10 -> 4 | O22: аренда в сутки | P22: =S22-C3 -> -210 | Q22: 0 | R22: руб. | S22: 0 | AA22: 60 | AB22: 40 | AF22: Екатеринбург | AG22: 1 | AI22: =9.5*B13 -> 76 | AJ22: =0.0056*B13 -> 0.0448 | AL22: =IF(O11="В каждую",1,1.5) -> 1
I23: 1 настил= | J23: 2 ригеля + 3 щита | O23: Залог | Q23: 0 | R23: руб. | AA23: 63 | AF23: Челябинск | AG23: 1.4
A24: Итого: | D24: =D17+D18+D19+D20+D21+D22+D23 -> 9400 | O24: Настил | Q24: 0 | R24: руб. | AA24: 66 | AF24: Пермь | AG24: 1.15 | AI24: =SUM(AI17:AI22) -> 375.6 | AJ24: =SUM(AJ17:AJ22) -> 1.6848
A25: в т.ч. Залог | D25: =D17 -> 3100 | I25: Процент окупаемости | L25: =IF(C4<=3,3,IF(C4<=7,4,IF(C4<=14,6,IF(C4<=21,8,IF(C4<=30,10,IF(C4<=45,14,IF(C4<=60,17,IF(C4<=90,22,IF(C4<=120,27,IF(C4<=180,32,IF(C4>180,40))))))))))) -> 10 | O25: Рын стоимость | Q25: 0 | AA25: 69 | AF25: Новосибирск | AG25: 1.15 | AJ25: =CEILING(AI24/400,2) -> 2
I26: Рекомендуемая цена | L26: =(D16/100*L25)/C4 -> 101.46667 | M26: руб | AA26: 72
O27: Стоимость всего | Q27: 0 | AA27: 75
AA28: 78
B29: минимум | C29: максимум | AA29: 81
A30: Доставки | AA30: 84 | AH30: коэф повышения | AI30: 1.15
A31: По городу | B31: 900 | AA31: 87 | AI31: наши | AJ31: цены абриса | AK31: стали | AL31: было
A32: Арамиль | B32: 1500 | C32: 1800 | AA32: 90 | AI32: =ROUNDUP(AJ32*$AI$30,-1) -> 1400 | AJ32: 1210 | AK32: 1459 | AL32: 1300 | AM32: 1520
A33: Балтым | B33: 1000 | C33: 1500 | AA33: 93 | AI33: =ROUNDUP(AJ33*$AI$30,-1) -> 1670 | AJ33: 1450 | AK33: 1770 | AL33: 1550 | AM33: 1760
A34: Верхнее Дуброво | B34: 1200 | AA34: 96 | AI34: =ROUNDUP(AJ34*$AI$30,-1) -> 630 | AJ34: 546 | AK34: 730 | AL34: 700 | AM34: 735
A35: Верхняя Пышма | B35: 1300 | C35: 1600 | AA35: 99 | AI35: =ROUNDUP(AJ35*$AI$30,-1) -> 320 | AJ35: 272 | AK35: 356 | AL35: 345 | AM35: 367
A36: Гагарский пос. | B36: 1500 | AA36: 102 | AI36: =ROUNDUP(AJ36*$AI$30,-1) -> 450 | AJ36: 390 | AK36: 390 | AL36: 390 | AM36: 390
A37: Горный Щит | B37: 1500 | AA37: 105 | AI37: =ROUNDUP(AJ37*$AI$30,-1) -> 1120 | AJ37: 970 | AK37: 1440 | AL37: 1150 | AM37: 1390
A38: Сухой лог, Глядены | B38: 3500 | AA38: 108
A39: Исток | B39: 1200 | C39: 1500 | AA39: 111
A40: Клевер | B40: 1800 | AA40: 114
A41: Кузино пос. | B41: 2400 | AA41: 117
A42: Карасеозерск1 | B42: 1200 | AA42: 120
A43: Косулино | B43: 1800 | C43: 2000 | AA43: 123
A44: Лукоморье КП | B44: 2100 | AA44: 126
A45: Мельница | B45: 1500 | C45: 1800 | AA45: 129
A46: Мезенское | B46: 1700 | AA46: 132
A47: Малые Брусяны | B47: 1500 | C47: 1200 | AA47: 135
A48: Н Тура | B48: 5000 | AA48: 138
A49: Новая Россоха | B49: 1800 | AA49: 141
A50: Первоуральск | B50: 2000 | C50: 2400 | AA50: 144
A51: Палкино дер. | B51: 1200 | AA51: 147
A52: Староуткинск | B52: 3000 | AA52: 150
A53: Березовский | B53: 1500 | C53: 1300 | AA53: 153
A54: Каменск-Уральский | B54: 3500 | C54: 4000 | AA54: 156
A55: Курганово | B55: 1600 | C55: 1900 | AA55: 159
A56: Первомайский пос. | B56: 1500 | AA56: 162
A57: Сысерть | B57: 2100 | C57: 2500
A58: Кирпичный | B58: 1300 | C58: 1500
A59: Кашино | B59: 2000 | C59: 2400
A60: Бисерть | B60: 3500
A61: Кольцово | B61: 1000 | C61: 1200
A62: Среднеуральск | B62: 1500 | C62: 1800
A63: Старопышминск | B63: 1500
A64: Реж | B64: 2100 | C64: 2500
A65: Ревда | B65: 2000 | C65: 2400
A66: Большие Брусяны | B66: 1500
A67: Новоуральск | B67: 2000 | C67: 2500
A68: Шайдурово | B68: 1600 | C68: 1800

Sheet Вышки туры
A1: УПСК Аренда вышек тур | B1: Параметры цен | F1: Высота (полная) | G1: 3.89 | H1: =G1+1 -> 4.89 | I1: город | J1: Екатеринбург | L1: к= | M1: =IF(J1="Екатеринбург",Z14,IF(J1="Челябинск",Z15,IF(J1="Новосибирск",Z16,IF(J1="Пермь",Z17)))) -> 1 | S1: Кол-во метров/ срок аренды | T1: До 4-х дней | U1: До недели | V1: До 2-х недель | W1: До 3х недель | X1: До 30дн | Y1: До 45 дней | Z1: Св 45 дней
F2: Кол-во дней | G2: 30 | Q2: 3.89 | R2: Вышка-тура | S2: до 3,89м | T2: 290 | U2: 230 | V2: 170 | W2: 150 | X2: 130 | Y2: 110 | Z2: 95
B3: ст-ть аренды | C3: =IF(AND(G2<=T8,G1<=Q2),T2, IF(AND(G2<=U8,G1<=Q2),U2, IF(AND(G2<=V8,G1<=Q2),V2, IF(AND(G2<=W8,G1<=Q2),W2, IF(AND(G2<=X8,G1<=Q2),X2, IF(AND(G2<=Y8,G1<=Q2),Y2, IF(AND(G2>Z8,G1<=Q2),Z2, IF(AND(G2<=T8,G1<=Q3),T3, IF(AND(G2<=U8,G1<=Q3),U3, IF(AND(G2<=V8,G1<=Q3),V3, IF(AND(G2<=W8,G1<=Q3),W3, IF(AND(G2<=X8,G1<=Q3),X3, IF(AND(G2<=Y8,G1<=Q3),Y3, IF(AND(G2>Z8,G1<=Q3),Z3, IF(AND(G2<=T8,G1<=Q4),T4, IF(AND(G2<=U8,G1<=Q4),U4, IF(AND(G2<=V8,G1<=Q4),V4, IF(AND(G2<=W8,G1<=Q4),W4, IF(AND(G2<=X8,G1<=Q4),X4, IF(AND(G2<=Y8,G1<=Q4),Y4, IF(AND(G2>Z8,G1<=Q4),Z4, IF(AND(G2<=T8,G1<=Q5),T5, IF(AND(G2<=U8,G1<=Q5),U5, IF(AND(G2<=V8,G1<=Q5),V5, IF(AND(G2<=W8,G1<=Q5),W5, IF(AND(G2<=X8,G1<=Q5),X5, IF(AND(G2<=Y8,G1<=Q5),Y5, IF(AND(G2>Z8,G1<=Q5),Z5, IF(AND(G2<=T8,G1<=Q6),T6, IF(AND(G2<=U8,G1<=Q6),U6, IF(AND(G2<=V8,G1<=Q6),V6, IF(AND(G2<=W8,G1<=Q6),W6, IF(AND(G2<=X8,G1<=Q6),X6, IF(AND(G2<=Y8,G1<=Q6),Y6, IF(AND(G2>Z8,G1<=Q6),Z6, IF(AND(G2<=T8,G1<=Q7),T7, IF(AND(G2<=U8,G1<=Q7),U7, IF(AND(G2<=V8,G1<=Q7),V7, IF(AND(G2<=W8,G1<=Q7),W7, IF(AND(G2<=X8,G1<=Q7),X7, IF(AND(G2<=Y8,G1<=Q7),Y7, IF(AND(G2>Z8,G1<=Q7),Z7,1300 ))))))))))))))))))))))))))))))))))))))))))*M1*L6+C6+K7 -> 156 | D3: в сутки | F3: Кол-во вышек | G3: 1 | H3: =T14 -> 20900 | I3: 0 | K3: =G5*G3 -> 2090 | Q3: 6.29 | R3: Вышка-тура | S3: до 6,29м | T3: 400 | U3: 320 | V3: 230 | W3: 210 | X3: 180 | Y3: 150 | Z3: 130
B4: ст-ть аренды за весь период | D4: =G2*C3 -> 4680 | F4: Доставка | G4: 0 | I4: 10 | J4: % | Q4: 8.69 | R4: Вышка-тура | S4: до 8,69м | T4: 480 | U4: 380 | V4: 270 | W4: 250 | X4: 220 | Y4: 180 | Z4: 160
B5: =C3*G3 -> 156 | C5: =CONCATENATE("за ",G3," шт.") -> за 1 шт. | D5: =D4*G3 -> 4680 | F5: =CONCATENATE("Залог ",I4,"%") -> Залог 10% | G5: =ROUNDUP((H3/100*I4+I3),0) -> 2090 | K5: Скидка | L5: =IF(J7="ПСРВ-21",0.85,1.05) -> 0.85 | Q5: 11.09 | R5: Вышка-тура | S5: до 11,09 | T5: 550 | U5: 440 | V5: 320 | W5: 290 | X5: 260 | Y5: 210 | Z5: 180
B6: корректировка аренды в день + | F6: Итого | G6: =(G2*C3+G5)*G3+G4*2 -> 6770 | K6: ндс | L6: 1.2 | Q6: 13.49 | R6: Вышка-тура | S6: до 13,49 | T6: 630 | U6: 500 | V6: 360 | W6: 330 | X6: 295 | Y6: 240 | Z6: 210
C7: =C6/(C3+C6) -> 0 | F7: Аренда | G7: =D5 -> 4680 | I7: Вышка | J7: ПСРВ-21 | K7: =IF(J7="ПСРВ-22",50,0) -> 0 | Q7: 14.69 | R7: Вышка-тура | S7: от 14,69 | T7: 720 | U7: 560 | V7: 410 | W7: 370 | X7: 330 | Y7: 270 | Z7: 240
A8: окупаемость 4 месяца = | B8: =H3/120 -> 174.16667 | C8: % окупаемости | D8: =IF(G2<=3,3,IF(G2<=7,4,IF(G2<=14,6,IF(G2<=21,8,IF(G2<=30,10,IF(G2<=45,14,IF(G2<=60,17,IF(G2<=90,22,IF(G2<=120,27,IF(G2<=180,32,IF(G2>180,40))))))))))) -> 10 | F8: Залог | G8: =G5*G3 -> 2090 | I8: Площадка | J8: =IF(J7="ПСРВ-21","2м на 1,2м","2м на 2м.") -> 2м на 1,2м | T8: 4 | U8: 7 | V8: 14 | W8: 21 | X8: 30 | Y8: 45 | Z8: 45
C9: Рек цена | D9: =ROUND(((H3/100*D8)/G2)*1.2,0) -> 84 | F9: Доставка | G9: =G4*2 -> 0 | L9: 0.1
A11: Рабочая площадка 2000 х1200 мм
A12: ПСРВ – 21 | B12: Высота полная, м | C12: Высота до настила, м | D12: Достигаемая высота, м | E12: Масса, кг | F12: Цена, руб. | H12: абрис | I12: секций | S12: =G1 -> 3.89
B13: 2.69 | C13: 1.69 | D13: 3.69 | E13: 126.7 | F13: =H13+H13*L9 -> 17050 | G13: =F13+$I$3 -> 17050 | H13: =IF($J$7="ПСРВ-21",X20,Y20) -> 15500 | I13: 1 | V13: Вышка | Y13: Город
B14: 3.89 | C14: 2.89 | D14: 4.89 | E14: 151.5 | F14: =H14+H14*L9 -> 20900 | G14: =F14+$I$3 -> 20900 | H14: =IF($J$7="ПСРВ-21",X21,Y21) -> 19000 | I14: 2 | S14: Расчет залога | T14: =IF(G1=B13,F13,IF(G1=B14,F14,IF(G1=B15,F15,IF(G1=B16,F16,IF(G1=B17,F17,IF(G1=B18,F18,IF(G1=B19,F19,IF(G1=B20,F20,IF(G1=B21,F21,IF(G1=B22,F22,IF(G1=B23,F23,IF(G1=B24,F24,IF(G1=B25,F25,IF(G1=B26,F26,IF(G1=B27,F27,IF(G1=B28,F28,)))))))))))))))) -> 20900 | V14: Столбец1 | Y14: Екатеринбург | Z14: 1
B15: 5.09 | C15: 4.09 | D15: 6.09 | E15: 192.3 | F15: =H15+H15*L9 -> 24200 | G15: =F15+$I$3 -> 24200 | H15: =IF($J$7="ПСРВ-21",X22,Y22) -> 22000 | I15: 3 | V15: ПСРВ-21 | Y15: Челябинск | Z15: 1.15
B16: 6.29 | C16: 5.29 | D16: 7.29 | E16: 218.8 | F16: =H16+H16*L9 -> 28820 | G16: =F16+$I$3 -> 28820 | H16: =IF($J$7="ПСРВ-21",X23,Y23) -> 26200 | I16: 4 | S16: =C3*G3 -> 156 | V16: ПСРВ-22 | Y16: Новосибирск | Z16: 1.4
B17: 7.49 | C17: 6.49 | D17: 8.49 | E17: 243.8 | F17: =H17+H17*L9+5 -> 32125 | G17: =F17+$I$3 -> 32125 | H17: =IF($J$7="ПСРВ-21",X24,Y24) -> 29200 | I17: 5 | Y17: Пермь | Z17: 1.15
B18: 8.69 | C18: 7.69 | D18: 9.69 | E18: 270.3 | F18: =H18+H18*0.1+5 -> 35315 | G18: =F18+$I$3 -> 35315 | H18: =IF($J$7="ПСРВ-21",X25,Y25) -> 32100 | I18: 6
B19: 9.89 | C19: 8.89 | D19: 10.89 | E19: 295.1 | F19: =H19+H19*L9+5 -> 38725 | G19: =F19+$I$3 -> 38725 | H19: =IF($J$7="ПСРВ-21",X26,Y26) -> 35200 | I19: 7
B20: 11.09 | C20: 10.09 | D20: 12.09 | E20: 319.9 | F20: =H20+H20*L9+5 -> 41915 | G20: =F20+$I$3 -> 41915 | H20: =IF($J$7="ПСРВ-21",X27,Y27) -> 38100 | I20: 8 | X20: 15500 | Y20: 21400 | AC20: База в сборе (2420мм) | AD20: База в сборе (2420мм)
B21: 12.29 | C21: 11.29 | D21: 13.29 | E21: 344.7 | F21: =H21+H21*L9+5 -> 45215 | G21: =F21+$I$3 -> 45215 | H21: =IF($J$7="ПСРВ-21",X28,Y28) -> 41100 | I21: 9 | X21: 19000 | Y21: 25140 | AC21: Лестница секции (1160мм х 1214мм) | AD21: Лестница секции (1160мм х 1930мм)
B22: 13.49 | C22: 12.49 | D22: 14.49 | E22: 369.5 | F22: =H22+H22*L9 -> 48510 | G22: =F22+$I$3 -> 48510 | H22: =IF($J$7="ПСРВ-21",X29,Y29) -> 44100 | I22: 10 | X22: 22000 | Y22: 28900 | AC22: Диагональ объемная (2305мм) | AD22: Диагональ объемная (2776мм)
B23: 14.69 | C23: 13.69 | D23: 15.69 | E23: 394.3 | F23: =H23+H23*L9 -> 51700 | G23: =F23+$I$3 -> 51700 | H23: =IF($J$7="ПСРВ-21",X30,Y30) -> 47000 | I23: 11 | X23: 26200 | Y23: 34900 | AC23: Гантель (1975мм) | AD23: Гантель (1975мм)
B24: 15.89 | C24: 14.89 | D24: 16.89 | E24: 419.1 | F24: =H24+H24*L9 -> 55110 | G24: =F24+$I$3 -> 55110 | H24: =IF($J$7="ПСРВ-21",X31,Y31) -> 50100 | I24: 12 | X24: 29200 | Y24: 38500 | AC24: Стяжка лестницы (840мм) | AD24: Стяжка лестницы (840мм)
B25: 17.09 | C25: 16.09 | D25: 18.09 | E25: 443.9 | F25: =H25+H25*L9 -> 58300 | G25: =F25+$I$3 -> 58300 | H25: =IF($J$7="ПСРВ-21",X32,Y32) -> 53000 | I25: 13 | X25: 32100 | Y25: 42500 | AC25: Стабилизатор в сборе (2400мм) | AD25: Стабилизатор в сборе (2400мм)
B26: 18.29 | C26: 17.29 | D26: 19.29 | E26: 468.7 | F26: =H26+H26*L9 -> 61600 | G26: =F26+$I$3 -> 61600 | H26: =IF($J$7="ПСРВ-21",X33,Y33) -> 56000 | I26: 14 | X26: 35200 | Y26: 46300 | AC26: Лестница ограждения (1160мм х 1214мм) | AD26: Лестница ограждения (1160мм х 1930мм)
B27: 19.49 | C27: 18.49 | D27: 20.49 | E27: 493.5 | F27: =H27+H27*L9 -> 64790 | G27: =F27+$I$3 -> 64790 | H27: =IF($J$7="ПСРВ-21",X34,Y34) -> 58900 | I27: 15 | X27: 38100 | Y27: 50000 | AC27: Гантель ограждения (1965мм) | AD27: Гантель ограждения (1965мм)
B28: 20.69 | C28: 19.69 | D28: 21.69 | E28: 518.3 | F28: =H28+H28*L9+5 -> 68205 | G28: =F28+$I$3 -> 68205 | H28: =IF($J$7="ПСРВ-21",X35,Y35) -> 62000 | I28: 16 | X28: 41100 | Y28: 53700 | AC28: Перекладина ограждения (1990мм) | AD28: Перекладина ограждения (1990мм)
H29: =IF($J$7="ПСРВ-21",X36,Y36) -> 0 | X29: 44100 | Y29: 57700 | AC29: Настил без люка (1995мм х 525мм) | AD29: Настил без люка (1995мм х 525мм)
X30: 47000 | Y30: 61000 | AC30: Настил с люком (1995мм х 525мм) | AD30: Настил с люком (1995мм х 525мм)
X31: 50100 | Y31: 65100
X32: 53000 | Y32: 69200
A33: Комплектующие | D33: =CONCATENATE("Количество на ",G3," вышки") -> Количество на 1 вышки | G33: Цена за элемент | J33: коэф | X33: 56000 | Y33: 72800
H34: 1.1 | J34: =IF(G1=2.69,1,IF(G1=3.89,2,IF(G1=5.09,3,IF(G1=6.29,4,IF(G1=7.49,5,IF(G1=8.69,6,IF(G1=9.89,7,IF(G1=11.09,8,IF(G1=12.29,9,IF(G1=13.49,10,IF(G1=14.69,11,IF(G1=15.89,12,IF(G1=17.09,13,IF(G1=18.29,14,IF(G1=19.49,15,IF(G1=20.69,16)))))))))))))))) -> 2 | X34: 58900 | Y34: 76500
G35: абрис | H35: с ндс наши | I35: итого | X35: 62000 | Y35: 80600
A36: =IF($J$7="ПСРВ-21",AC20,AD20) -> База в сборе (2420мм) | B36: 2 | D36: =B36*G3 -> 2 | G36: 3774 | H36: =ROUNDUP(G36*$H$34,-1) -> 4160 | I36: =D36*H36 -> 8320 | Y36: 83900
A37: =IF($J$7="ПСРВ-21",AC21,AD21) -> Лестница секции (1160мм х 1214мм) | B37: =2*J34+B42 -> 6 | D37: =B37*G3 -> 6 | G37: 1180 | H37: =ROUNDUP(G37*$H$34,-1) -> 1300 | I37: =D37*H37 -> 7800
A38: =IF($J$7="ПСРВ-21",AC22,AD22) -> Диагональ объемная (2305мм) | B38: =ROUNDUP(J34/3,0) -> 1 | D38: =B38*G3 -> 1 | G38: 571 | H38: =ROUNDUP(G38*$H$34,-1) -> 630 | I38: =D38*H38 -> 630
A39: =IF($J$7="ПСРВ-21",AC23,AD23) -> Гантель (1975мм) | B39: =2*J34 -> 4 | D39: =B39*G3 -> 4 | G39: 781 | H39: =ROUNDUP(G39*$H$34,-1) -> 860 | I39: =D39*H39 -> 3440
A40: =IF($J$7="ПСРВ-21",AC24,AD24) -> Стяжка лестницы (840мм) | B40: =8+8*J34 -> 24 | D40: =B40*G3 -> 24 | G40: 122 | H40: =ROUNDUP(G40*$H$34,-1) -> 140 | I40: =D40*H40 -> 3360
A41: =IF($J$7="ПСРВ-21",AC25,AD25) -> Стабилизатор в сборе (2400мм) | B41: =IF(G1>=6.29,4,0) -> 0 | D41: =B41*G3 -> 0 | G41: 779 | H41: =ROUNDUP(G41*$H$34,-1) -> 860 | I41: =D41*H41 -> 0
A42: =IF($J$7="ПСРВ-21",AC26,AD26) -> Лестница ограждения (1160мм х 1214мм) | B42: 2 | D42: =B42*G3 -> 2 | G42: 1180 | H42: =ROUNDUP(G42*$H$34,-1) -> 1300 | I42: =D42*H42 -> 2600
A43: =IF($J$7="ПСРВ-21",AC27,AD27) -> Гантель ограждения (1965мм) | B43: 2 | D43: =B43*G3 -> 2 | G43: 694 | H43: =ROUNDUP(G43*$H$34,-1) -> 770 | I43: =D43*H43 -> 1540
A44: =IF($J$7="ПСРВ-21",AC28,AD28) -> Перекладина ограждения (1990мм) | B44: 2 | D44: =B44*G3 -> 2 | H44: =ROUNDUP(G44*$H$34,-1) -> 0 | I44: =D44*H44 -> 0
A45: =IF($J$7="ПСРВ-21",AC29,AD29) -> Настил без люка (1995мм х 525мм) | B45: =IF(J7="ПСРВ-21",1,2) -> 1 | D45: =B45*G3 -> 1 | G45: 3850 | H45: =ROUNDUP(G45*$H$34,-1) -> 4240 | I45: =D45*H45 -> 4240
A46: =IF($J$7="ПСРВ-21",AC30,AD30) -> Настил с люком (1995мм х 525мм) | B46: 1 | D46: =B46*G3 -> 1 | G46: 4004 | H46: =ROUNDUP(G46*$H$34,-1) -> 4410 | I46: =D46*H46 -> 4410
G48: ст-ть вышки | I48: =SUM(I36:I46) -> 36340
G49: наша стоимость | H49: =G5 -> 2090

Sheet Договор аренды лесов Физ
A1: ='Расчет лесов'!C3 -> 210
A2: =CONCATENATE("ДОГОВОР №",AW2) -> ДОГОВОР №27/06-А(16) | AV2: № договора | AW2: 27/06-А(16) | BK2: Вспомогательные значения
A3: на аренду строительных лесов | AV3: Дата | AW3: "27" июня 2016 г. | BK3: Срок аренды | BL3: ='Расчет лесов'!C4 -> 30
AV4: ФИО | AW4: __________________________________
B5: г. Екатеринбург | AK5: =AW3 -> "27" июня 2016 г. | AV5: Город | AW5: ______________________________________ | BK5: длина | BL5: ='Расчет лесов'!J3+'Расчет лесов'!J5+'Расчет лесов'!J7+'Расчет лесов'!J9 -> 3
AV6: Улица | BK6: высота | BL6: ='Расчет лесов'!K3+'Расчет лесов'!K5+'Расчет лесов'!K7+'Расчет лесов'!K9 -> 8
C7: Гражданин Выборных Андрей Павлович, проживающий по адресу: г. Екатеринбург, ул. | AV7: Паспорт | AW7: _____________
A8: Боровая, д. 24, кв. 163, паспорт серия 6505 N 554016 выдан "29" июля 2005г. ОВД г Краснотурьинска Свердловской области, именуемый в дальнейшем "Арендодатель", с одной стороны, и | AV8: выдан когда | AW8: ______________
AV9: выдан кем | AW9: _________________________________________________
C11: Гражданин(ка) | J11: _______________________________________________________________ | AV11: сумма в сутки | AW11: =SUBSTITUTE(PROPER(INDEX(n_4,MID(TEXT(A1,n0),1,1)+1)&INDEX(n0x,MID(TEXT(A1,n0),2,1)+1,MID(TEXT(A1,n0),3,1)+1)&IF(-MID(TEXT(A1,n0),1,3),"миллиард"&VLOOKUP(MID(TEXT(A1,n0),3,1)*AND(MID(TEXT(A1,n0),2,1)-1),мил,2),"")&INDEX(n_4,MID(TEXT(A1,n0),4,1)+1)&INDEX(n0x,MID(TEXT(A1,n0),5,1)+1,MID(TEXT(A1,n0),6,1)+1)&IF(-MID(TEXT(A1,n0),4,3),"миллион"&VLOOKUP(MID(TEXT(A1,n0),6,1)*AND(MID(TEXT(A1,n0),5,1)-1),мил,2),"")&INDEX(n_4,MID(TEXT(A1,n0),7,1)+1)&INDEX(n1x,MID(TEXT(A1,n0),8,1)+1,MID(TEXT(A1,n0),9,1)+1)&IF(-MID(TEXT(A1,n0),7,3),VLOOKUP(MID(TEXT(A1,n0),9,1)*AND(MID(TEXT(A1,n0),8,1)-1),тыс,2),"")&INDEX(n_4,MID(TEXT(A1,n0),10,1)+1)&INDEX(n0x,MID(TEXT(A1,n0),11,1)+1,MID(TEXT(A1,n0),12,1)+1)),"z"," ")&IF(TRUNC(TEXT(A1,n0)),"","Ноль ")&"рубл"&VLOOKUP(MOD(MAX(MOD(MID(TEXT(A1,n0),11,2)-11,100),9),10),{0,"ь ";1,"я ";4,"ей "},2)&RIGHT(TEXT(A1,n0),2)&" копе"&VLOOKUP(MOD(MAX(MOD(RIGHT(TEXT(A1,n0),2)-11,100),9),10),{0,"йка";1,"йки";4,"ек"},2) -> Двести десять рублей 00 копеек
A12: проживающий по адресу:_________________________________________________________ | AV12: конт телефон
A13: паспорт серия/номер__________________ | V13: выдан _____________________________________ | AV13: Адрес доставки
A14: именуемый в дальнейшем "Арендатор", с другой стороны, заключили настоящий Договор
A15: о нижеследующем:
A17: 1. ПРЕДМЕТ ДОГОВОРА
A19: =CONCATENATE("1.1. Арендодатель обязуется предоставить во временное владение и пользование Арендатору строительные леса (длина ",BL5,"м, высота ",BL6,"м) согласно Акту приема-передачи (приложение №1) настоящего договора, именуемые в дальнейшем «оборудование».") -> 1.1. Арендодатель обязуется предоставить во временное владение и пользование Арендатору строительные леса (длина 3м, высота 8м) согласно Акту приема-передачи (приложение №1) настоящего договора, именуемые в дальнейшем «оборудование».
A22: 1.2. Оборудование будет использоваться по прямому назначению.
A23: 1.3. Оборудование передается в состоянии, пригодном для его использования в соответствии с пунктом 1.2. настоящего договора.
A25: 2. ОБЯЗАННОСТИ СТОРОН
A27: 2.1. Арендодатель обязан: 2.1.1. Передать Арендатору арендованное имущество в состоянии, отвечающем условиям Договора, в течение трех рабочих дней с момента подписания договора и получения аванса. 2.1.2. Оказывать консультативную и иную помощь в целях наиболее эффективного использования арендованного имущества. 2.1.3. Обязан осуществить все иные действия, необходимые для исполнения данного договора, предусмотренные законодательством, настоящим договором и дополнениями к нему. 2.2. Арендатор обязан: 2.2.1. Использовать имущество в соответствии с условиями Договора и назначением имущества. 2.2.2. Поддерживать имущество в исправном состоянии, производить за свой счет текущий ремонт. 2.2.3. Нести иные расходы по содержанию имущества. 2.2.4. В установленные Договором сроки вносить арендную плату. 2.2.5. Возвратить имущество Арендодателю после прекращения Договора по Акту приема-передачи в том состоянии, в каком оно было передано, с учетом нормального износа. 2.2.6. Производить ежедневную проверку исправности имущества. 2.2.7. Провести инструктаж по технике безопасности при работе с имуществом. 2.2.8. Письменно уведомить Арендодателя при смене местонахождения оборудования. 2.2.9. Исполнитель обязан осуществить все иные действия, необходимые для исполнения данного договора, предусмотренные законодательством, настоящим договором и дополнениями к нему.
A47: 3. РАСЧЕТЫ
A49: 3.1. Арендная плата по настоящему договору составляет:
C50: =CONCATENATE('Расчет лесов'!C3," (",AW11,") за каждые сутки аренды.") -> 210 (Двести десять рублей 00 копеек) за каждые сутки аренды.
A51: 3.2. Оплата производится по безналичному расчету, либо другими способами удовлетворяющими обе стороны путем выдачи Арендодателю раз в две недели суммы (за 14 дней), определенной пунктом 3.1. договора. 3.3 Залог Арендатору возвращается в полном объеме после возврата оборудования Арендодателю в исправном состоянии.
A57: 4. ОТВЕТСТВЕННОСТЬ СТОРОН
A59: 4.1. Стороны несут имущественную ответственность за неисполнение или ненадлежащее исполнение условий Договора. 4.2. За каждый день просрочки выплаты арендной платы начисляется пеня в размере 5% от суммы задолженности. 4.3. В случае просрочки внесения арендной платы свыше одного месяца Арендодатель имеет право расторгнуть Договор и потребовать возмещения убытков, причиненных этой просрочкой. 4.4. За просрочку предоставления арендуемого имущества в установленный договором срок Арендодатель уплачивает Арендатору пени в размере 50 % за каждый день просрочки от суммы арендной платы за день. 4.5. За просрочку возврата арендованного имущества в установленный договором срок Арендатор уплачивает Арендодателю пени в размере 50% за каждый день просрочки от суммы арендной платы за день. 4.6. При возврате неисправного арендованного имущества, поврежденного по вине Арендатора, что подтверждается двусторонним актом, последний уплачивает Арендодателю расходы по ремонту их и штраф в размере 100% стоимости поврежденного арендованного имущества. 4.7. Уплата неустойки не освобождает стороны от исполнения обязательств или устранения нарушений. 4.8. Арендодатель не несет ответственность за несчастные случаи допущенные вследствие нарушении техники безопасности.
A79: 5. ФОРС-МАЖОР
A81: 5.1. Ни одна из сторон не несет ответственности перед другой стороной за невыполнение обязательств, обусловленное обстоятельствами, возникшими помимо воли и желания сторон и которые нельзя предвидеть или избежать, включая объявленную или фактическую войну, гражданские волнения, эпидемии, блокаду, эмбарго, землетрясения, наводнения, пожары и другие стихийные бедствия. 5.2. Сторона, которая не может исполнить своего обязательства, должна известить другую сторону о препятствии и его влиянии на исполнение обязательств по Договору в разумный срок с момента возникновения этих обстоятельств. 5.3. Дальнейшая судьба настоящего договора в таких случаях должна быть определена соглашением сторон. При не достижении согласия стороны вправе обратиться в суд для решения этого вопроса.
A93: 6. ПОРЯДОК РАЗРЕШЕНИЯ СПОРОВ
A95: 6.1. Все споры или разногласия, возникающие между сторонами по настоящему Договору или в связи с ним, разрешаются путем переговоров между сторонами. 6.2. В случае невозможности разрешения разногласий путем переговоров они подлежат рассмотрению в суде общей юрисдикции в установленном законодательством порядке.
A100: 7. КОНФИДЕНЦИАЛЬНОСТЬ
A102: 7.1. Условия настоящего договора и соглашений (протоколов и т.п.) к нему конфиденциальны и не подлежат разглашению. 7.2. Стороны принимают все необходимые меры для того, чтобы их сотрудники, агенты, правопреемники без предварительного согласия другой стороны не информировали третьих лиц о деталях данного договора и приложений к нему.
A108: 8. ПОРЯДОК ИЗМЕНЕНИЯ И ДОПОЛНЕНИЯ ДОГОВОРА
A110: 8.1. Любые изменения и дополнения к настоящему Договору имеют силу только в том случае, если они оформлены в письменном виде и подписаны обеими сторонами. 8.2. Досрочное расторжение Договора может иметь место по соглашению сторон либо по основаниям, предусмотренным действующим на территории Российской Федерации гражданским законодательством, с возмещением понесенных убытков.
A116: 9. ЗАКЛЮЧИТЕЛЬНЫЕ ПОЛОЖЕНИЯ
... A124: 10. ЮРИДИЧЕСКИЕ АДРЕСА И ПЛАТЕЖНЫЕ РЕКВИЗИТЫ СТОРОН
B126: Арендодатель:
B127: Выборных Андрей Павлович, паспорт серия 6505 N 554016 выдан "29" июля 2005г. ОВД г Краснотурьинска Свердловской области, конт. тел. 8(343)206-88-82
B129: №карты Сбербанка 5469 1600 1322 4162
B130: Арендатор:
B131: ______________________________________________________________________________
B132: ______________________________________________________________________________
B133: ______________________________________________________________________________
AF134: конт. тел.________________
B136: ПОДПИСИ СТОРОН:
B138: Арендодатель | AF138: Арендатор
L140: Выборных А.П.
B142: М.П. | AF142: М.П.
Q151: =CONCATENATE("Приложение к договору №1") -> Приложение к договору №1 | AK151: =CONCATENATE("от ",AW3) -> от "27" июня 2016 г.
V153: Акт
M154: приема-передачи оборудования в аренду
A155: г. Екатеринбург | AK155: =AW3 -> "27" июня 2016 г.
C157: =CONCATENATE("Настоящие стороны согласно договору № ",AW2," от ",AW3," на аренду, ") -> Настоящие стороны согласно договору № 27/06-А(16) от "27" июня 2016 г. на аренду,
A158: заключенному между Арендодателем и Арендатором, настоящим актом приема-передачи подтверждают факт передачи Арендодателем оборудования (строительных лесов), в исправном состоянии(согласно технического паспорта) и технически пригодном для выполнения строительных работ, Арендатору в следующей комплектности:
A160: № п/п | E160: Наименование | Y160: Количество, шт. | AF160: Стоимость руб. за ед. | AM160: Сумма, руб.
A161: 1 | E161: Рама проходная ЛСПР-200 | Y161: ='Расчет лесов'!B8 -> 4 | AF161: ='Расчет лесов'!C8 -> 1400 | AM161: =Y161*AF161 -> 5600
A162: 2 | E162: Рама с лестницей ЛСПР-200 | Y162: ='Расчет лесов'!B9 -> 4 | AF162: ='Расчет лесов'!C9 -> 1670 | AM162: =Y162*AF162 -> 6680
A163: 3 | E163: Диагональная связь (3,3 м) ЛСПР-200 | Y163: ='Расчет лесов'!B10 -> 4 | AF163: ='Расчет лесов'!C10 -> 630 | AM163: =Y163*AF163 -> 2520
A164: 4 | E164: Горизонтальная связь | Y164: ='Расчет лесов'!B11 -> 4 | AF164: ='Расчет лесов'!C11 -> 320 | AM164: =Y164*AF164 -> 1280
A165: 5 | E165: Мостки (настил) деревянные | Y165: ='Расчет лесов'!B12 -> 12 | AF165: ='Расчет лесов'!C12 -> 450 | AM165: =Y165*AF165 -> 5400
A166: 6 | E166: Рама для настила | Y166: ='Расчет лесов'!B13 -> 8 | AF166: ='Расчет лесов'!C13 -> 1120 | AM166: =Y166*AF166 -> 8960
E167: Общая рыночная стоимость арендуемого оборудования | AM167: =SUM(AM161:AS166) -> 30440
E168: =CONCATENATE("Стоимость залога за оборудование составляет ",'Расчет лесов'!O7,"% от общей рыночной стоимости") -> Стоимость залога за оборудование составляет 10% от общей рыночной стоимости | AM168: ='Расчет лесов'!D17 -> 3100
E169: =CONCATENATE("Стоимость доставки оборудования до объекта Арендатора (",AW13,")") -> Стоимость доставки оборудования до объекта Арендатора () | AM169: ='Расчет лесов'!O2 -> 0
E170: =CONCATENATE("Стоимость вывоза оборудования до объекта Арендатора (",AW13,")") -> Стоимость вывоза оборудования до объекта Арендатора () | AM170: ='Расчет лесов'!O2 -> 0
E171: =CONCATENATE("Стоимость аренды оборудования за ",BL3," суток согласно п. 3.1 договора") -> Стоимость аренды оборудования за 30 суток согласно п. 3.1 договора | AM171: ='Расчет лесов'!D22 -> 6300
E172: ИТОГО к оплате | AM172: =AM168+AM169+AM170+AM171 -> 9400
A174: Примечание: * стоимость транспортных услуг принимаются из учета минимального тарифа транспортного средства.
A175: Простой транспортного средства оплачивается из тарифа 250 рублей в час.
A177: Подписи сторон
A179: Арендодатель______________________Выборных А.П.
A181: Арендатор_________________________
A183: Оборудование (строительные леса) возвращены в полном объеме, претензий не имею
A184: _______________________________________________________.

Sheet Договор аренды тур Физ
A1: ='Вышки туры'!B5 -> 156
A2: =CONCATENATE("ДОГОВОР №",AW2) -> ДОГОВОР №14/06-А(16) | AV2: № договора | AW2: 14/06-А(16) | BK2: Вспомогательные значения
A3: на аренду вышки туры | AV3: Дата | AW3: "14" июня 2016 г. | BK3: Срок аренды | BL3: ='Вышки туры'!G2 -> 30
AV4: ФИО | AW4: ____________________________
B5: г. Екатеринбург | AK5: =AW3 -> "14" июня 2016 г. | AV5: Город | AW5: ______________________
AV6: Улица | AW6: ____________________________
C7: Гражданин Выборных Андрей Павлович, проживающий по адресу: г. Екатеринбург, ул. | AV7: Паспорт | AW7: ______________
A8: Боровая, д. 24, кв. 163, паспорт серия 6505 N 554016 выдан "29" июля 2005г. ОВД г Краснотурьинска Свердловской области, именуемый в дальнейшем "Арендодатель", с одной стороны, и | AV8: выдан когда | AW8: ______________________________
AV9: выдан кем | AW9: _________________________________________________________
C11: Гражданин(ка) | J11: _______________________________________________________________ | AV11: сумма в сутки | AW11: =SUBSTITUTE(PROPER(INDEX(n_4,MID(TEXT(A1,n0),1,1)+1)&INDEX(n0x,MID(TEXT(A1,n0),2,1)+1,MID(TEXT(A1,n0),3,1)+1)&IF(-MID(TEXT(A1,n0),1,3),"миллиард"&VLOOKUP(MID(TEXT(A1,n0),3,1)*AND(MID(TEXT(A1,n0),2,1)-1),мил,2),"")&INDEX(n_4,MID(TEXT(A1,n0),4,1)+1)&INDEX(n0x,MID(TEXT(A1,n0),5,1)+1,MID(TEXT(A1,n0),6,1)+1)&IF(-MID(TEXT(A1,n0),4,3),"миллион"&VLOOKUP(MID(TEXT(A1,n0),6,1)*AND(MID(TEXT(A1,n0),5,1)-1),мил,2),"")&INDEX(n_4,MID(TEXT(A1,n0),7,1)+1)&INDEX(n1x,MID(TEXT(A1,n0),8,1)+1,MID(TEXT(A1,n0),9,1)+1)&IF(-MID(TEXT(A1,n0),7,3),VLOOKUP(MID(TEXT(A1,n0),9,1)*AND(MID(TEXT(A1,n0),8,1)-1),тыс,2),"")&INDEX(n_4,MID(TEXT(A1,n0),10,1)+1)&INDEX(n0x,MID(TEXT(A1,n0),11,1)+1,MID(TEXT(A1,n0),12,1)+1)),"z"," ")&IF(TRUNC(TEXT(A1,n0)),"","Ноль ")&"рубл"&VLOOKUP(MOD(MAX(MOD(MID(TEXT(A1,n0),11,2)-11,100),9),10),{0,"ь ";1,"я ";4,"ей "},2)&RIGHT(TEXT(A1,n0),2)&" копе"&VLOOKUP(MOD(MAX(MOD(RIGHT(TEXT(A1,n0),2)-11,100),9),10),{0,"йка";1,"йки";4,"ек"},2) -> Сто пятьдесят шесть рублей 00 копеек
A12: проживающий по адресу:_________________________________________________________ | AV12: конт телефон | AW12: ___________________________
A13: паспорт серия/номер__________________ | V13: выдан _____________________________________ | AV13: Адрес доставки | AW13: ___________________
A14: именуемый в дальнейшем "Арендатор", с другой стороны, заключили настоящий Договор
A15: о нижеследующем:
A17: 1. ПРЕДМЕТ ДОГОВОРА
A19: 1.1. Арендодатель обязуется предоставить во временное владение и пользование Арендатору строительные леса согласно Акту приема-передачи (приложение №1") настоящего договора), именуемые в дальнейшем «оборудование».
A22: 1.2. Оборудование будет использоваться по прямому назначению.
A23: 1.3. Оборудование передается в состоянии, пригодном для его использования в соответствии с пунктом 1.2. настоящего договора.
A25: 2. ОБЯЗАННОСТИ СТОРОН
A27: 2.1. Арендодатель обязан: 2.1.1. Передать Арендатору арендованное имущество(вышка тура ПСРВ-21 высотой 8,69м - 1 штука) в состоянии, отвечающем условиям Договора, в течение двух календарных дней с момента подписания договора и получения аванса. 2.1.2. Оказывать консультативную и иную помощь в целях наиболее эффективного использования арендованного имущества. 2.1.3. Обязан осуществить все иные действия, необходимые для исполнения данного договора, предусмотренные законодательством, настоящим договором и дополнениями к нему. 2.2. Арендатор обязан: 2.2.1. Использовать имущество в соответствии с условиями Договора и назначением имущества. 2.2.2. Поддерживать имущество в исправном состоянии, производить за свой счет текущий ремонт. 2.2.3. Нести иные расходы по содержанию имущества. 2.2.4. В установленные Договором сроки вносить арендную плату. 2.2.5. Возвратить имущество Арендодателю после прекращения Договора по Акту приема-передачи в том состоянии, в каком оно было передано, с учетом нормального износа. 2.2.6. Производить ежедневную проверку исправности имущества. 2.2.7. Провести инструктаж по технике безопасности при работе с имуществом. 2.2.8. Письменно уведомить Арендодателя при смене местонахождения оборудования. 2.2.9. Исполнитель обязан осуществить все иные действия, необходимые для исполнения данного договора, предусмотренные законодательством, настоящим договором и дополнениями к нему.
A47: 3. РАСЧЕТЫ
A49: 3.1. Арендная плата по настоящему договору составляет:
C50: =CONCATENATE('Вышки туры'!B5," (",AW11,") за каждые сутки аренды.") -> 156 (Сто пятьдесят шесть рублей 00 копеек) за каждые сутки аренды.
A51: 3.2. Оплата производится по безналичному расчету, либо другими способами удовлетворяющими обе стороны путем выдачи Арендодателю раз в две недели суммы (за 14 дней), определенной пунктом 3.1. договора на основании расписки между сторонами. 3.3 Залог Арендатору возвращается в полном объеме после возврата оборудования Арендодателю в исправном состоянии.
A57: 4. ОТВЕТСТВЕННОСТЬ СТОРОН
A59: 4.1. Стороны несут имущественную ответственность за неисполнение или ненадлежащее исполнение условий Договора. 4.2. За каждый день просрочки выплаты арендной платы начисляется пеня в размере 5% от суммы задолженности. 4.3. В случае просрочки внесения арендной платы свыше одного месяца Арендодатель имеет право расторгнуть Договор и потребовать возмещения убытков, причиненных этой просрочкой. 4.4. За просрочку предоставления арендуемого имущества в установленный договором срок Арендодатель уплачивает Арендатору пени в размере 50 % за каждый день просрочки от суммы арендной платы за день. 4.5. За просрочку возврата арендованного имущества в установленный договором срок Арендатор уплачивает Арендодателю пени в размере 50% за каждый день просрочки от суммы арендной платы за день. 4.6. При возврате неисправного арендованного имущества, поврежденного по вине Арендатора, что подтверждается двусторонним актом, последний уплачивает Арендодателю расходы по ремонту их и штраф в размере 100% стоимости поврежденного арендованного имущества. 4.7. Уплата неустойки не освобождает стороны от исполнения обязательств или устранения нарушений. 4.8. Арендодатель не несет ответственность за несчастные случаи допущенные вследствие нарушении техники безопасности.
A79: 5. ФОРС-МАЖОР
A81: 5.1. Ни одна из сторон не несет ответственности перед другой стороной за невыполнение обязательств, обусловленное обстоятельствами, возникшими помимо воли и желания сторон и которые нельзя предвидеть или избежать, включая объявленную или фактическую войну, гражданские волнения, эпидемии, блокаду, эмбарго, землетрясения, наводнения, пожары и другие стихийные бедствия. 5.2. Сторона, которая не может исполнить своего обязательства, должна известить другую сторону о препятствии и его влиянии на исполнение обязательств по Договору в разумный срок с момента возникновения этих обстоятельств. 5.3. Дальнейшая судьба настоящего договора в таких случаях должна быть определена соглашением сторон. При не достижении согласия стороны вправе обратиться в суд для решения этого вопроса.
A93: 6. ПОРЯДОК РАЗРЕШЕНИЯ СПОРОВ
A95: 6.1. Все споры или разногласия, возникающие между сторонами по настоящему Договору или в связи с ним, разрешаются путем переговоров между сторонами. 6.2. В случае невозможности разрешения разногласий путем переговоров они подлежат рассмотрению в суде общей юрисдикции в установленном законодательством порядке.
A100: 7. КОНФИДЕНЦИАЛЬНОСТЬ
A102: 7.1. Условия настоящего договора и соглашений (протоколов и т.п.) к нему конфиденциальны и не подлежат разглашению. 7.2. Стороны принимают все необходимые меры для того, чтобы их сотрудники, агенты, правопреемники без предварительного согласия другой стороны не информировали третьих лиц о деталях данного договора и приложений к нему.
A108: 8. ПОРЯДОК ИЗМЕНЕНИЯ И ДОПОЛНЕНИЯ ДОГОВОРА
A110: 8.1. Любые изменения и дополнения к настоящему Договору имеют силу только в том случае, если они оформлены в письменном виде и подписаны обеими сторонами. 8.2. Досрочное расторжение Договора может иметь место по соглашению сторон либо по основаниям, предусмотренным действующим на территории Российской Федерации гражданским законодательством, с возмещением понесенных убытков.
A116: 9. ЗАКЛЮЧИТЕЛЬНЫЕ ПОЛОЖЕНИЯ
... A124: 10. ЮРИДИЧЕСКИЕ АДРЕСА И ПЛАТЕЖНЫЕ РЕКВИЗИТЫ СТОРОН
B126: Арендодатель:
B127: Выборных Андрей Павлович, паспорт серия 6505 N 554016 выдан "29" июля 2005г. ОВД г Краснотурьинска Свердловской области, конт. тел. 8(343)206-88-82
B129: №карты Сбербанка 5469 1600 1322 4162
B130: Арендатор:
B131: ______________________________________________________________________________
B132: ______________________________________________________________________________
B133: ______________________________________________________________________________
AF134: =CONCATENATE("конт. тел. ",AW12) -> конт. тел. ___________________________
B135: ПОДПИСИ СТОРОН:
B137: Арендодатель | AF137: Арендатор
B141: М.П. | AF141: М.П.
P157: =CONCATENATE("Приложение №1 к договору №",AW2) -> Приложение №1 к договору №14/06-А(16) | AK157: =CONCATENATE("от ",AW3) -> от "14" июня 2016 г.
V159: Акт
M160: приема-передачи оборудования в аренду
A161: г. Екатеринбург | AK161: =AW3 -> "14" июня 2016 г.
C163: =CONCATENATE("Настоящие стороны согласно договору № ",AW2," от ",AW3," на аренду, ") -> Настоящие стороны согласно договору № 14/06-А(16) от "14" июня 2016 г. на аренду,
A164: заключенному между Арендодателем и Арендатором, настоящим актом приема-передачи подтверждают факт передачи Арендодателем оборудования (строительных лесов), в исправном состоянии(согласно технического паспорта) и технически пригодном для выполнения строительных работ, Арендатору в следующей комплектности:
A166: № п/п | E166: Наименование | Y166: Количество, шт. | AF166: Стоимость руб. за ед. | AM166: Сумма, руб.
A167: 1 | E167: =CONCATENATE("Строительная вышка тура ПСРВ-21 (",'Вышки туры'!S12," м)") -> Строительная вышка тура ПСРВ-21 (3,89 м) | Y167: ='Вышки туры'!G3 -> 1 | AF167: ='Вышки туры'!H3 -> 20900 | AM167: =Y167*AF167 -> 20900
E168: Общая рыночная стоимость арендуемого оборудования | AM168: =SUM(AM167:AS167) -> 20900
E169: Стоимость залога за оборудование составляет 50 % от общей рыночной стоимости | AM169: ='Вышки туры'!K3 -> 2090
E170: =CONCATENATE("Стоимость доставки оборудования до объекта Арендатора (",AW13,")") -> Стоимость доставки оборудования до объекта Арендатора (___________________) | AM170: ='Вышки туры'!G4 -> 0
E171: =CONCATENATE("Стоимость вывоза оборудования до объекта Арендатора (",AW13,")") -> Стоимость вывоза оборудования до объекта Арендатора (___________________) | AM171: ='Вышки туры'!G4 -> 0
E172: =CONCATENATE("Стоимость аренды оборудования за ",BL3," суток согласно п. 3.1 договора") -> Стоимость аренды оборудования за 30 суток согласно п. 3.1 договора | AM172: ='Вышки туры'!D5 -> 4680
E173: ИТОГО к оплате | AM173: =AM169+AM170+AM171+AM172 -> 6770
A175: Примечание: * стоимость транспортных услуг принимаются из учета минимального тарифа транспортного средства.
A176: Простой транспортного средства оплачивается из тарифа 250 рублей в час.
A178: Подписи сторон
A180: Арендодатель______________________Выборных А.П.
A182: Арендатор_________________________
A184: Оборудование (строительные леса) возвращены в полном объеме, претензий не имею
A185: _______________________________________________________.
P187: Приложение №2 к договору №______________ | AI187: от _____________
U189: Акт
L190: приема-передачи оборудования в аренду
P192: Общее количество элементов
A194: №п.п | D194: Наименование элемента | AH194: Количество
A195: 1 | D195: ='Вышки туры'!A36 -> База в сборе (2420мм) | AH195: ='Вышки туры'!D36 -> 2
A196: 2 | D196: ='Вышки туры'!A37 -> Лестница секции (1160мм х 1214мм) | AH196: ='Вышки туры'!D37 -> 6
A197: 3 | D197: ='Вышки туры'!A38 -> Диагональ объемная (2305мм) | AH197: ='Вышки туры'!D38 -> 1
A198: 4 | D198: ='Вышки туры'!A39 -> Гантель (1975мм) | AH198: ='Вышки туры'!D39 -> 4
A199: 5 | D199: ='Вышки туры'!A40 -> Стяжка лестницы (840мм) | AH199: ='Вышки туры'!D40 -> 24
A200: 6 | D200: ='Вышки туры'!A41 -> Стабилизатор в сборе (2400мм)
A201: 7 | D201: ='Вышки туры'!A42 -> Лестница ограждения (1160мм х 1214мм) | AH201: ='Вышки туры'!D42 -> 2
A202: 8 | D202: ='Вышки туры'!A43 -> Гантель ограждения (1965мм) | AH202: ='Вышки туры'!D43 -> 2
A203: 9 | D203: ='Вышки туры'!A44 -> Перекладина ограждения (1990мм) | AH203: ='Вышки туры'!D44 -> 2
A204: 10 | D204: ='Вышки туры'!A45 -> Настил без люка (1995мм х 525мм) | AH204: ='Вышки туры'!D45 -> 1
A205: 11 | D205: ='Вышки туры'!A46 -> Настил с люком (1995мм х 525мм) | AH205: ='Вышки туры'!D46 -> 1
A211: Арендодатель______________________Выборных А.П.
A213: Арендатор_________________________
A215: Оборудование (вышка тура) возвращены в полном объеме, претензий не имею
A216: _______________________________________________________.

Sheet ДляДоговора
A1: Реквизиты контрагента | D1: Дата для договора
A2: № договора | B2: =CONCATENATE(E2,"/",H3,"-",E5,"(",F4,")",E6) -> 30/03-А(23) | D2: День | E2: =DAY(TODAY()) -> 30 | V2: В Лице
A3: Дата | B3: =CONCATENATE(E2," ",F3," ",E4,"г.") -> 30 марта 2023г. | D3: Месяц | E3: =MONTH(TODAY()) -> 3 | F3: =IF(E3=1,"января",IF(E3=2,"февраля",IF(E3=3,"марта",IF(E3=4,"апреля",IF(E3=5,"мая",IF(E3=6,"июня",IF(E3=7,"июля",IF(E3=8,"августа",IF(E3=9,"сентября",IF(E3=10,"октября",IF(E3=11,"ноября",IF(E3=12,"декабря")))))))))))) -> марта | H3: =IF(E3=1,"01",IF(E3=2,"02",IF(E3=3,"03",IF(E3=4,"04",IF(E3=5,"05",IF(E3=6,"06",IF(E3=7,"07",IF(E3=8,"08",IF(E3=9,"09",IF(E3=10,"10",IF(E3=11,"11",IF(E3=12,"12")))))))))))) -> 03 | V3: директора | X3: Действующий
A4: Организация | B4: ООО "Эдвако-Инжиниринг" | D4: Год | E4: =YEAR(TODAY()) -> 2023 | F4: =RIGHT(E4,2) -> 23 | V4: генерального директора | X4: Устава
A5: в лице | B5: генерального директора | D5: Буква | E5: А | V5: исполнительного директора | X5: записи в ЕГРН
A6: ФИО директора | B6: Коряжбина Эдуарда Васильевича | D6: Индекс | V6: индивидуального предпринимателя | X6: Свидетельства
A7: Дейсвующий на основании | B7: Устава | V7: управляющего | X7: договора
A8: Свидетельство(Договор) № | V8: управляющего индивидуального предпринимателя | X8: доверенности
A9: Юр.Адрес | B9: 620014, РФ, г. Екатеринбург, ул. Московская, д.11 офис 903 | V9: заместителя директора
A10: ИНН | B10: 6658401387
A11: КПП | B11: 665801001
A12: р/счет | B12: 40702810562130001221
A13: в банке | B13: ПАО КБ «УБРиР»
A14: БИК | B14: 046577795
A15: кор/счет | B15: 30101810900000000795
A16: ОГРН | B16: 1126658000050
A17: Почт адрес | B17: 620014, РФ, г. Екатеринбург, ул. Московская, д.11 офис 903
A18: Адрес доставки | C18: Самовывоз
A19: E-MAIL | B19: ekoryazhbin@mail.ru
A20: Телефон | B20: (+7343) 227-34-77
A22: Город работы | B22: г. Екатеринбург

Sheet Договор аренды лесов Юр
A1: ='Расчет лесов'!C3 -> 210 | B1: =AW41 -> 0
BK2: Вспомогательные значения | BW2: Наименование | BX2: =IF($AW$20="без НДС",реквизиты!C3,реквизиты!G3) -> Универсальная производственно-строительная компания
A3: =CONCATENATE("ДОГОВОР АРЕНДЫ ОБОРУДОВАНИЯ №",ДляДоговора!B2) -> ДОГОВОР АРЕНДЫ ОБОРУДОВАНИЯ №30/03-А(23) | BK3: Срок аренды | BL3: ='Расчет лесов'!C4 -> 30 | BW3: В лице Директора | BX3: =IF($AW$20="без НДС",реквизиты!C4,реквизиты!G4) -> Выборных Андрея Павловича
BW4: Для подписи | BX4: =IF($AW$20="без НДС",реквизиты!C5,реквизиты!G5) -> А.П. Выборных
A5: =ДляДоговора!B22 -> г. Екатеринбург | AK5: =ДляДоговора!B3 -> 30 марта 2023г. | BK5: длина | BL5: ='Расчет лесов'!J3 -> 3 | BW5: ИНН | BX5: =IF($AW$20="без НДС",реквизиты!C6,реквизиты!G6) -> 6670463929
BK6: высота | BL6: ='Расчет лесов'!K3 -> 8 | BW6: КПП | BX6: =IF($AW$20="без НДС",реквизиты!C7,реквизиты!G7) -> 667001001
A7: ="Общество с ограниченной ответственностью «"&BX2&"» (ООО «УПСК»), именуемое в дальнейшем «Арендодатель», в лице директора "&BX3&", действующего на основании Устава, с одной стороны, и "&ДляДоговора!B4&" именуемое в дальнейшем «Арендатор», в лице "&ДляДоговора!B5&" "&ДляДоговора!B6&", действующего на основании "&ДляДоговора!B7&ДляДоговора!B8&", с другой стороны, именуемые вместе «Стороны», а по отдельности «Сторона», заключили настоящий договор (далее - Договор) о нижеследующем." -> Общество с ограниченной ответственностью «Универсальная производственно-строительная компания» (ООО «УПСК»), именуемое в дальнейшем «Арендодатель», в лице директора Выборных Андрея Павловича, действующего на основании Устава, с одной стороны, и ООО "Эдвако-Инжиниринг" именуемое в дальнейшем «Арендатор», в лице генерального директора Коряжбина Эдуарда Васильевича, действующего на основании Устава, с другой стороны, именуемые вместе «Стороны», а по отдельности «Сторона», заключили настоящий договор (далее - Договор) о нижеследующем. | BW7: ОГРН | BX7: =IF($AW$20="без НДС",реквизиты!C8,реквизиты!G8) -> 1186658009042
BL8: =TODAY() -> 45015 | BW8: Юр. адрес | BX8: =IF($AW$20="без НДС",реквизиты!C9,реквизиты!G9) -> 620066, Свердловская область, г. Екатеринбург, ул. Вилонова, стр. 45Л, офис 506,
BL9: =DAY(TODAY()) -> 30 | BM9: -4 | BW9: Почт. Адрес | BX9: =IF($AW$20="без НДС",реквизиты!C10,реквизиты!G10) -> 620066, Свердловская область, г. Екатеринбург, ул. Вилонова, стр. 45Л
BF10: =MONTH(TODAY()) -> 3 | BL10: =YEAR(TODAY()) -> 2023 | BW10: Р/счет | BX10: =IF($AW$20="без НДС",реквизиты!C11,реквизиты!G11) -> 40702810816540041503
BL11: =IF(BF10=1,"01",IF(BF10=2,"02",IF(BF10=3,"03",IF(BF10=4,"04",IF(BF10=5,"05",IF(BF10=6,"06",IF(BF10=7,"07",IF(BF10=8,"08",IF(BF10=9,"09",IF(BF10=10,"10",IF(BF10=11,"11",IF(BF10=12,"12")))))))))))) -> 03 | BW11: в банке | BX11: =IF($AW$20="без НДС",реквизиты!C12,реквизиты!G12) -> УРАЛЬСКИЙ БАНК ПАО СБЕРБАНК
BW12: Кор. Счет | BX12: =IF($AW$20="без НДС",реквизиты!C13,реквизиты!G13) -> 30101810500000000674
A13: 1. ПРЕДМЕТ ДОГОВОРА | BL13: =IF(BF10=1,"января",IF(BF10=2,"февраля",IF(BF10=3,"марта",IF(BF10=4,"апреля",IF(BF10=5,"мая",IF(BF10=6,"июня",IF(BF10=7,"июля",IF(BF10=8,"августа",IF(BF10=9,"сентября",IF(BF10=10,"октября",IF(BF10=11,"ноября",IF(BF10=12,"декабря")))))))))))) -> марта | BW13: БИК | BX13: =IF($AW$20="без НДС",реквизиты!C14,реквизиты!G14) -> 046577674
A14: 1.1. В порядке и на условиях настоящего Договора Арендодатель обязуется передать за плату во временное пользование (аренду) Арендатору имущество (далее по тексту «имущество» или «Оборудование») согласно Спецификации (Приложение №1 к настоящему Договору)
A17: 1.2. Арендуемое имущество передается Арендатору для осуществления предпринимательской деятельности.
A18: 1.3. Перечень, количество, стоимость передаваемого в аренду Оборудования, срок его аренды согласовывается сторонами в Спецификации, являющейся неотъемлемой частью настоящего Договора (Приложение №1 к Договору). | AV18: Объем | AW18: =CONCATENATE('Расчет лесов'!L12,'Расчет лесов'!M12) -> 24м2
A20: 2. ПОРЯДОК ПЕРЕДАЧИ, ТРАНСПОРТИРОВКИ И ВОЗВРАТА АРЕНДУЕМОГО ИМУЩЕСТВА | AV20: Налогообложение | AW20: с НДС 20%
A21: 2.1. Арендуемое имущество передается в состоянии, пригодном для немедленного и непосредственного осуществления Арендатором своей деятельности с его использованием. | AV21: сумма в сутки | AW21: =SUBSTITUTE(PROPER(INDEX(n_4,MID(TEXT(A1,n0),1,1)+1)&INDEX(n0x,MID(TEXT(A1,n0),2,1)+1,MID(TEXT(A1,n0),3,1)+1)&IF(-MID(TEXT(A1,n0),1,3),"миллиард"&VLOOKUP(MID(TEXT(A1,n0),3,1)*AND(MID(TEXT(A1,n0),2,1)-1),мил,2),"")&INDEX(n_4,MID(TEXT(A1,n0),4,1)+1)&INDEX(n0x,MID(TEXT(A1,n0),5,1)+1,MID(TEXT(A1,n0),6,1)+1)&IF(-MID(TEXT(A1,n0),4,3),"миллион"&VLOOKUP(MID(TEXT(A1,n0),6,1)*AND(MID(TEXT(A1,n0),5,1)-1),мил,2),"")&INDEX(n_4,MID(TEXT(A1,n0),7,1)+1)&INDEX(n1x,MID(TEXT(A1,n0),8,1)+1,MID(TEXT(A1,n0),9,1)+1)&IF(-MID(TEXT(A1,n0),7,3),VLOOKUP(MID(TEXT(A1,n0),9,1)*AND(MID(TEXT(A1,n0),8,1)-1),тыс,2),"")&INDEX(n_4,MID(TEXT(A1,n0),10,1)+1)&INDEX(n0x,MID(TEXT(A1,n0),11,1)+1,MID(TEXT(A1,n0),12,1)+1)),"z"," ")&IF(TRUNC(TEXT(A1,n0)),"","Ноль ")&"рубл"&VLOOKUP(MOD(MAX(MOD(MID(TEXT(A1,n0),11,2)-11,100),9),10),{0,"ь ";1,"я ";4,"ей "},2)&RIGHT(TEXT(A1,n0),2)&" копе"&VLOOKUP(MOD(MAX(MOD(RIGHT(TEXT(A1,n0),2)-11,100),9),10),{0,"йка";1,"йки";4,"ек"},2) -> Двести десять рублей 00 копеек | AX21: =SUBSTITUTE(PROPER(INDEX(n_4,MID(TEXT(B1,n0),1,1)+1)&INDEX(n0x,MID(TEXT(B1,n0),2,1)+1,MID(TEXT(B1,n0),3,1)+1)&IF(-MID(TEXT(B1,n0),1,3),"миллиард"&VLOOKUP(MID(TEXT(B1,n0),3,1)*AND(MID(TEXT(B1,n0),2,1)-1),мил,2),"")&INDEX(n_4,MID(TEXT(B1,n0),4,1)+1)&INDEX(n0x,MID(TEXT(B1,n0),5,1)+1,MID(TEXT(B1,n0),6,1)+1)&IF(-MID(TEXT(B1,n0),4,3),"миллион"&VLOOKUP(MID(TEXT(B1,n0),6,1)*AND(MID(TEXT(B1,n0),5,1)-1),мил,2),"")&INDEX(n_4,MID(TEXT(B1,n0),7,1)+1)&INDEX(n1x,MID(TEXT(B1,n0),8,1)+1,MID(TEXT(B1,n0),9,1)+1)&IF(-MID(TEXT(B1,n0),7,3),VLOOKUP(MID(TEXT(B1,n0),9,1)*AND(MID(TEXT(B1,n0),8,1)-1),тыс,2),"")&INDEX(n_4,MID(TEXT(B1,n0),10,1)+1)&INDEX(n0x,MID(TEXT(B1,n0),11,1)+1,MID(TEXT(B1,n0),12,1)+1)),"z"," ")&IF(TRUNC(TEXT(B1,n0)),"","Ноль ")&"рубл"&VLOOKUP(MOD(MAX(MOD(MID(TEXT(B1,n0),11,2)-11,100),9),10),{0,"ь ";1,"я ";4,"ей "},2)&RIGHT(TEXT(B1,n0),2)&" копе"&VLOOKUP(MOD(MAX(MOD(RIGHT(TEXT(B1,n0),2)-11,100),9),10),{0,"йка";1,"йки";4,"ек"},2) -> Ноль рублей 00 копеек
A22: 2.2. Арендуемое имущество передается Арендодателем Арендатору по Акту приема-передачи арендованного имущества (Приложение № 2 к настоящему Договору).
A23: 2.3. Транспортировка и погрузо-разгрузочные работы арендованного имущества со склада Арендодателя до объекта Арендатора и по истечении срока аренды на склад Арендодателя осуществляется за счет Арендатора.
A24: Прием и передача арендованного оборудования, производится в рабочие дни понедельник – пятница (кроме праздничных дней) с 09:00 до 17:00 часов если иное не согласованно сторонами.
A25: 2.4. По окончании срока аренды Сторонами или их представителями производится осмотр арендованного имущества с целью выявления дефектов и повреждений, не предусмотренных условиями нормальной эксплуатации и износа, после чего Стороны (их представители) составляют и подписывают акт приема-передачи (Возврата) арендованного имущества от Арендатора.
A26: Если в ходе осмотра выявлены дефекты и повреждения Стороны или их представители заносят характер дефектов и повреждений в акт приема-передачи (возврата) оборудования, который является основанием для оплаты Арендатором стоимости обслуживания и ремонта арендованного имущества в установленном настоящим Договором размере.
A27: 2.5. Арендодатель не производит приемку и передачу оборудования в случаях: 2.5.1. Отсутствия доверенности у представителя Арендатора;
A28: 2.5.2. Предъявления доверенности срок действия которой истек, или доверенности оформленной ненадлежащим образом (ошибки, поправки, исправления);
A29: 2.5.3. Отсутствия у представителя документа, удостоверяющего его личность и указанного в доверенности.
A30: 2.6. При наступлении обстоятельств, предусмотренных п. 2.5. Договора Арендатор обязан возместить все расходы, понесенные Арендодателем, связанные с организацией приемки-передачи Оборудования (погрузочно-разгрузочные работы, транспортные расходы).
A31: 2.7. Оборудование должно быть возвращено Арендодателю в том состоянии и комплектности, в котором было передано Арендатору.
A32: 2.8. 2.8. Возврат Оборудования не освобождает Арендатора от исполнения обязательств по оплате всех причитающихся в связи пользованием Оборудованием платежей в соответствии с условиями Договора.
A33: 2.9. Требования к возврату оборудования регламентируются, разделом 8 настоящего Договора.
... A61: 4.1. Арендатор, в течение 3 (Трех) рабочих дней с момента подписания Договора, уплачивает Арендодателю обеспечительный взнос в размере согласованном Сторонами в Спецификации на арендуемое имущество, а так же авансом арендную плату согласно Приложению №1 к настоящему Договору.
A62: 4.2. Арендная плата подлежит начислению с даты передачи Имущества Арендатору по Акту приема -передачи, включая день когда Имущество было передано, по день возврата этого Имущества Арендатору. | AU62: ='Расчет лесов'!C4 -> 30 | AV62: аванс за … дней
A63: 4.3. В случае продления срока аренды, Арендатор, в течение 3 (Трех) рабочих дней до момента окончания Срока аренды, оплачивает Стоимость продления аренды авансом в размере 100%.
A64: 4.4. Арендодатель, в течение 10 (десяти) рабочих дней с момента подписания Акта приема – передачи (возврата) оборудования и получения от Арендатора оригинала письма о возврате обеспечительного взноса, возвращает Арендатору обеспечительный взнос или его остаток.
A65: 4.5. Арендодатель имеет право самостоятельно в одностороннем порядке производить вычеты из обеспечительного взноса, в случае, если Арендатор не оплачивает в течение 5 (Пяти) рабочих дней с момента его уведомления, следующие платежи:
A66: 4.5.1. Арендной платы при продления аренды, арендной платы за время просрочки возврата оборудования;
A67: 4.5.2. Стоимость утраченного оборудования.
A68: 4.5.3. Стоимость ремонта / обслуживания оборудования.
A69: 4.5.4. Сумму расходов, связанных с досрочным расторжением Договора и вывозом оборудования с объекта (транспортные расходы, расходы по погрузке и разгрузке Оборудования, стоимость утраченного оборудования, ремонт/обслуживание оборудования и т.д.).
A70: 4.5.5. Суммы штрафных санкций, неустоек (пени) предусмотренных Договором.
A71: 4.6. Вычет из обеспечительного взноса может составлять как частичную, так и полную сумму обеспечительного взноса.
A72: 4.6.1. В случае, если внесенных Арендатором авансом в порядке предусмотренном п.п. 4.1, 4.2 Договора размера обеспечительного взноса не достаточно для полной оплаты суммы начисленных платежей, предусмотренных п. 4.5. Договора, арендная плата начисляется до момента полного исполнения Арендатором обязательств по возврату арендованного Имущества.
A73: 4.7. При досрочном расторжении Договора, а также при возврате Оборудования Арендодателю, или его части ранее окончания срока аренды, стоимость аренды пересчитывается на фактический срок использования Оборудования согласно условиям, согласованным Сторонами в Спецификации, если иное не установлено Сторонами.
A75: 5. ОТВЕТСТВЕННОСТЬ СТОРОН
... A102: 8. АДРЕСА, РЕКВИЗИТЫ И ПОДПИСИ СТОРОН:
B103: =CONCATENATE("Арендодатель: ООО «",BX2,"»") -> Арендодатель: ООО «Универсальная производственно-строительная компания»
B104: =CONCATENATE("Почтовый адрес: ",BX9) -> Почтовый адрес: 620066, Свердловская область, г. Екатеринбург, ул. Вилонова, стр. 45Л
B105: =CONCATENATE("Юридический адрес: ",BX8) -> Юридический адрес: 620066, Свердловская область, г. Екатеринбург, ул. Вилонова, стр. 45Л, офис 506,
B106: =CONCATENATE("ИНН/КПП ",BX5," / ",BX6) -> ИНН/КПП 6670463929 / 667001001
B107: =CONCATENATE("Р/счет ",BX10," в ",BX11) -> Р/счет 40702810816540041503 в УРАЛЬСКИЙ БАНК ПАО СБЕРБАНК
B108: =CONCATENATE("БИК ",BX13) -> БИК 046577674
B109: =CONCATENATE("К/с ",BX12) -> К/с 30101810500000000674 | V109: e-mail: upsk-2007@bk.ru
B110: =CONCATENATE("ОГРН: ",BX7) -> ОГРН: 1186658009042
B112: =CONCATENATE("Арендатор: ",ДляДоговора!B4) -> Арендатор: ООО "Эдвако-Инжиниринг"
B113: =CONCATENATE("Юридический адрес: ",ДляДоговора!B9) -> Юридический адрес: 620014, РФ, г. Екатеринбург, ул. Московская, д.11 офис 903
B114: =CONCATENATE("Фактический адрес: ",ДляДоговора!B17) -> Фактический адрес: 620014, РФ, г. Екатеринбург, ул. Московская, д.11 офис 903
B115: =CONCATENATE("ИНН/КПП ",ДляДоговора!B10,"/",ДляДоговора!B11) -> ИНН/КПП 6658401387/665801001
B116: =CONCATENATE("Р/счет ",ДляДоговора!B12," в ",ДляДоговора!B13) -> Р/счет 40702810562130001221 в ПАО КБ «УБРиР»
B117: =CONCATENATE("БИК ",ДляДоговора!B14) -> БИК 046577795
B118: =CONCATENATE("К/с ",ДляДоговора!B15) -> К/с 30101810900000000795 | V118: =CONCATENATE("e-mail: ",ДляДоговора!B19) -> e-mail: ekoryazhbin@mail.ru
B119: =CONCATENATE("ОГРН: ",ДляДоговора!B16) -> ОГРН: 1126658000050
Q120: ПОДПИСИ СТОРОН:
B122: Арендодатель | AF122: Арендатор
M124: =BX4 -> А.П. Выборных
B126: М.П. | AF126: М.П.
A129: =CONCATENATE("Приложение №1 к договору аренды оборудования №",ДляДоговора!B2) -> Приложение №1 к договору аренды оборудования №30/03-А(23)
AL130: =CONCATENATE("от ",ДляДоговора!B3) -> от 30 марта 2023г.
A132: =CONCATENATE("СПЕЦИФИКАЦИЯ №",AV132," НА АРЕНДУЕМОЕ ОБОРУДОВАНИЕ") -> СПЕЦИФИКАЦИЯ №1 НА АРЕНДУЕМОЕ ОБОРУДОВАНИЕ | AV132: 1 | AW132: номер спецификации/акта
A133: =CONCATENATE("СТРОИТЕЛЬНЫЕ ЛЕСА ЛСПР-200 ",AW18,) -> СТРОИТЕЛЬНЫЕ ЛЕСА ЛСПР-200 24м2
A135: =ДляДоговора!B22 -> г. Екатеринбург
A137: 1. Перечень и стоимость передаваемого в аренду оборудования:
X139: Стоимость оборудования | AJ139: Арендная ставка
A140: № п/п | C140: Наименование | T140: Кол-во, шт. | X140: Стоимость руб. за ед. | AD140: Сумма, руб. | AJ140: Стоимость аренды 1шт/сут. | AO140: Сумма, руб
A141: 1 | C141: Рама проходная ЛСПР-200 | T141: ='Расчет лесов'!B$8 -> 4 | X141: ='Расчет лесов'!C$8 -> 1400 | AD141: =T141*X141 -> 5600 | AJ141: =AU141 -> 9.7 | AO141: =AJ141*T141 -> 38.8 | AU141: =ROUND(AV141,1) -> 9.7 | AV141: ='Расчет лесов'!G8 -> 9.6583443
A142: 2 | C142: Рама с лестницей ЛСПР-200 | T142: ='Расчет лесов'!B$9 -> 4 | X142: ='Расчет лесов'!C$9 -> 1670 | AD142: =T142*X142 -> 6680 | AJ142: =AU142 -> 11.5 | AO142: =AJ142*T142 -> 46 | AU142: =ROUND(AV142,1) -> 11.5 | AV142: ='Расчет лесов'!G9 -> 11.521025
A143: 3 | C143: Диагональная связь (3,3 м) ЛСПР-200 | T143: ='Расчет лесов'!B$10 -> 4 | X143: ='Расчет лесов'!C$10 -> 630 | AD143: =T143*X143 -> 2520 | AJ143: =AU143 -> 4.3 | AO143: =AJ143*T143 -> 17.2 | AU143: =ROUND(AV143,1) -> 4.3 | AV143: ='Расчет лесов'!G10 -> 4.3462549
A144: 4 | C144: Горизонтальная связь (3м) ЛСПР-200 | T144: ='Расчет лесов'!B$11 -> 4 | X144: ='Расчет лесов'!C$11 -> 320 | AD144: =T144*X144 -> 1280 | AJ144: =AU144 -> 2.2 | AO144: =AJ144*T144 -> 8.8 | AU144: =ROUND(AV144,1) -> 2.2 | AV144: ='Расчет лесов'!G11 -> 2.2076216
A145: 5 | C145: Мостки (настил) деревянные | T145: ='Расчет лесов'!B$12 -> 12 | X145: ='Расчет лесов'!C$12 -> 450 | AD145: =T145*X145 -> 5400 | AJ145: =AU145 -> 3.1 | AO145: =AJ145*T145 -> 37.2 | AU145: =ROUND(AV145,1) -> 3.1 | AV145: ='Расчет лесов'!G12 -> 3.1044678
A146: 6 | C146: Ригель для настила | T146: ='Расчет лесов'!B$13 -> 8 | X146: ='Расчет лесов'!C$13 -> 1120 | AD146: =T146*X146 -> 8960 | AJ146: =AU146 -> 7.7 | AO146: =AJ146*T146 -> 61.6 | AU146: =ROUND(AV146,1) -> 7.7 | AV146: ='Расчет лесов'!G13 -> 7.7266754 | AX146: 4 | AY146: 7 | AZ146: 14 | BA146: 30 | BB146: 45 | BC146: 60
A147: 7 | C147: Кронштейн | T147: ='Расчет лесов'!B$14 -> 0 | X147: ='Расчет лесов'!C$14 -> 200 | AD147: =T147*X147 -> 0 | AJ147: =AU147 -> 0 | AO147: =AJ147*T147 -> 0
A148: 8 | C148: Башмак | T148: ='Расчет лесов'!B$15 -> 0 | X148: ='Расчет лесов'!C$15 -> 150 | AD148: =T148*X148 -> 0 | AJ148: =AU148 -> 0 | AO148: =AJ148*T148 -> 0
X149: Всего: | AD149: =SUM(AD141:AI148) -> 30440 | AJ149: Всего: | AO149: ='Расчет лесов'!C3 -> 210 | AU149: =SUM(AO141:AS146) -> 209.6
AV150: ='Расчет лесов'!C4 -> 30
A151: 2. Арендная плата за комплект арендуемого оборудования составляет :
C152: =CONCATENATE(AU152," (",AW152,") за каждые сутки аренды",BX152,", срок аренды до ",AV152," дней") -> 800 (Восемьсот рублей 00 копеек) за каждые сутки аренды с учетом 20% НДС, срок аренды до 14 дней | AU152: 800 | AV152: =IF(AV150>=BC146,BB146,IF(AV150>=BB146,BA146,IF(AV150>=BA146,AZ146,IF(AV150>=AZ146,AY146,IF(AV150>=AY146,AX146,1))))) -> 14 | AW152: =SUBSTITUTE(PROPER(INDEX(n_4,MID(TEXT(AU152,n0),1,1)+1)&INDEX(n0x,MID(TEXT(AU152,n0),2,1)+1,MID(TEXT(AU152,n0),3,1)+1)&IF(-MID(TEXT(AU152,n0),1,3),"миллиард"&VLOOKUP(MID(TEXT(AU152,n0),3,1)*AND(MID(TEXT(AU152,n0),2,1)-1),мил,2),"")&INDEX(n_4,MID(TEXT(AU152,n0),4,1)+1)&INDEX(n0x,MID(TEXT(AU152,n0),5,1)+1,MID(TEXT(AU152,n0),6,1)+1)&IF(-MID(TEXT(AU152,n0),4,3),"миллион"&VLOOKUP(MID(TEXT(AU152,n0),6,1)*AND(MID(TEXT(AU152,n0),5,1)-1),мил,2),"")&INDEX(n_4,MID(TEXT(AU152,n0),7,1)+1)&INDEX(n1x,MID(TEXT(AU152,n0),8,1)+1,MID(TEXT(AU152,n0),9,1)+1)&IF(-MID(TEXT(AU152,n0),7,3),VLOOKUP(MID(TEXT(AU152,n0),9,1)*AND(MID(TEXT(AU152,n0),8,1)-1),тыс,2),"")&INDEX(n_4,MID(TEXT(AU152,n0),10,1)+1)&INDEX(n0x,MID(TEXT(AU152,n0),11,1)+1,MID(TEXT(AU152,n0),12,1)+1)),"z"," ")&IF(TRUNC(TEXT(AU152,n0)),"","Ноль ")&"рубл"&VLOOKUP(MOD(MAX(MOD(MID(TEXT(AU152,n0),11,2)-11,100),9),10),{0,"ь ";1,"я ";4,"ей "},2)&RIGHT(TEXT(AU152,n0),2)&" копе"&VLOOKUP(MOD(MAX(MOD(RIGHT(TEXT(AU152,n0),2)-11,100),9),10),{0,"йка";1,"йки";4,"ек"},2) -> Восемьсот рублей 00 копеек | BX152: =IF(AW20="с НДС 20%"," с учетом 20% НДС","") -> с учетом 20% НДС
C153: =CONCATENATE(AU153," (",AW153,") за каждые сутки аренды",BX152,", срок аренды до ",AV153," дней") -> 500 (Пятьсот рублей 00 копеек) за каждые сутки аренды с учетом 20% НДС, срок аренды до 30 дней | AU153: 500 | AV153: =IF(AV150>=BC146,BC146,IF(AV150>=BB146,BB146,IF(AV150>=BA146,BA146,IF(AV150>=AZ146,AZ146,IF(AV150>=AY146,AY146,IF(AV150>=AX146,AX146,1)))))) -> 30 | AW153: =SUBSTITUTE(PROPER(INDEX(n_4,MID(TEXT(AU153,n0),1,1)+1)&INDEX(n0x,MID(TEXT(AU153,n0),2,1)+1,MID(TEXT(AU153,n0),3,1)+1)&IF(-MID(TEXT(AU153,n0),1,3),"миллиард"&VLOOKUP(MID(TEXT(AU153,n0),3,1)*AND(MID(TEXT(AU153,n0),2,1)-1),мил,2),"")&INDEX(n_4,MID(TEXT(AU153,n0),4,1)+1)&INDEX(n0x,MID(TEXT(AU153,n0),5,1)+1,MID(TEXT(AU153,n0),6,1)+1)&IF(-MID(TEXT(AU153,n0),4,3),"миллион"&VLOOKUP(MID(TEXT(AU153,n0),6,1)*AND(MID(TEXT(AU153,n0),5,1)-1),мил,2),"")&INDEX(n_4,MID(TEXT(AU153,n0),7,1)+1)&INDEX(n1x,MID(TEXT(AU153,n0),8,1)+1,MID(TEXT(AU153,n0),9,1)+1)&IF(-MID(TEXT(AU153,n0),7,3),VLOOKUP(MID(TEXT(AU153,n0),9,1)*AND(MID(TEXT(AU153,n0),8,1)-1),тыс,2),"")&INDEX(n_4,MID(TEXT(AU153,n0),10,1)+1)&INDEX(n0x,MID(TEXT(AU153,n0),11,1)+1,MID(TEXT(AU153,n0),12,1)+1)),"z"," ")&IF(TRUNC(TEXT(AU153,n0)),"","Ноль ")&"рубл"&VLOOKUP(MOD(MAX(MOD(MID(TEXT(AU153,n0),11,2)-11,100),9),10),{0,"ь ";1,"я ";4,"ей "},2)&RIGHT(TEXT(AU153,n0),2)&" копе"&VLOOKUP(MOD(MAX(MOD(RIGHT(TEXT(AU153,n0),2)-11,100),9),10),{0,"йка";1,"йки";4,"ек"},2) -> Пятьсот рублей 00 копеек
C154: =CONCATENATE('Расчет лесов'!C3," (",AW21,") за каждые сутки аренды",BX152,", срок аренды от ",AV153," дней") -> 210 (Двести десять рублей 00 копеек) за каждые сутки аренды с учетом 20% НДС, срок аренды от 30 дней | AU154: 1
A155: =CONCATENATE("3. Срок аренды составляет ",'Расчет лесов'!C4," суток с момента подписания акта приема-передачи оборудования") -> 3. Срок аренды составляет 30 суток с момента подписания акта приема-передачи оборудования | AU155: =TODAY()+AU154 -> 45016 | AV155: =AU155+'Расчет лесов'!C4 -> 45046
A156: 4. Размер арендной платы за период аренды | AM156: ='Расчет лесов'!D22 -> 6300
A157: 5. Размер обеспечительного взноса | AM157: ='Расчет лесов'!D17 -> 3100
A158: =CONCATENATE("6.1. Стоимость доставки до адреса: ",ДляДоговора!B18,", составит ") -> 6.1. Стоимость доставки до адреса: , составит | AM158: ='Расчет лесов'!D18 -> 0
A159: =CONCATENATE("6.2. Стоимость вывоза с адреса: ",ДляДоговора!B18," , составит ") -> 6.2. Стоимость вывоза с адреса: , составит | AM159: ='Расчет лесов'!D19 -> 0
A160: 7. Итоговая стоимость по договору составляет | AM160: ='Расчет лесов'!D24 -> 9400
A161: Все цены указаны с учетом 20% НДС (кроме обеспечительного взноса)
A162: Настоящая Спецификация составлена в двух идентичных экземплярах, по одному для каждой из Сторон.
A165: Подписи представителей сторон:
B166: Арендодатель | AF166: Арендатор
M168: =BX4 -> А.П. Выборных
B170: М.П. | AF170: М.П.
A171: =CONCATENATE("Приложение №2 к договору аренды оборудования №",ДляДоговора!B2) -> Приложение №2 к договору аренды оборудования №30/03-А(23)
...

Sheet Счет Юр леса
B1: Внимание! Оплата данного счета означает согласие с условиями поставки товара. Уведомление об оплате обязательно, в противном случае не гарантируется наличие товара на складе. Товар отпускается по факту прихода денег на р/с Поставщика, самовывозом, при наличии доверенности и паспорта.
AX2: № СЧЕТА | AY2: 660
A3: =AH26 -> 9400 | AX3: Всего наименований | AY3: 4
B5: ='Договор аренды лесов Юр'!BX11 -> УРАЛЬСКИЙ БАНК ПАО СБЕРБАНК | T5: БИК | X5: ='Договор аренды лесов Юр'!BX13 -> 046577674 | AX5: день | AY5: =DAY(TODAY()) -> 30
T6: Сч. № | X6: ='Договор аренды лесов Юр'!BX12 -> 30101810500000000674 | AX6: месяц | AY6: =IF(BF10=1,"января",IF(BF10=2,"февраля",IF(BF10=3,"марта",IF(BF10=4,"апреля",IF(BF10=5,"мая",IF(BF10=6,"июня",IF(BF10=7,"июля",IF(BF10=8,"августа",IF(BF10=9,"сентября",IF(BF10=10,"октября",IF(BF10=11,"ноября",IF(BF10=12,"декабря")))))))))))) -> марта
B7: Банк получателя | AX7: год | AY7: =YEAR(TODAY()) -> 2023
B8: ИНН | D8: ='Договор аренды лесов Юр'!BX5 -> 6670463929 | K8: КПП | M8: ='Договор аренды лесов Юр'!BX6 -> 667001001 | T8: Сч. № | X8: ='Договор аренды лесов Юр'!BX10 -> 40702810816540041503
B9: ООО"УПСК"
BF10: =MONTH(TODAY()) -> 3
B11: Получатель
B13: =CONCATENATE("Счет на оплату № ",AY2," от ",AY5," ",AY6," ",AY7,"г.") -> Счет на оплату № 660 от 30 марта 2023г.
B17: Поставщик: | F17: =CONCATENATE("ООО «УПСК», ИНН ",D8,", КПП ",M8,", ",реквизиты!G9," тел.8(343)2068882") -> ООО «УПСК», ИНН 6670463929, КПП 667001001, 620066, Свердловская область, г. Екатеринбург, ул. Вилонова, стр. 45Л, офис 506, тел.8(343)2068882
B19: Покупатель: | F19: =CONCATENATE(ДляДоговора!B4,", ИНН ",ДляДоговора!B10,", КПП ",ДляДоговора!B11,", Адрес: ",ДляДоговора!B9) -> ООО "Эдвако-Инжиниринг", ИНН 6658401387, КПП 665801001, Адрес: 620014, РФ, г. Екатеринбург, ул. Московская, д.11 офис 903
B21: № | D21: Товары (работы, услуги) | U21: Кол-во | Y21: Ед. | AB21: Цена | AH21: Сумма
B22: 1 | D22: =CONCATENATE("Оплата по договору № ",ДляДоговора!B2," от ",ДляДоговора!B3) -> Оплата по договору № 30/03-А(23) от 30 марта 2023г. | U22: ='Расчет лесов'!C4 -> 30 | Y22: сутки | AB22: ='Расчет лесов'!C3 -> 210 | AH22: =U22*AB22 -> 6300
B23: 2 | D23: Залоговая стоимость оборудования | U23: =IF(AY3=1,0,1) -> 1 | Y23: шт | AB23: ='Расчет лесов'!D17 -> 3100 | AH23: =U23*AB23 -> 3100
B24: 3 | D24: Доставка | U24: =IF(AY3=1,0,IF(AY3=2,0,1)) -> 1 | Y24: шт | AB24: ='Расчет лесов'!D18 -> 0 | AH24: =U24*AB24 -> 0
B25: 4 | D25: Доставка | U25: =IF(AY3=1,0,IF(AY3=2,0,IF(AY3=3,0,1))) -> 1 | Y25: шт | AB25: ='Расчет лесов'!D19 -> 0 | AH25: =U25*AB25 -> 0
AG26: Итого: | AH26: =SUM(AH22:AL25) -> 9400
AG27: В том числе НДС 20%: | AH27: =IF(D8=6670428868,AX28,AX27) -> 1050 | AX27: =(AH26-AH23)*20/120 -> 1050
AG28: Всего к оплате: | AH28: =AH26 -> 9400 | AX28: -
B29: =CONCATENATE("Всего наименований ",AY3," на сумму ",AH28,",00 руб.") -> Всего наименований 4 на сумму 9400,00 руб.
B30: =SUBSTITUTE(PROPER(INDEX(n_4,MID(TEXT(A3,n0),1,1)+1)&INDEX(n0x,MID(TEXT(A3,n0),2,1)+1,MID(TEXT(A3,n0),3,1)+1)&IF(-MID(TEXT(A3,n0),1,3),"миллиард"&VLOOKUP(MID(TEXT(A3,n0),3,1)*AND(MID(TEXT(A3,n0),2,1)-1),мил,2),"")&INDEX(n_4,MID(TEXT(A3,n0),4,1)+1)&INDEX(n0x,MID(TEXT(A3,n0),5,1)+1,MID(TEXT(A3,n0),6,1)+1)&IF(-MID(TEXT(A3,n0),4,3),"миллион"&VLOOKUP(MID(TEXT(A3,n0),6,1)*AND(MID(TEXT(A3,n0),5,1)-1),мил,2),"")&INDEX(n_4,MID(TEXT(A3,n0),7,1)+1)&INDEX(n1x,MID(TEXT(A3,n0),8,1)+1,MID(TEXT(A3,n0),9,1)+1)&IF(-MID(TEXT(A3,n0),7,3),VLOOKUP(MID(TEXT(A3,n0),9,1)*AND(MID(TEXT(A3,n0),8,1)-1),тыс,2),"")&INDEX(n_4,MID(TEXT(A3,n0),10,1)+1)&INDEX(n0x,MID(TEXT(A3,n0),11,1)+1,MID(TEXT(A3,n0),12,1)+1)),"z"," ")&IF(TRUNC(TEXT(A3,n0)),"","Ноль ")&"рубл"&VLOOKUP(MOD(MAX(MOD(MID(TEXT(A3,n0),11,2)-11,100),9),10),{0,"ь ";1,"я ";4,"ей "},2)&RIGHT(TEXT(A3,n0),2)&" копе"&VLOOKUP(MOD(MAX(MOD(RIGHT(TEXT(A3,n0),2)-11,100),9),10),{0,"йка";1,"йки";4,"ек"},2) -> Девять тысяч четыреста рублей 00 копеек
AX32: ='Договор аренды лесов Юр'!BX4 -> А.П. Выборных
B33: Руководитель | K33: =AX32 -> А.П. Выборных | V33: Бухгалтер | AE33: =AX32 -> А.П. Выборных
C36: Важно! Перед оплатой счета необходимо связаться с менеджером для уточнения наличия
C37: продукции на складе.

Sheet Договор аренды тур Юр
A1: ='Вышки туры'!B5 -> 156
BK2: Вспомогательные значения | BW2: Наименование | BX2: =IF($AW$20="без НДС",реквизиты!C3,реквизиты!G3) -> Универсальная производственно-строительная компания
A3: =CONCATENATE("ДОГОВОР АРЕНДЫ ОБОРУДОВАНИЯ №",ДляДоговора!B2) -> ДОГОВОР АРЕНДЫ ОБОРУДОВАНИЯ №30/03-А(23) | BK3: Срок аренды | BL3: ='Вышки туры'!G2 -> 30 | BW3: В лице Директора | BX3: =IF($AW$20="без НДС",реквизиты!C4,реквизиты!G4) -> Выборных Андрея Павловича
BW4: Для подписи | BX4: =IF($AW$20="без НДС",реквизиты!C5,реквизиты!G5) -> А.П. Выборных
A5: =ДляДоговора!B22 -> г. Екатеринбург | AK5: =ДляДоговора!B3 -> 30 марта 2023г. | BW5: ИНН | BX5: =IF($AW$20="без НДС",реквизиты!C6,реквизиты!G6) -> 6670463929
BW6: КПП | BX6: =IF($AW$20="без НДС",реквизиты!C7,реквизиты!G7) -> 667001001
A7: ="Общество с ограниченной ответственностью «"&BX2&"» (ООО «УПСК»), именуемое в дальнейшем «Арендодатель», в лице директора "&BX3&", действующего на основании Устава, с одной стороны, и "&ДляДоговора!B4&" именуемое в дальнейшем «Арендатор», в лице "&ДляДоговора!B5&" "&ДляДоговора!B6&", действующего на основании "&ДляДоговора!B7&ДляДоговора!B8&", с другой стороны, именуемые вместе «Стороны», а по отдельности «Сторона», заключили настоящий договор (далее - Договор) о нижеследующем." -> Общество с ограниченной ответственностью «Универсальная производственно-строительная компания» (ООО «УПСК»), именуемое в дальнейшем «Арендодатель», в лице директора Выборных Андрея Павловича, действующего на основании Устава, с одной стороны, и ООО "Эдвако-Инжиниринг" именуемое в дальнейшем «Арендатор», в лице генерального директора Коряжбина Эдуарда Васильевича, действующего на основании Устава, с другой стороны, именуемые вместе «Стороны», а по отдельности «Сторона», заключили настоящий договор (далее - Договор) о нижеследующем. | BW7: ОГРН | BX7: =IF($AW$20="без НДС",реквизиты!C8,реквизиты!G8) -> 1186658009042
BL8: =TODAY() -> 45015 | BW8: Юр. адрес | BX8: =IF($AW$20="без НДС",реквизиты!C9,реквизиты!G9) -> 620066, Свердловская область, г. Екатеринбург, ул. Вилонова, стр. 45Л, офис 506,
BL9: =DAY(TODAY()) -> 30 | BM9: -4 | BW9: Почт. Адрес | BX9: =IF($AW$20="без НДС",реквизиты!C10,реквизиты!G10) -> 620066, Свердловская область, г. Екатеринбург, ул. Вилонова, стр. 45Л
BF10: =MONTH(TODAY()) -> 3 | BL10: =YEAR(TODAY()) -> 2023 | BW10: Р/счет | BX10: =IF($AW$20="без НДС",реквизиты!C11,реквизиты!G11) -> 40702810816540041503
BL11: =IF(BF10=1,"01",IF(BF10=2,"02",IF(BF10=3,"03",IF(BF10=4,"04",IF(BF10=5,"05",IF(BF10=6,"06",IF(BF10=7,"07",IF(BF10=8,"08",IF(BF10=9,"09",IF(BF10=10,"10",IF(BF10=11,"11",IF(BF10=12,"12")))))))))))) -> 03 | BW11: в банке | BX11: =IF($AW$20="без НДС",реквизиты!C12,реквизиты!G12) -> УРАЛЬСКИЙ БАНК ПАО СБЕРБАНК
BW12: Кор. Счет | BX12: =IF($AW$20="без НДС",реквизиты!C13,реквизиты!G13) -> 30101810500000000674
A13: 1. ПРЕДМЕТ ДОГОВОРА | BL13: =IF(BF10=1,"января",IF(BF10=2,"февраля",IF(BF10=3,"марта",IF(BF10=4,"апреля",IF(BF10=5,"мая",IF(BF10=6,"июня",IF(BF10=7,"июля",IF(BF10=8,"августа",IF(BF10=9,"сентября",IF(BF10=10,"октября",IF(BF10=11,"ноября",IF(BF10=12,"декабря")))))))))))) -> марта | BW13: БИК | BX13: =IF($AW$20="без НДС",реквизиты!C14,реквизиты!G14) -> 046577674
A14: 1.1. В порядке и на условиях настоящего Договора Арендодатель обязуется передать за плату во временное владение и пользование (аренду) Арендатору имущество(оборудование) (далее по тексту «имущество» или «оборудование») согласно Спецификации (Приложение №1 к настоящему Договору)
A17: 1.2. Арендуемое имущество передается Арендатору для осуществления предпринимательской деятельности.
A18: 1.3. Срок аренды оборудования согласовывается сторонами в Спецификации (Приложение №1 к настоящему Договору).
A20: 2. ПОРЯДОК ПЕРЕДАЧИ, ТРАНСПОРТИРОВКИ И ВОЗВРАТА АРЕНДУЕМОГО ИМУЩЕСТВА | AV20: Налогообложение | AW20: с НДС 20%
A21: 2.1. Арендуемое имущество передается в состоянии, пригодном для немедленного и непосредственного осуществления Арендатором своей деятельности с его использованием.
A22: 2.2. Арендуемое имущество передается Арендодателем Арендатору по Акту приема-передачи арендованного имущества (Приложение № 2). | AV22: высота | AW22: ='Вышки туры'!G1 -> 3.89
A23: 2.3. Транспортировка и погрузо-разгрузочные работы арендованного имущества со склада Арендодателя до объекта Арендатора и по истечении срока аренды на склад Арендодателя осуществляется за счет Арендатора. | AV23: количество | AW23: ='Вышки туры'!G3 -> 1
A24: Прием и передача арендованного оборудования, производится в рабочие дни понедельник – пятница (кроме праздничных дней) с 09:00 до 17:00 часов если иное не согласованно сторонами. | AV24: сумма в сутки | AW24: =SUBSTITUTE(PROPER(INDEX(n_4,MID(TEXT(A1,n0),1,1)+1)&INDEX(n0x,MID(TEXT(A1,n0),2,1)+1,MID(TEXT(A1,n0),3,1)+1)&IF(-MID(TEXT(A1,n0),1,3),"миллиард"&VLOOKUP(MID(TEXT(A1,n0),3,1)*AND(MID(TEXT(A1,n0),2,1)-1),мил,2),"")&INDEX(n_4,MID(TEXT(A1,n0),4,1)+1)&INDEX(n0x,MID(TEXT(A1,n0),5,1)+1,MID(TEXT(A1,n0),6,1)+1)&IF(-MID(TEXT(A1,n0),4,3),"миллион"&VLOOKUP(MID(TEXT(A1,n0),6,1)*AND(MID(TEXT(A1,n0),5,1)-1),мил,2),"")&INDEX(n_4,MID(TEXT(A1,n0),7,1)+1)&INDEX(n1x,MID(TEXT(A1,n0),8,1)+1,MID(TEXT(A1,n0),9,1)+1)&IF(-MID(TEXT(A1,n0),7,3),VLOOKUP(MID(TEXT(A1,n0),9,1)*AND(MID(TEXT(A1,n0),8,1)-1),тыс,2),"")&INDEX(n_4,MID(TEXT(A1,n0),10,1)+1)&INDEX(n0x,MID(TEXT(A1,n0),11,1)+1,MID(TEXT(A1,n0),12,1)+1)),"z"," ")&IF(TRUNC(TEXT(A1,n0)),"","Ноль ")&"рубл"&VLOOKUP(MOD(MAX(MOD(MID(TEXT(A1,n0),11,2)-11,100),9),10),{0,"ь ";1,"я ";4,"ей "},2)&RIGHT(TEXT(A1,n0),2)&" копе"&VLOOKUP(MOD(MAX(MOD(RIGHT(TEXT(A1,n0),2)-11,100),9),10),{0,"йка";1,"йки";4,"ек"},2) -> Сто пятьдесят шесть рублей 00 копеек
A25: 2.4. По окончании срока аренды Сторонами или их представителями производится осмотр арендованного имущества с целью выявления дефектов и повреждений, не предусмотренных условиями нормальной эксплуатации и износа, после чего Стороны (их представители) составляют и подписывают акт приема-передачи (Возврата) арендованного имущества от Арендатора.
A26: Если в ходе осмотра выявлены дефекты и повреждения Стороны или их представители заносят характер дефектов и повреждений в акт приема-передачи (возврата) оборудования, который является основанием для оплаты Арендатором стоимости обслуживания и ремонта арендованного имущества в установленном настоящим Договором размере.
A27: 2.5. Арендодатель не производит приемку и передачу оборудования в случаях: 2.5.1. Отсутствия доверенности у представителя Арендатора;
A28: 2.5.2. Предъявления доверенности срок действия которой истек, или доверенности оформленной ненадлежащим образом (ошибки, поправки, исправления);
A29: 2.5.3. Отсутствия у представителя документа, удостоверяющего его личность и указанного в доверенности.
A30: 2.6. При наступлении обстоятельств по п.2.5. Арендатор обязан возместить все расходы, понесенные Арендодателем связанные с организацией приемки-передачи Оборудования (погрузочно-разгрузочные работы, транспортные расходы).
A31: 2.7. Оборудование должно быть возвращено Арендодателю в том состоянии и комплектности, в котором было передано Арендатору.
A32: 2.8. Возврат Оборудования не освобождает Арендатора от исполнения обязательств по оплате всех платежей в соответствии с условиями Договора.
A33: 2.9. Приемка оборудования регламентируется Инструкцией по приему - передаче оборудования, настоящего Договора (стр. 4)
A35: 3. ПРАВА И ОБЯЗАННОСТИ СТОРОН
A37: 3.1. Арендодатель обязуется: 3.1.1. Передать Арендатору арендуемое имущество в порядке и сроки, предусмотренные настоящим Договором.
A38: 3.1.2. По истечении срока аренды принять арендуемое имущество от Арендатора по акту приема-передачи.
... A62: 4.1. Арендатор, в течение 3 (Трех) рабочих дней с момента подписания Договора, уплачивает Арендодателю обеспечительный взнос в размере согласованном Сторонами в Спецификации на арендуемое имущество (Приложение №1 к настоящему Договору).
A63: =CONCATENATE("4.2. Арендатор, в течение 3 (Трех) рабочих дней с момента подписания Договора, оплачивает Арендодателю авансом арендную плату за ",AU63," суток аренды") -> 4.2. Арендатор, в течение 3 (Трех) рабочих дней с момента подписания Договора, оплачивает Арендодателю авансом арендную плату за 30 суток аренды | AU63: ='Вышки туры'!G2 -> 30 | AV63: аванс за … дней
A64: 4.3. В случае продления срока аренды, Арендатор, в течение 3 (Трех) рабочих дней до момента окончания Срока аренды, оплачивает Стоимость продления аренды авансом в размере 100%.
A65: 4.4. Арендодатель, в течение 10 (десяти) рабочих дней с момента подписания Акта приема – передачи (возврата) оборудования и получения от Арендатора оригинала письма о возврате обеспечительного взноса, возвращает Арендатору обеспечительный взнос или его остаток.
A66: 4.5. Арендодатель имеет право самостоятельно в одностороннем порядке производить вычеты из обеспечительного взноса, в случае, если Арендатор не оплачивает в течение 5 (Пяти) рабочих дней с момента его уведомления, следующие платежи:
A67: 4.5.1. Арендной платы при продления аренды, арендной платы за время просрочки возврата оборудования;
A68: 4.5.2. Стоимость утраченного оборудования.
A69: 4.5.3. Стоимость ремонта / обслуживания оборудования.
A70: 4.5.4. Сумму расходов, связанных с досрочным расторжением Договора и вывозом оборудования с объекта (транспортные расходы, расходы по погрузке и разгрузке Оборудования, стоимость утраченного оборудования, ремонт/обслуживание оборудования и т.д.).
A71: 4.6. Вычет из обеспечительного взноса может составлять как частичную, так и полную сумму обеспечительного взноса.
A72: 4.6.1. В случае, если внесенные Арендатором авансом в порядке п.п. 4.1, 4.2 Договора обеспечительный взнос и арендной платы не достаточны для полной оплаты суммы арендных платежей, а также иных платежей, предусмотренных п.п. 4.5.1., 4.5.2., 4.5.3., 4.5.4. Договора, арендная плата начисляется до момента полного исполнения Арендатором всех обязательств.
A73: 4.7. При досрочном расторжении Договора, а также при возврате оборудования Арендодателю или его части ранее окончания срока аренды, стоимость аренды пересчитывается на фактический срок использования оборудования согластно Спецификации (Приложение №1 к настоящему договору), если иное не согласовано Сторонами.
A75: 5. ОТВЕТСТВЕННОСТЬ СТОРОН
A76: 5.1. За нарушение сроков возврата арендованного имущества, нарушение сроков оплаты стоимости ремонта / обслуживания арендованного имущества, нарушение сроков уплаты арендной платы, Арендатор обязан уплатить Арендодателю неустойку в размере 0,3% (три десятых процента) от суммы (стоимости) неисполненного за каждый день просрочки до момента полного и надлежащего исполнения такого обязательства. Уплата неустойки не освобождает виновную Сторону от покрытия нанесенных другой Стороне убытков в полном объеме сверх подлежащей уплате неустойки и не освобождает виновную Сторону от надлежащего исполнения обязательств, принятых на себя по настоящему Договору.
... A99: 8. АДРЕСА, РЕКВИЗИТЫ И ПОДПИСИ СТОРОН:
B100: =CONCATENATE("Арендодатель: ООО «",BX2,"»") -> Арендодатель: ООО «Универсальная производственно-строительная компания»
B101: =CONCATENATE("Почтовый адрес: ",BX9) -> Почтовый адрес: 620066, Свердловская область, г. Екатеринбург, ул. Вилонова, стр. 45Л
B102: =CONCATENATE("Юридический адрес: ",BX8) -> Юридический адрес: 620066, Свердловская область, г. Екатеринбург, ул. Вилонова, стр. 45Л, офис 506,
B103: =CONCATENATE("ИНН/КПП ",BX5," / ",BX6) -> ИНН/КПП 6670463929 / 667001001
B104: =CONCATENATE("Р/счет ",BX10," в ",BX11) -> Р/счет 40702810816540041503 в УРАЛЬСКИЙ БАНК ПАО СБЕРБАНК
B105: =CONCATENATE("БИК ",BX13) -> БИК 046577674
B106: =CONCATENATE("К/с ",BX12) -> К/с 30101810500000000674 | X106: e-mail: upsk-2007@bk.ru
B107: =CONCATENATE("ОГРН: ",BX7) -> ОГРН: 1186658009042
B109: =CONCATENATE("Арендатор: ",ДляДоговора!B4) -> Арендатор: ООО "Эдвако-Инжиниринг"
B110: =CONCATENATE("Юридический адрес: ",ДляДоговора!B9) -> Юридический адрес: 620014, РФ, г. Екатеринбург, ул. Московская, д.11 офис 903
B111: =CONCATENATE("Фактический адрес: ",ДляДоговора!B17) -> Фактический адрес: 620014, РФ, г. Екатеринбург, ул. Московская, д.11 офис 903
B112: =CONCATENATE("ИНН/КПП ",ДляДоговора!B10,"/",ДляДоговора!B11) -> ИНН/КПП 6658401387/665801001
B113: =CONCATENATE("Р/счет ",ДляДоговора!B12," в ",ДляДоговора!B13) -> Р/счет 40702810562130001221 в ПАО КБ «УБРиР»
B114: =CONCATENATE("БИК ",ДляДоговора!B14) -> БИК 046577795
B115: =CONCATENATE("К/с ",ДляДоговора!B15) -> К/с 30101810900000000795 | X115: =CONCATENATE("e-mail: ",ДляДоговора!B19) -> e-mail: ekoryazhbin@mail.ru
B116: =CONCATENATE("ОГРН: ",ДляДоговора!B16) -> ОГРН: 1126658000050
Q117: ПОДПИСИ СТОРОН:
B119: Арендодатель | AF119: Арендатор
M121: =BX4 -> А.П. Выборных
B123: М.П. | AF123: М.П.
A124: =CONCATENATE("Приложение №1 к договору аренды оборудования №",ДляДоговора!B2) -> Приложение №1 к договору аренды оборудования №30/03-А(23)
AL125: =CONCATENATE("от ",ДляДоговора!B3) -> от 30 марта 2023г.
A127: =CONCATENATE("СПЕЦИФИКАЦИЯ №",AV127," НА АРЕНДУЕМОЕ ОБОРУДОВАНИЕ") -> СПЕЦИФИКАЦИЯ №1 НА АРЕНДУЕМОЕ ОБОРУДОВАНИЕ | AV127: 1 | AW127: номер спецификации/акта
A128: =CONCATENATE("ВЫШКА-ТУРА ",'Вышки туры'!J7," Высотой ",AW22,"м, ",AW23," шт.") -> ВЫШКА-ТУРА ПСРВ-21 Высотой 3,89м, 1 шт.
A130: =ДляДоговора!B22 -> г. Екатеринбург
A132: 1. Перечень и стоимость передаваемого в аренду оборудования:
A134: № п/п | E134: Наименование | Y134: Количество, шт. | AF134: Стоимость руб. за ед. | AM134: Сумма, руб.
A135: 1 | E135: ='Вышки туры'!A36 -> База в сборе (2420мм) | Y135: ='Вышки туры'!D36 -> 2 | AF135: ='Вышки туры'!H36 -> 4160 | AM135: =Y135*AF135 -> 8320
A136: 2 | E136: ='Вышки туры'!A37 -> Лестница секции (1160мм х 1214мм) | Y136: ='Вышки туры'!D37 -> 6 | AF136: ='Вышки туры'!H37 -> 1300 | AM136: =Y136*AF136 -> 7800
A137: 3 | E137: ='Вышки туры'!A38 -> Диагональ объемная (2305мм) | Y137: ='Вышки туры'!D38 -> 1 | AF137: ='Вышки туры'!H38 -> 630 | AM137: =Y137*AF137 -> 630
A138: 4 | E138: ='Вышки туры'!A39 -> Гантель (1975мм) | Y138: ='Вышки туры'!D39 -> 4 | AF138: ='Вышки туры'!H39 -> 860 | AM138: =Y138*AF138 -> 3440
A139: 5 | E139: ='Вышки туры'!A40 -> Стяжка лестницы (840мм) | Y139: ='Вышки туры'!D40 -> 24 | AF139: ='Вышки туры'!H40 -> 140 | AM139: =Y139*AF139 -> 3360
A140: 6 | E140: ='Вышки туры'!A41 -> Стабилизатор в сборе (2400мм) | Y140: ='Вышки туры'!D41 -> 0 | AF140: ='Вышки туры'!H41 -> 860 | AM140: =Y140*AF140 -> 0
A141: 7 | E141: ='Вышки туры'!A43 -> Гантель ограждения (1965мм) | Y141: ='Вышки туры'!D42 -> 2 | AF141: ='Вышки туры'!H39 -> 860 | AM141: =Y141*AF141 -> 1720
A142: 8 | E142: ='Вышки туры'!A45 -> Настил без люка (1995мм х 525мм) | Y142: ='Вышки туры'!D45 -> 1 | AF142: ='Вышки туры'!H45 -> 4240 | AM142: =Y142*AF142 -> 4240
A143: 9 | E143: ='Вышки туры'!A46 -> Настил с люком (1995мм х 525мм) | Y143: ='Вышки туры'!D46 -> 1 | AF143: ='Вышки туры'!H46 -> 4410 | AM143: =Y143*AF143 -> 4410
AF144: Всего: | AM144: =SUM(AM135:AS143) -> 33920
AV145: ='Вышки туры'!G2 -> 30
A146: 2. Арендная плата за комплект арендуемого оборудования составляет :
C147: =CONCATENATE(AU147," (",AW147,") за каждые сутки аренды",BX155,", срок аренды до ",AV147," дней") -> 240 (Двести сорок рублей 00 копеек) за каждые сутки аренды с учетом 20% НДС, срок аренды до 21 дней | AU147: 240 | AV147: =IF(AV148>='Вышки туры'!Y8,'Вышки туры'!X8,IF('Договор аренды тур Юр'!AV148>='Вышки туры'!X8,'Вышки туры'!W8,IF('Договор аренды тур Юр'!AV148>='Вышки туры'!W8,'Вышки туры'!V8,IF('Договор аренды тур Юр'!AV148>='Вышки туры'!V8,'Вышки туры'!U8,IF('Договор аренды тур Юр'!AV148>='Вышки туры'!U8,'Вышки туры'!T8,IF('Договор аренды тур Юр'!AV148>='Вышки туры'!T8,'Вышки туры'!T8,0)))))) -> 21 | AW147: =SUBSTITUTE(PROPER(INDEX(n_4,MID(TEXT(AU147,n0),1,1)+1)&INDEX(n0x,MID(TEXT(AU147,n0),2,1)+1,MID(TEXT(AU147,n0),3,1)+1)&IF(-MID(TEXT(AU147,n0),1,3),"миллиард"&VLOOKUP(MID(TEXT(AU147,n0),3,1)*AND(MID(TEXT(AU147,n0),2,1)-1),мил,2),"")&INDEX(n_4,MID(TEXT(AU147,n0),4,1)+1)&INDEX(n0x,MID(TEXT(AU147,n0),5,1)+1,MID(TEXT(AU147,n0),6,1)+1)&IF(-MID(TEXT(AU147,n0),4,3),"миллион"&VLOOKUP(MID(TEXT(AU147,n0),6,1)*AND(MID(TEXT(AU147,n0),5,1)-1),мил,2),"")&INDEX(n_4,MID(TEXT(AU147,n0),7,1)+1)&INDEX(n1x,MID(TEXT(AU147,n0),8,1)+1,MID(TEXT(AU147,n0),9,1)+1)&IF(-MID(TEXT(AU147,n0),7,3),VLOOKUP(MID(TEXT(AU147,n0),9,1)*AND(MID(TEXT(AU147,n0),8,1)-1),тыс,2),"")&INDEX(n_4,MID(TEXT(AU147,n0),10,1)+1)&INDEX(n0x,MID(TEXT(AU147,n0),11,1)+1,MID(TEXT(AU147,n0),12,1)+1)),"z"," ")&IF(TRUNC(TEXT(AU147,n0)),"","Ноль ")&"рубл"&VLOOKUP(MOD(MAX(MOD(MID(TEXT(AU147,n0),11,2)-11,100),9),10),{0,"ь ";1,"я ";4,"ей "},2)&RIGHT(TEXT(AU147,n0),2)&" копе"&VLOOKUP(MOD(MAX(MOD(RIGHT(TEXT(AU147,n0),2)-11,100),9),10),{0,"йка";1,"йки";4,"ек"},2) -> Двести сорок рублей 00 копеек
C148: =CONCATENATE(AU148," (",AW148,") за каждые сутки аренды",BX155,", срок аренды до ",AV148," дней") -> 200 (Двести рублей 00 копеек) за каждые сутки аренды с учетом 20% НДС, срок аренды до 30 дней | AU148: 200 | AV148: =IF(AV145>='Вышки туры'!Y8,'Вышки туры'!Y8,IF('Договор аренды тур Юр'!AV145>='Вышки туры'!X8,'Вышки туры'!X8,IF('Договор аренды тур Юр'!AV145>='Вышки туры'!W8,'Вышки туры'!W8,IF('Договор аренды тур Юр'!AV145>='Вышки туры'!V8,'Вышки туры'!V8,IF('Договор аренды тур Юр'!AV145>='Вышки туры'!U8,'Вышки туры'!U8,IF('Договор аренды тур Юр'!AV145>='Вышки туры'!T8,'Вышки туры'!T8,AV145)))))) -> 30 | AW148: =SUBSTITUTE(PROPER(INDEX(n_4,MID(TEXT(AU148,n0),1,1)+1)&INDEX(n0x,MID(TEXT(AU148,n0),2,1)+1,MID(TEXT(AU148,n0),3,1)+1)&IF(-MID(TEXT(AU148,n0),1,3),"миллиард"&VLOOKUP(MID(TEXT(AU148,n0),3,1)*AND(MID(TEXT(AU148,n0),2,1)-1),мил,2),"")&INDEX(n_4,MID(TEXT(AU148,n0),4,1)+1)&INDEX(n0x,MID(TEXT(AU148,n0),5,1)+1,MID(TEXT(AU148,n0),6,1)+1)&IF(-MID(TEXT(AU148,n0),4,3),"миллион"&VLOOKUP(MID(TEXT(AU148,n0),6,1)*AND(MID(TEXT(AU148,n0),5,1)-1),мил,2),"")&INDEX(n_4,MID(TEXT(AU148,n0),7,1)+1)&INDEX(n1x,MID(TEXT(AU148,n0),8,1)+1,MID(TEXT(AU148,n0),9,1)+1)&IF(-MID(TEXT(AU148,n0),7,3),VLOOKUP(MID(TEXT(AU148,n0),9,1)*AND(MID(TEXT(AU148,n0),8,1)-1),тыс,2),"")&INDEX(n_4,MID(TEXT(AU148,n0),10,1)+1)&INDEX(n0x,MID(TEXT(AU148,n0),11,1)+1,MID(TEXT(AU148,n0),12,1)+1)),"z"," ")&IF(TRUNC(TEXT(AU148,n0)),"","Ноль ")&"рубл"&VLOOKUP(MOD(MAX(MOD(MID(TEXT(AU148,n0),11,2)-11,100),9),10),{0,"ь ";1,"я ";4,"ей "},2)&RIGHT(TEXT(AU148,n0),2)&" копе"&VLOOKUP(MOD(MAX(MOD(RIGHT(TEXT(AU148,n0),2)-11,100),9),10),{0,"йка";1,"йки";4,"ек"},2) -> Двести рублей 00 копеек
C149: =CONCATENATE('Вышки туры'!B5," (",AW24,") за каждые сутки аренды",BX155,", срок аренды от ",AV148," дней") -> 156 (Сто пятьдесят шесть рублей 00 копеек) за каждые сутки аренды с учетом 20% НДС, срок аренды от 30 дней | AU149: 2
A150: =CONCATENATE("3. Срок аренды составляет ",'Вышки туры'!G2," суток с момента подписания акта приема-передачи оборудования") -> 3. Срок аренды составляет 30 суток с момента подписания акта приема-передачи оборудования | AU150: =TODAY()+AU149 -> 45017 | AV150: =AU150+'Вышки туры'!G2 -> 45047
A151: 4. Размер арендной платы за период аренды | AM151: ='Вышки туры'!$D5 -> 4680
A152: 5. Размер обеспечительного взноса | AM152: ='Вышки туры'!G8 -> 2090
A153: =CONCATENATE("6.1. Стоимость доставки до адреса: ",ДляДоговора!B18,", составит ") -> 6.1. Стоимость доставки до адреса: , составит | AM153: ='Вышки туры'!G4 -> 0
A154: =CONCATENATE("6.2. Стоимость вывоза с адреса: ",ДляДоговора!B18," , составит ") -> 6.2. Стоимость вывоза с адреса: , составит | AM154: ='Вышки туры'!G4 -> 0
A155: 7. Итоговая стоимость по договору составляет | AM155: ='Вышки туры'!G6 -> 6770 | BX155: =IF(AW20="с НДС 20%"," с учетом 20% НДС","") -> с учетом 20% НДС
A156: Все цены указаны с учетом 20% НДС (кроме обеспечительного взноса)
A157: Настоящая Спецификация составлена в двух идентичных экземплярах, по одному для каждой из Сторон.
A159: Подписи представителей сторон:
B161: Арендодатель | AF161: Арендатор
...

Sheet Счет Юр вышка
B1: Внимание! Оплата данного счета означает согласие с условиями поставки товара. Уведомление об оплате обязательно, в противном случае не гарантируется наличие товара на складе. Товар отпускается по факту прихода денег на р/с Поставщика, самовывозом, при наличии доверенности и паспорта.
AX2: № СЧЕТА | AY2: 579
A3: =AH26 -> 6770 | AX3: Всего наименований | AY3: 2
B5: ='Договор аренды тур Юр'!BX11 -> УРАЛЬСКИЙ БАНК ПАО СБЕРБАНК | T5: БИК | X5: ='Договор аренды тур Юр'!BX13 -> 046577674 | AX5: день | AY5: =DAY(TODAY()) -> 30
T6: Сч. № | X6: ='Договор аренды тур Юр'!BX12 -> 30101810500000000674 | AX6: месяц | AY6: =IF(BF10=1,"января",IF(BF10=2,"февраля",IF(BF10=3,"марта",IF(BF10=4,"апреля",IF(BF10=5,"мая",IF(BF10=6,"июня",IF(BF10=7,"июля",IF(BF10=8,"августа",IF(BF10=9,"сентября",IF(BF10=10,"октября",IF(BF10=11,"ноября",IF(BF10=12,"декабря")))))))))))) -> марта
B7: Банк получателя | AX7: год | AY7: =YEAR(TODAY()) -> 2023
B8: ИНН | D8: ='Договор аренды тур Юр'!BX5 -> 6670463929 | K8: КПП | M8: ='Договор аренды тур Юр'!BX6 -> 667001001 | T8: Сч. № | X8: ='Договор аренды тур Юр'!BX10 -> 40702810816540041503
B9: ООО"УПСК"
BF10: =MONTH(TODAY()) -> 3
B11: Получатель
B13: =CONCATENATE("Счет на оплату № ",AY2," от ",AY5," ",AY6," ",AY7,"г.") -> Счет на оплату № 579 от 30 марта 2023г.
B17: Поставщик: | F17: =CONCATENATE("ООО «УПСК», ИНН ",D8,", КПП ",M8,", ",реквизиты!G9," тел.8(343)2068882") -> ООО «УПСК», ИНН 6670463929, КПП 667001001, 620066, Свердловская область, г. Екатеринбург, ул. Вилонова, стр. 45Л, офис 506, тел.8(343)2068882
B19: Покупатель: | F19: =CONCATENATE(ДляДоговора!B4,", ИНН ",ДляДоговора!B10,", КПП ",ДляДоговора!B11,", Адрес: ",ДляДоговора!B9) -> ООО "Эдвако-Инжиниринг", ИНН 6658401387, КПП 665801001, Адрес: 620014, РФ, г. Екатеринбург, ул. Московская, д.11 офис 903
B21: № | D21: Товары (работы, услуги) | U21: Кол-во | Y21: Ед. | AB21: Цена | AH21: Сумма
B22: 1 | D22: =CONCATENATE("Оплата по договору № ",ДляДоговора!B2," от ",ДляДоговора!B3) -> Оплата по договору № 30/03-А(23) от 30 марта 2023г. | U22: ='Вышки туры'!G2 -> 30 | Y22: сутки | AB22: ='Вышки туры'!S16 -> 156 | AH22: =U22*AB22 -> 4680
B23: 2 | D23: Залоговая стоимость оборудования | U23: =IF(AY3=1,0,1) -> 1 | Y23: шт | AB23: ='Вышки туры'!K3 -> 2090 | AH23: =U23*AB23 -> 2090
B24: 3 | D24: Доставка | U24: =IF(AY3=1,0,IF(AY3=2,0,1)) -> 0 | Y24: шт | AB24: ='Вышки туры'!G4 -> 0 | AH24: =U24*AB24 -> 0
B25: 4 | D25: Доставка | U25: =IF(AY3=1,0,IF(AY3=2,0,IF(AY3=3,0,1))) -> 0 | Y25: шт | AB25: ='Вышки туры'!G4 -> 0 | AH25: =U25*AB25 -> 0
AG26: Итого: | AH26: =SUM(AH22:AL25) -> 6770
AG27: В том числе НДС 20%: | AH27: =IF(D8=6670428868,AX28,AX27) -> 780 | AX27: =(AH26-AH23)*20/120 -> 780
AG28: Всего к оплате: | AH28: =AH26 -> 6770 | AX28: -
B29: =CONCATENATE("Всего наименований ",AY3," на сумму ",AH28,",00 руб.") -> Всего наименований 2 на сумму 6770,00 руб.
B30: =SUBSTITUTE(PROPER(INDEX(n_4,MID(TEXT(A3,n0),1,1)+1)&INDEX(n0x,MID(TEXT(A3,n0),2,1)+1,MID(TEXT(A3,n0),3,1)+1)&IF(-MID(TEXT(A3,n0),1,3),"миллиард"&VLOOKUP(MID(TEXT(A3,n0),3,1)*AND(MID(TEXT(A3,n0),2,1)-1),мил,2),"")&INDEX(n_4,MID(TEXT(A3,n0),4,1)+1)&INDEX(n0x,MID(TEXT(A3,n0),5,1)+1,MID(TEXT(A3,n0),6,1)+1)&IF(-MID(TEXT(A3,n0),4,3),"миллион"&VLOOKUP(MID(TEXT(A3,n0),6,1)*AND(MID(TEXT(A3,n0),5,1)-1),мил,2),"")&INDEX(n_4,MID(TEXT(A3,n0),7,1)+1)&INDEX(n1x,MID(TEXT(A3,n0),8,1)+1,MID(TEXT(A3,n0),9,1)+1)&IF(-MID(TEXT(A3,n0),7,3),VLOOKUP(MID(TEXT(A3,n0),9,1)*AND(MID(TEXT(A3,n0),8,1)-1),тыс,2),"")&INDEX(n_4,MID(TEXT(A3,n0),10,1)+1)&INDEX(n0x,MID(TEXT(A3,n0),11,1)+1,MID(TEXT(A3,n0),12,1)+1)),"z"," ")&IF(TRUNC(TEXT(A3,n0)),"","Ноль ")&"рубл"&VLOOKUP(MOD(MAX(MOD(MID(TEXT(A3,n0),11,2)-11,100),9),10),{0,"ь ";1,"я ";4,"ей "},2)&RIGHT(TEXT(A3,n0),2)&" копе"&VLOOKUP(MOD(MAX(MOD(RIGHT(TEXT(A3,n0),2)-11,100),9),10),{0,"йка";1,"йки";4,"ек"},2) -> Шесть тысяч семьсот семьдесят рублей 00 копеек
AX32: ='Договор аренды тур Юр'!BX4 -> А.П. Выборных
B33: Руководитель | K33: =AX32 -> А.П. Выборных | V33: Бухгалтер | AE33: =AX32 -> А.П. Выборных
C36: Важно! Перед оплатой счета необходимо связаться с менеджером для уточнения наличия
C37: продукции на складе.

Sheet Акт невозврата Леса
N1: ОБЩЕСТВО С ОГРАНИЧЕННОЙ ОТВЕТСТВЕННОСТЬЮ
N2: Универсальная производственно-строительная компания
N3: Адрес: 620075, г. Екатеринбург, ул. Мамина-Сибиряка, 101, оф. 16.09 | BN3: Должность | BO3: =ДляДоговора!B5 -> генерального директора | BP3: =IF(BO3="директора","Директору",IF(BO3="генерального директора","Генеральному директору",IF(BO3="исполнительного директора","Исполнительному директору",IF(BO3="индивидуального предпринимателя","Индивидуальному предпринимателю",IF(BO3="управляющего","Управляющему",IF(BO3="управляющего индивидуального предпринимателя","Управляющему индивидуальному предпринимателю",0)))))) -> Генеральному директору
N4: ИНН/КПП 6670463929 / 667001001, ОГРН 1186658009042 | BN4: ФИО | BP4: =ДляДоговора!B6 -> Коряжбина Эдуарда Васильевича
N5: Р/счет 40702810816540041503 в Банке УРАЛЬСКИЙ БАНК ПАО СБЕРБАНК | BN5: Написать вручную | BP5: Краснопольскому Роману Евгеньевичу
N6: БИК 046577674 К/с 30101810500000000674
N7: E-mail: upsk-2007@bk.ru Телефон: +7(343)2068882
BN8: Дата исходящего
B9: =CONCATENATE("Исх. от ",BO9,".",BP10,".",BO11) -> Исх. от 30.03.2023 | AC9: =BP3 -> Генеральному директору | BN9: День | BO9: =DAY(TODAY()) -> 30
AC10: =ДляДоговора!B4 -> ООО "Эдвако-Инжиниринг" | BN10: Месяц | BO10: =MONTH(TODAY()) -> 3 | BP10: =IF(BO10=1,"01",IF(BO10=2,"02",IF(BO10=3,"03",IF(BO10=4,"04",IF(BO10=5,"05",IF(BO10=6,"06",IF(BO10=7,"07",IF(BO10=8,"08",IF(BO10=9,"09",IF(BO10=10,"10",IF(BO10=11,"11",IF(BO10=12,"12")))))))))))) -> 03
AC11: =BP5 -> Краснопольскому Роману Евгеньевичу | BN11: Год | BO11: =YEAR(TODAY()) -> 2023
A13: Акт невозврата и повреждений
A15: =CONCATENATE("В соответсвии с пунктом 4.5 Договора аренды оборудования №",ДляДоговора!B2," от ",ДляДоговора!B3," направляем вам уведомление о необходимости оплаты оборудования сданного в аренду и не возвращеного обратно.") -> В соответсвии с пунктом 4.5 Договора аренды оборудования №30/03-А(23) от 30 марта 2023г. направляем вам уведомление о необходимости оплаты оборудования сданного в аренду и не возвращеного обратно.
A16: Калькуляция ущерба
A17: Сдано в аренду «актом приема передачи оборудования в аренду»:
A19: № п/п | E19: Наименование | AB19: Кол-во, шт. | AG19: Стоимость руб. за ед. | AN19: Сумма, руб.
A20: 1 | E20: ='Договор аренды лесов Юр'!C141 -> Рама проходная ЛСПР-200 | AB20: ='Договор аренды лесов Юр'!T141 -> 4 | AG20: ='Договор аренды лесов Юр'!X141 -> 1400 | AN20: =AB20*AG20 -> 5600
A21: 2 | E21: ='Договор аренды лесов Юр'!C142 -> Рама с лестницей ЛСПР-200 | AB21: ='Договор аренды лесов Юр'!T142 -> 4 | AG21: ='Договор аренды лесов Юр'!X142 -> 1670 | AN21: =AB21*AG21 -> 6680
A22: 3 | E22: ='Договор аренды лесов Юр'!C143 -> Диагональная связь (3,3 м) ЛСПР-200 | AB22: ='Договор аренды лесов Юр'!T143 -> 4 | AG22: ='Договор аренды лесов Юр'!X143 -> 630 | AN22: =AB22*AG22 -> 2520
A23: 4 | E23: ='Договор аренды лесов Юр'!C144 -> Горизонтальная связь (3м) ЛСПР-200 | AB23: ='Договор аренды лесов Юр'!T144 -> 4 | AG23: ='Договор аренды лесов Юр'!X144 -> 320 | AN23: =AB23*AG23 -> 1280
A24: 5 | E24: ='Договор аренды лесов Юр'!C145 -> Мостки (настил) деревянные | AB24: ='Договор аренды лесов Юр'!T145 -> 12 | AG24: ='Договор аренды лесов Юр'!X145 -> 450 | AN24: =AB24*AG24 -> 5400
A25: 6 | E25: ='Договор аренды лесов Юр'!C146 -> Ригель для настила | AB25: ='Договор аренды лесов Юр'!T146 -> 8 | AG25: ='Договор аренды лесов Юр'!X146 -> 1120 | AN25: =AB25*AG25 -> 8960
A26: 7
A27: 8
AN28: =SUM(AN20:AU25) -> 30440
A30: Возвращено «актом приема-передачи (возврата) оборудования»:
A32: № п/п | E32: Наименование | AB32: Кол-во, шт. | AG32: Стоимость руб. за ед. | AN32: Сумма, руб.
A33: 1 | E33: =E20 -> Рама проходная ЛСПР-200 | AB33: 3 | AG33: =AG20 -> 1400 | AN33: =AB33*AG33 -> 4200
A34: 2 | E34: =E21 -> Рама с лестницей ЛСПР-200 | AB34: 2 | AG34: =AG21 -> 1670 | AN34: =AB34*AG34 -> 3340
A35: 3 | E35: =E22 -> Диагональная связь (3,3 м) ЛСПР-200 | AB35: 1 | AG35: =AG22 -> 630 | AN35: =AB35*AG35 -> 630
A36: 4 | E36: =E23 -> Горизонтальная связь (3м) ЛСПР-200 | AB36: 0 | AG36: =AG23 -> 320 | AN36: =AB36*AG36 -> 0
A37: 5 | E37: =E24 -> Мостки (настил) деревянные | AB37: 10 | AG37: =AG24 -> 450 | AN37: =AB37*AG37 -> 4500
A38: 6 | E38: =E25 -> Ригель для настила | AB38: 0 | AG38: =AG25 -> 1120 | AN38: =AB38*AG38 -> 0
A39: 7 | E39: =E26 -> 0 | AB39: 0 | AG39: =AG26 -> 0 | AN39: =AB39*AG39 -> 0
A40: 8 | E40: =E27 -> 0 | AB40: 0 | AG40: =AG27 -> 0 | AN40: =AB40*AG40 -> 0
AN41: =SUM(AN33:AU38) -> 12670
A43: =CONCATENATE("Остаток не возвращенного оборудования с ценами в соответствии с приложением №1 к Договору аренды оборудования №",ДляДоговора!B2," от ",ДляДоговора!B3) -> Остаток не возвращенного оборудования с ценами в соответствии с приложением №1 к Договору аренды оборудования №30/03-А(23) от 30 марта 2023г.
A45: № п/п | E45: Наименование | AB45: Кол-во, шт. | AG45: Стоимость руб. за ед. | AN45: Сумма, руб.
A46: 1 | E46: =E20 -> Рама проходная ЛСПР-200 | AB46: =AB20-AB33 -> 1 | AG46: =AG20 -> 1400 | AN46: =AB46*AG46 -> 1400
A47: 2 | E47: =E21 -> Рама с лестницей ЛСПР-200 | AB47: =AB21-AB34 -> 2 | AG47: =AG21 -> 1670 | AN47: =AB47*AG47 -> 3340
A48: 3 | E48: =E22 -> Диагональная связь (3,3 м) ЛСПР-200 | AB48: =AB22-AB35 -> 3 | AG48: =AG22 -> 630 | AN48: =AB48*AG48 -> 1890
A49: 4 | E49: =E23 -> Горизонтальная связь (3м) ЛСПР-200 | AB49: =AB23-AB36 -> 4 | AG49: =AG23 -> 320 | AN49: =AB49*AG49 -> 1280
A50: 5 | E50: =E24 -> Мостки (настил) деревянные | AB50: =AB24-AB37 -> 2 | AG50: =AG24 -> 450 | AN50: =AB50*AG50 -> 900
A51: 6 | E51: =E25 -> Ригель для настила | AB51: =AB25-AB38 -> 8 | AG51: =AG25 -> 1120 | AN51: =AB51*AG51 -> 8960
A52: 7 | E52: =E26 -> 0 | AB52: =AB26-AB39 -> 0 | AG52: =AG26 -> 0 | AN52: =AB52*AG52 -> 0
A53: 8 | E53: =E27 -> 0 | AB53: =AB27-AB40 -> 0 | AG53: =AG27 -> 0 | AN53: =AB53*AG53 -> 0
AN54: =SUM(AN46:AU51) -> 17770
A56: Повреждение оборудования согласно акта приема(возврата):
A58: № п/п | E58: Наименование | AB58: Кол-во, шт. | AG58: Стоимость ремонта руб. за ед. | AN58: Сумма, руб.
A59: 1 | E59: =E20 -> Рама проходная ЛСПР-200 | AB59: 0 | AG59: ='[1]Договор аренды лесов Юр'!AI222 -> 300 | AN59: =AB59*AG59 -> 0
A60: 2 | E60: =E21 -> Рама с лестницей ЛСПР-200 | AB60: 0 | AG60: ='[1]Договор аренды лесов Юр'!AI223 -> 350 | AN60: =AB60*AG60 -> 0
A61: 3 | E61: =E22 -> Диагональная связь (3,3 м) ЛСПР-200 | AB61: 8 | AG61: ='[1]Договор аренды лесов Юр'!AI224 -> 100 | AN61: =AB61*AG61 -> 800
A62: 4 | E62: =E23 -> Горизонтальная связь (3м) ЛСПР-200 | AB62: 8 | AG62: ='[1]Договор аренды лесов Юр'!AI225 -> 50 | AN62: =AB62*AG62 -> 400 | BN62: Не вернули | BO62: =AN54 -> 17770
A63: 5 | E63: =E24 -> Мостки (настил) деревянные | AB63: 0 | AG63: ='[1]Договор аренды лесов Юр'!AI226 -> 100 | AN63: =AB63*AG63 -> 0 | BN63: Ремонт | BO63: =AN67 -> 1200
A64: 6 | E64: =E25 -> Ригель для настила | AB64: 0 | AG64: ='[1]Договор аренды лесов Юр'!AI227 -> 350 | AN64: =AB64*AG64 -> 0 | BN64: Очистка | BO64: 0
A65: 7 | E65: =E26 -> 0 | AB65: 0 | AG65: ='[1]Договор аренды лесов Юр'!AI228 -> 100 | AN65: =AB65*AG65 -> 0
A66: 8 | E66: =E27 -> 0 | AB66: 0 | AG66: ='[1]Договор аренды лесов Юр'!AI229 -> 50 | AN66: =AB66*AG66 -> 0
AN67: =SUM(AN59:AU66) -> 1200
BN68: Сумма | BO68: =BO62+BO63+BO64 -> 18970
A69: =CONCATENATE("Просим оплатить стоимость не возвращенного оборудования в полном объеме ",BO62," (",Доп!B5,"), а также стоимость ремонта оборудования согласно актам приема-передачи (возврата) в размере ",BO63," (",Доп!B6,")"," и ",BO64," (",Доп!B7,") стоимость очистки оборудования.") -> Просим оплатить стоимость не возвращенного оборудования в полном объеме 17770 (Семнадцать тысяч семьсот семьдесят рублей 00 копеек), а также стоимость ремонта оборудования согласно актам приема-передачи (возврата) в размере 1200 (Одна тысяча двести рублей 00 копеек) и 0 (Ноль рублей 00 копеек) стоимость очистки оборудования.
A70: =CONCATENATE("Итого сумма задолженности составит ",BO68," (",Доп!B8,")",) -> Итого сумма задолженности составит 18970 (Восемнадцать тысяч девятьсот семьдесят рублей 00 копеек)
A71: =CONCATENATE("При не оплате данного акта в соответствии с пунктом 4.5 Договора аренды оборудования №",ДляДоговора!B2," от ",ДляДоговора!B3,", мы будем вынуждены в одностороннем порядке произвести вычет из обеспечительного взноса.") -> При не оплате данного акта в соответствии с пунктом 4.5 Договора аренды оборудования №30/03-А(23) от 30 марта 2023г., мы будем вынуждены в одностороннем порядке произвести вычет из обеспечительного взноса.
A75: Директор ООО "УПСК" | AG75: Выборных Андрей Павлович
AB77: М.П.

Sheet Акт невозврата Вышки
N1: ОБЩЕСТВО С ОГРАНИЧЕННОЙ ОТВЕТСТВЕННОСТЬЮ
N2: Универсальная производственно-строительная компания
N3: Адрес: 620075, г. Екатеринбург, ул. Мамина-Сибиряка, 101, оф. 16.09 | BN3: Должность | BO3: =ДляДоговора!B5 -> генерального директора | BP3: =IF(BO3="директора","Директору",IF(BO3="генерального директора","Генеральному директору",IF(BO3="исполнительного директора","Исполнительному директору",IF(BO3="индивидуального предпринимателя","Индивидуальному предпринимателю",IF(BO3="управляющего","Управляющему",IF(BO3="управляющего индивидуального предпринимателя","Управляющему индивидуальному предпринимателю",0)))))) -> Генеральному директору
N4: ИНН/КПП 6670463929 / 667001001, ОГРН 1186658009042 | BN4: ФИО | BP4: =ДляДоговора!B6 -> Коряжбина Эдуарда Васильевича
N5: Р/счет 40702810816540041503 в Банке УРАЛЬСКИЙ БАНК ПАО СБЕРБАНК | BN5: Написать вручную | BP5: Краснопольскому Роману Евгеньевичу
N6: БИК 046577674 К/с 30101810500000000674
N7: E-mail: upsk-2007@bk.ru Телефон: +7(343)2068882
BN8: Дата исходящего
B9: =CONCATENATE("Исх. от ",BO9,".",BP10,".",BO11) -> Исх. от 30.03.2023 | AC9: =BP3 -> Генеральному директору | BN9: День | BO9: =DAY(TODAY()) -> 30
AC10: =ДляДоговора!B4 -> ООО "Эдвако-Инжиниринг" | BN10: Месяц | BO10: =MONTH(TODAY()) -> 3 | BP10: =IF(BO10=1,"01",IF(BO10=2,"02",IF(BO10=3,"03",IF(BO10=4,"04",IF(BO10=5,"05",IF(BO10=6,"06",IF(BO10=7,"07",IF(BO10=8,"08",IF(BO10=9,"09",IF(BO10=10,"10",IF(BO10=11,"11",IF(BO10=12,"12")))))))))))) -> 03
AC11: =BP5 -> Краснопольскому Роману Евгеньевичу | BN11: Год | BO11: =YEAR(TODAY()) -> 2023
A13: Акт невозврата и повреждений
A15: =CONCATENATE("В соответсвии с пунктом 4.5 Договора аренды оборудования №",ДляДоговора!B2," от ",ДляДоговора!B3," направляем вам уведомление о необходимости оплаты оборудования сданного в аренду и не возвращеного обратно.") -> В соответсвии с пунктом 4.5 Договора аренды оборудования №30/03-А(23) от 30 марта 2023г. направляем вам уведомление о необходимости оплаты оборудования сданного в аренду и не возвращеного обратно.
A16: Калькуляция ущерба
A17: Сдано в аренду «актом приема передачи оборудования в аренду»:
A19: № п/п | E19: Наименование | AB19: Кол-во, шт. | AG19: Стоимость руб. за ед. | AN19: Сумма, руб.
A20: 1 | E20: ='Договор аренды тур Юр'!E135 -> База в сборе (2420мм) | AB20: ='Договор аренды тур Юр'!Y135 -> 2 | AG20: ='Договор аренды тур Юр'!AF135 -> 4160 | AN20: =AB20*AG20 -> 8320
A21: 2 | E21: ='Договор аренды тур Юр'!E136 -> Лестница секции (1160мм х 1214мм) | AB21: ='Договор аренды тур Юр'!Y136 -> 6 | AG21: ='Договор аренды тур Юр'!AF136 -> 1300 | AN21: =AB21*AG21 -> 7800
A22: 3 | E22: ='Договор аренды тур Юр'!E137 -> Диагональ объемная (2305мм) | AB22: ='Договор аренды тур Юр'!Y137 -> 1 | AG22: ='Договор аренды тур Юр'!AF137 -> 630 | AN22: =AB22*AG22 -> 630
A23: 4 | E23: ='Договор аренды тур Юр'!E138 -> Гантель (1975мм) | AB23: ='Договор аренды тур Юр'!Y138 -> 4 | AG23: ='Договор аренды тур Юр'!AF138 -> 860 | AN23: =AB23*AG23 -> 3440
A24: 5 | E24: ='Договор аренды тур Юр'!E139 -> Стяжка лестницы (840мм) | AB24: ='Договор аренды тур Юр'!Y139 -> 24 | AG24: ='Договор аренды тур Юр'!AF139 -> 140 | AN24: =AB24*AG24 -> 3360
A25: 6 | E25: ='Договор аренды тур Юр'!E140 -> Стабилизатор в сборе (2400мм) | AB25: ='Договор аренды тур Юр'!Y140 -> 0 | AG25: ='Договор аренды тур Юр'!AF140 -> 860 | AN25: =AB25*AG25 -> 0
A26: 7 | E26: ='Договор аренды тур Юр'!E141 -> Гантель ограждения (1965мм) | AB26: ='Договор аренды тур Юр'!Y141 -> 2 | AG26: ='Договор аренды тур Юр'!AF141 -> 860 | AN26: =AB26*AG26 -> 1720
A27: 8 | E27: ='Договор аренды тур Юр'!E142 -> Настил без люка (1995мм х 525мм) | AB27: ='Договор аренды тур Юр'!Y142 -> 1 | AG27: ='Договор аренды тур Юр'!AF142 -> 4240 | AN27: =AB27*AG27 -> 4240
A28: 9 | E28: ='Договор аренды тур Юр'!E143 -> Настил с люком (1995мм х 525мм) | AB28: ='Договор аренды тур Юр'!Y143 -> 1 | AG28: ='Договор аренды тур Юр'!AF143 -> 4410 | AN28: =AB28*AG28 -> 4410
AN29: =SUM(AN20:AU28) -> 33920
A31: Возвращено «актом приема-передачи (возврата) оборудования»:
A33: № п/п | E33: Наименование | AB33: Кол-во, шт. | AG33: Стоимость руб. за ед. | AN33: Сумма, руб.
A34: 1 | E34: =E20 -> База в сборе (2420мм) | AB34: 2 | AG34: =AG20 -> 4160 | AN34: =AB34*AG34 -> 8320
A35: 2 | E35: =E21 -> Лестница секции (1160мм х 1214мм) | AB35: 4 | AG35: =AG21 -> 1300 | AN35: =AB35*AG35 -> 5200
A36: 3 | E36: =E22 -> Диагональ объемная (2305мм) | AB36: 1 | AG36: =AG22 -> 630 | AN36: =AB36*AG36 -> 630
A37: 4 | E37: =E23 -> Гантель (1975мм) | AB37: 0 | AG37: =AG23 -> 860 | AN37: =AB37*AG37 -> 0
A38: 5 | E38: =E24 -> Стяжка лестницы (840мм) | AB38: 20 | AG38: =AG24 -> 140 | AN38: =AB38*AG38 -> 2800
A39: 6 | E39: =E25 -> Стабилизатор в сборе (2400мм) | AB39: 0 | AG39: =AG25 -> 860 | AN39: =AB39*AG39 -> 0
A40: 7 | E40: =E26 -> Гантель ограждения (1965мм) | AB40: 2 | AG40: =AG26 -> 860 | AN40: =AB40*AG40 -> 1720
A41: 8 | E41: =E27 -> Настил без люка (1995мм х 525мм) | AB41: 1 | AG41: =AG27 -> 4240 | AN41: =AB41*AG41 -> 4240
A42: 8 | E42: =E28 -> Настил с люком (1995мм х 525мм) | AB42: 1 | AG42: =AG28 -> 4410 | AN42: =AB42*AG42 -> 4410
AN43: =SUM(AN34:AU39) -> 16950
A45: =CONCATENATE("Остаток не возвращенного оборудования с ценами в соответствии с приложением №1 к Договору аренды оборудования №",ДляДоговора!B2," от ",ДляДоговора!B3) -> Остаток не возвращенного оборудования с ценами в соответствии с приложением №1 к Договору аренды оборудования №30/03-А(23) от 30 марта 2023г.
A47: № п/п | E47: Наименование | AB47: Кол-во, шт. | AG47: Стоимость руб. за ед. | AN47: Сумма, руб.
A48: 1 | E48: =E20 -> База в сборе (2420мм) | AB48: =AB20-AB34 -> 0 | AG48: =AG20 -> 4160 | AN48: =AB48*AG48 -> 0
A49: 2 | E49: =E21 -> Лестница секции (1160мм х 1214мм) | AB49: =AB21-AB35 -> 2 | AG49: =AG21 -> 1300 | AN49: =AB49*AG49 -> 2600
A50: 3 | E50: =E22 -> Диагональ объемная (2305мм) | AB50: =AB22-AB36 -> 0 | AG50: =AG22 -> 630 | AN50: =AB50*AG50 -> 0
A51: 4 | E51: =E23 -> Гантель (1975мм) | AB51: =AB23-AB37 -> 4 | AG51: =AG23 -> 860 | AN51: =AB51*AG51 -> 3440
A52: 5 | E52: =E24 -> Стяжка лестницы (840мм) | AB52: =AB24-AB38 -> 4 | AG52: =AG24 -> 140 | AN52: =AB52*AG52 -> 560
A53: 6 | E53: =E25 -> Стабилизатор в сборе (2400мм) | AB53: =AB25-AB39 -> 0 | AG53: =AG25 -> 860 | AN53: =AB53*AG53 -> 0
A54: 7 | E54: =E26 -> Гантель ограждения (1965мм) | AB54: =AB26-AB40 -> 0 | AG54: =AG26 -> 860 | AN54: =AB54*AG54 -> 0
A55: 8 | E55: =E27 -> Настил без люка (1995мм х 525мм) | AB55: =AB27-AB41 -> 0 | AG55: =AG27 -> 4240 | AN55: =AB55*AG55 -> 0
A56: 9 | E56: =E28 -> Настил с люком (1995мм х 525мм) | AB56: =AB28-AB42 -> 0 | AG56: =AG28 -> 4410 | AN56: =AB56*AG56 -> 0
AN57: =SUM(AN48:AU56) -> 6600
A59: Повреждение оборудования согласно акта приема(возврата):
A61: № п/п | E61: Наименование | AB61: Кол-во, шт. | AG61: Стоимость ремонта руб. за ед. | AN61: Сумма, руб.
A62: 1 | E62: =E20 -> База в сборе (2420мм) | AB62: 0 | AG62: ='Договор аренды тур Юр'!AV222 -> 500 | AN62: =AB62*AG62 -> 0
A63: 2 | E63: =E21 -> Лестница секции (1160мм х 1214мм) | AB63: 2 | AG63: ='Договор аренды тур Юр'!AV223 -> 200 | AN63: =AB63*AG63 -> 400
A64: 3 | E64: =E22 -> Диагональ объемная (2305мм) | AB64: 0 | AG64: ='Договор аренды тур Юр'!AV224 -> 50 | AN64: =AB64*AG64 -> 0
A65: 4 | E65: =E23 -> Гантель (1975мм) | AB65: 0 | AG65: ='Договор аренды тур Юр'!AV225 -> 50 | AN65: =AB65*AG65 -> 0 | BN65: Не вернули | BO65: =AN57 -> 6600
A66: 5 | E66: =E24 -> Стяжка лестницы (840мм) | AB66: 0 | AG66: ='Договор аренды тур Юр'!AV226 -> 30 | AN66: =AB66*AG66 -> 0 | BN66: Ремонт | BO66: =AN71 -> 400
A67: 6 | E67: =E25 -> Стабилизатор в сборе (2400мм) | AB67: 0 | AG67: ='Договор аренды тур Юр'!AV227 -> 100 | AN67: =AB67*AG67 -> 0 | BN67: Очистка | BO67: 0
A68: 7 | E68: =E26 -> Гантель ограждения (1965мм) | AB68: 0 | AG68: ='Договор аренды тур Юр'!AV228 -> 50 | AN68: =AB68*AG68 -> 0
A69: 8 | E69: =E27 -> Настил без люка (1995мм х 525мм) | AB69: 0 | AG69: ='Договор аренды тур Юр'!AV229 -> 500 | AN69: =AB69*AG69 -> 0
A70: 9 | E70: =E28 -> Настил с люком (1995мм х 525мм) | AB70: 0 | AG70: ='Договор аренды тур Юр'!AV230 -> 500 | AN70: =AB70*AG70 -> 0
AN71: =SUM(AN62:AU70) -> 400
BN72: Сумма | BO72: =BO65+BO66+BO67 -> 7000
A73: =CONCATENATE("Просим оплатить стоимость не возвращенного оборудования в полном объеме ",BO65," (",Доп!B10,"), а также стоимость ремонта оборудования согласно актам приема-передачи (возврата) в размере ",BO66," (",Доп!B11,")"," и ",BO67," (",Доп!B12,") стоимость очистки оборудования.") -> Просим оплатить стоимость не возвращенного оборудования в полном объеме 6600 (Шесть тысяч шестьсот рублей 00 копеек), а также стоимость ремонта оборудования согласно актам приема-передачи (возврата) в размере 400 (Четыреста рублей 00 копеек) и 0 (Ноль рублей 00 копеек) стоимость очистки оборудования.
A74: =CONCATENATE("Итого сумма задолженности составит ",BO72," (",Доп!B13,")",) -> Итого сумма задолженности составит 7000 (Семь тысяч рублей 00 копеек)
A75: =CONCATENATE("При не оплате данного акта в соответствии с пунктом 4.5 Договора аренды оборудования №",ДляДоговора!B2," от ",ДляДоговора!B3,", мы будем вынуждены в одностороннем порядке произвести вычет из обеспечительного взноса.") -> При не оплате данного акта в соответствии с пунктом 4.5 Договора аренды оборудования №30/03-А(23) от 30 марта 2023г., мы будем вынуждены в одностороннем порядке произвести вычет из обеспечительного взноса.
A79: Директор ООО "УПСК" | AG79: Выборных Андрей Павлович
AB81: М.П.

Sheet Перерасчет
B2: Цена за элемент | C2: Арендовали | D2: Сумма | F2: Сдали | G2: Остаток | H2: Сумма в день
A3: ='Договор аренды лесов Юр'!C141 -> Рама проходная ЛСПР-200 | B3: ='Договор аренды лесов Юр'!AU141 -> 9.7 | C3: ='Договор аренды лесов Юр'!T141 -> 4 | D3: =B3*C3 -> 38.8 | F3: 0 | G3: =C3-F3 -> 4 | H3: =G3*B3 -> 38.8
A4: ='Договор аренды лесов Юр'!C142 -> Рама с лестницей ЛСПР-200 | B4: ='Договор аренды лесов Юр'!AU142 -> 11.5 | C4: ='Договор аренды лесов Юр'!T142 -> 4 | D4: =B4*C4 -> 46 | F4: 0 | G4: =C4-F4 -> 4 | H4: =G4*B4 -> 46
A5: ='Договор аренды лесов Юр'!C143 -> Диагональная связь (3,3 м) ЛСПР-200 | B5: ='Договор аренды лесов Юр'!AU143 -> 4.3 | C5: ='Договор аренды лесов Юр'!T143 -> 4 | D5: =B5*C5 -> 17.2 | F5: 0 | G5: =C5-F5 -> 4 | H5: =G5*B5 -> 17.2
A6: ='Договор аренды лесов Юр'!C144 -> Горизонтальная связь (3м) ЛСПР-200 | B6: ='Договор аренды лесов Юр'!AU144 -> 2.2 | C6: ='Договор аренды лесов Юр'!T144 -> 4 | D6: =B6*C6 -> 8.8 | F6: 0 | G6: =C6-F6 -> 4 | H6: =G6*B6 -> 8.8
A7: ='Договор аренды лесов Юр'!C145 -> Мостки (настил) деревянные | B7: ='Договор аренды лесов Юр'!AU145 -> 3.1 | C7: ='Договор аренды лесов Юр'!T145 -> 12 | D7: =B7*C7 -> 37.2 | F7: 0 | G7: =C7-F7 -> 12 | H7: =G7*B7 -> 37.2
A8: ='Договор аренды лесов Юр'!C146 -> Ригель для настила | B8: ='Договор аренды лесов Юр'!AU146 -> 7.7 | C8: ='Договор аренды лесов Юр'!T146 -> 8 | D8: =B8*C8 -> 61.6 | F8: 0 | G8: =C8-F8 -> 8 | H8: =G8*B8 -> 61.6
D9: =SUM(D3:D8) -> 209.6 | H9: =SUM(H3:H8) -> 209.6

Sheet реквизиты
B1: Реквизиты УПСК | F1: Реквизиты УПСК2 с НДС
B3: Наименование | C3: Универсальная проектно-строительная компания | F3: Наименование | G3: Универсальная производственно-строительная компания
B4: В лице Директора | C4: Колосова Ивана Андреевича | F4: В лице Директора | G4: Выборных Андрея Павловича
B5: Для подписи | C5: И.А. Колосов | F5: Для подписи | G5: А.П. Выборных
B6: ИНН | C6: 6670428868 | F6: ИНН | G6: 6670463929
B7: КПП | C7: 667001001 | F7: КПП | G7: 667001001
B8: ОГРН | C8: 1146670028141 | F8: ОГРН | G8: 1186658009042
B9: Юр. адрес | C9: 620066, Свердловская область, г. Екатеринбург, ул. Вилонова, стр. 45Л | F9: Юр. адрес | G9: 620066, Свердловская область, г. Екатеринбург, ул. Вилонова, стр. 45Л, офис 506,
B10: Почт. Адрес | C10: 620066, Свердловская область, г. Екатеринбург, ул. Вилонова, стр. 45Л | F10: Почт. Адрес | G10: 620066, Свердловская область, г. Екатеринбург, ул. Вилонова, стр. 45Л
B11: Р/счет | C11: 40702810238030005462 | F11: Р/счет | G11: 40702810816540041503
B12: в банке | C12: Филиале «Екатеринбургский» АО «АЛЬФА БАНК» | F12: в банке | G12: УРАЛЬСКИЙ БАНК ПАО СБЕРБАНК
B13: Кор. Счет | C13: 30101810100000000964 | F13: Кор. Счет | G13: 30101810500000000674
B14: БИК | C14: 046577964 | F14: БИК | G14: 046577674

Sheet Доп
A1: СУММА ПРОПИСЬЮ
A3: 1e+12 | B3: =SUBSTITUTE(PROPER(INDEX(n_4,MID(TEXT(A3,n0),1,1)+1)&INDEX(n0x,MID(TEXT(A3,n0),2,1)+1,MID(TEXT(A3,n0),3,1)+1)&IF(-MID(TEXT(A3,n0),1,3),"миллиард"&VLOOKUP(MID(TEXT(A3,n0),3,1)*AND(MID(TEXT(A3,n0),2,1)-1),мил,2),"")&INDEX(n_4,MID(TEXT(A3,n0),4,1)+1)&INDEX(n0x,MID(TEXT(A3,n0),5,1)+1,MID(TEXT(A3,n0),6,1)+1)&IF(-MID(TEXT(A3,n0),4,3),"миллион"&VLOOKUP(MID(TEXT(A3,n0),6,1)*AND(MID(TEXT(A3,n0),5,1)-1),мил,2),"")&INDEX(n_4,MID(TEXT(A3,n0),7,1)+1)&INDEX(n1x,MID(TEXT(A3,n0),8,1)+1,MID(TEXT(A3,n0),9,1)+1)&IF(-MID(TEXT(A3,n0),7,3),VLOOKUP(MID(TEXT(A3,n0),9,1)*AND(MID(TEXT(A3,n0),8,1)-1),тыс,2),"")&INDEX(n_4,MID(TEXT(A3,n0),10,1)+1)&INDEX(n0x,MID(TEXT(A3,n0),11,1)+1,MID(TEXT(A3,n0),12,1)+1)),"z"," ")&IF(TRUNC(TEXT(A3,n0)),"","Ноль ")&"рубл"&VLOOKUP(MOD(MAX(MOD(MID(TEXT(A3,n0),11,2)-11,100),9),10),{0,"ь ";1,"я ";4,"ей "},2)&RIGHT(TEXT(A3,n0),2)&" копе"&VLOOKUP(MOD(MAX(MOD(RIGHT(TEXT(A3,n0),2)-11,100),9),10),{0,"йка";1,"йки";4,"ек"},2) -> Девятьсот девяносто девять миллиардов девятьсот девяносто девять миллионов девятьсот девяносто девять тысяч девятьсот девяносто девять рублей 99 копеек
A4: Константы:
A5: ='Акт невозврата Леса'!BO62 -> 17770 | B5: =SUBSTITUTE(PROPER(INDEX(n_4,MID(TEXT(A5,n0),1,1)+1)&INDEX(n0x,MID(TEXT(A5,n0),2,1)+1,MID(TEXT(A5,n0),3,1)+1)&IF(-MID(TEXT(A5,n0),1,3),"миллиард"&VLOOKUP(MID(TEXT(A5,n0),3,1)*AND(MID(TEXT(A5,n0),2,1)-1),мил,2),"")&INDEX(n_4,MID(TEXT(A5,n0),4,1)+1)&INDEX(n0x,MID(TEXT(A5,n0),5,1)+1,MID(TEXT(A5,n0),6,1)+1)&IF(-MID(TEXT(A5,n0),4,3),"миллион"&VLOOKUP(MID(TEXT(A5,n0),6,1)*AND(MID(TEXT(A5,n0),5,1)-1),мил,2),"")&INDEX(n_4,MID(TEXT(A5,n0),7,1)+1)&INDEX(n1x,MID(TEXT(A5,n0),8,1)+1,MID(TEXT(A5,n0),9,1)+1)&IF(-MID(TEXT(A5,n0),7,3),VLOOKUP(MID(TEXT(A5,n0),9,1)*AND(MID(TEXT(A5,n0),8,1)-1),тыс,2),"")&INDEX(n_4,MID(TEXT(A5,n0),10,1)+1)&INDEX(n0x,MID(TEXT(A5,n0),11,1)+1,MID(TEXT(A5,n0),12,1)+1)),"z"," ")&IF(TRUNC(TEXT(A5,n0)),"","Ноль ")&"рубл"&VLOOKUP(MOD(MAX(MOD(MID(TEXT(A5,n0),11,2)-11,100),9),10),{0,"ь ";1,"я ";4,"ей "},2)&RIGHT(TEXT(A5,n0),2)&" копе"&VLOOKUP(MOD(MAX(MOD(RIGHT(TEXT(A5,n0),2)-11,100),9),10),{0,"йка";1,"йки";4,"ек"},2) -> Семнадцать тысяч семьсот семьдесят рублей 00 копеек
A6: ='Акт невозврата Леса'!BO63 -> 1200 | B6: =SUBSTITUTE(PROPER(INDEX(n_4,MID(TEXT(A6,n0),1,1)+1)&INDEX(n0x,MID(TEXT(A6,n0),2,1)+1,MID(TEXT(A6,n0),3,1)+1)&IF(-MID(TEXT(A6,n0),1,3),"миллиард"&VLOOKUP(MID(TEXT(A6,n0),3,1)*AND(MID(TEXT(A6,n0),2,1)-1),мил,2),"")&INDEX(n_4,MID(TEXT(A6,n0),4,1)+1)&INDEX(n0x,MID(TEXT(A6,n0),5,1)+1,MID(TEXT(A6,n0),6,1)+1)&IF(-MID(TEXT(A6,n0),4,3),"миллион"&VLOOKUP(MID(TEXT(A6,n0),6,1)*AND(MID(TEXT(A6,n0),5,1)-1),мил,2),"")&INDEX(n_4,MID(TEXT(A6,n0),7,1)+1)&INDEX(n1x,MID(TEXT(A6,n0),8,1)+1,MID(TEXT(A6,n0),9,1)+1)&IF(-MID(TEXT(A6,n0),7,3),VLOOKUP(MID(TEXT(A6,n0),9,1)*AND(MID(TEXT(A6,n0),8,1)-1),тыс,2),"")&INDEX(n_4,MID(TEXT(A6,n0),10,1)+1)&INDEX(n0x,MID(TEXT(A6,n0),11,1)+1,MID(TEXT(A6,n0),12,1)+1)),"z"," ")&IF(TRUNC(TEXT(A6,n0)),"","Ноль ")&"рубл"&VLOOKUP(MOD(MAX(MOD(MID(TEXT(A6,n0),11,2)-11,100),9),10),{0,"ь ";1,"я ";4,"ей "},2)&RIGHT(TEXT(A6,n0),2)&" копе"&VLOOKUP(MOD(MAX(MOD(RIGHT(TEXT(A6,n0),2)-11,100),9),10),{0,"йка";1,"йки";4,"ек"},2) -> Одна тысяча двести рублей 00 копеек
A7: ='Акт невозврата Леса'!BO64 -> 0 | B7: =SUBSTITUTE(PROPER(INDEX(n_4,MID(TEXT(A7,n0),1,1)+1)&INDEX(n0x,MID(TEXT(A7,n0),2,1)+1,MID(TEXT(A7,n0),3,1)+1)&IF(-MID(TEXT(A7,n0),1,3),"миллиард"&VLOOKUP(MID(TEXT(A7,n0),3,1)*AND(MID(TEXT(A7,n0),2,1)-1),мил,2),"")&INDEX(n_4,MID(TEXT(A7,n0),4,1)+1)&INDEX(n0x,MID(TEXT(A7,n0),5,1)+1,MID(TEXT(A7,n0),6,1)+1)&IF(-MID(TEXT(A7,n0),4,3),"миллион"&VLOOKUP(MID(TEXT(A7,n0),6,1)*AND(MID(TEXT(A7,n0),5,1)-1),мил,2),"")&INDEX(n_4,MID(TEXT(A7,n0),7,1)+1)&INDEX(n1x,MID(TEXT(A7,n0),8,1)+1,MID(TEXT(A7,n0),9,1)+1)&IF(-MID(TEXT(A7,n0),7,3),VLOOKUP(MID(TEXT(A7,n0),9,1)*AND(MID(TEXT(A7,n0),8,1)-1),тыс,2),"")&INDEX(n_4,MID(TEXT(A7,n0),10,1)+1)&INDEX(n0x,MID(TEXT(A7,n0),11,1)+1,MID(TEXT(A7,n0),12,1)+1)),"z"," ")&IF(TRUNC(TEXT(A7,n0)),"","Ноль ")&"рубл"&VLOOKUP(MOD(MAX(MOD(MID(TEXT(A7,n0),11,2)-11,100),9),10),{0,"ь ";1,"я ";4,"ей "},2)&RIGHT(TEXT(A7,n0),2)&" копе"&VLOOKUP(MOD(MAX(MOD(RIGHT(TEXT(A7,n0),2)-11,100),9),10),{0,"йка";1,"йки";4,"ек"},2) -> Ноль рублей 00 копеек
A8: ='Акт невозврата Леса'!BO68 -> 18970 | B8: =SUBSTITUTE(PROPER(INDEX(n_4,MID(TEXT(A8,n0),1,1)+1)&INDEX(n0x,MID(TEXT(A8,n0),2,1)+1,MID(TEXT(A8,n0),3,1)+1)&IF(-MID(TEXT(A8,n0),1,3),"миллиард"&VLOOKUP(MID(TEXT(A8,n0),3,1)*AND(MID(TEXT(A8,n0),2,1)-1),мил,2),"")&INDEX(n_4,MID(TEXT(A8,n0),4,1)+1)&INDEX(n0x,MID(TEXT(A8,n0),5,1)+1,MID(TEXT(A8,n0),6,1)+1)&IF(-MID(TEXT(A8,n0),4,3),"миллион"&VLOOKUP(MID(TEXT(A8,n0),6,1)*AND(MID(TEXT(A8,n0),5,1)-1),мил,2),"")&INDEX(n_4,MID(TEXT(A8,n0),7,1)+1)&INDEX(n1x,MID(TEXT(A8,n0),8,1)+1,MID(TEXT(A8,n0),9,1)+1)&IF(-MID(TEXT(A8,n0),7,3),VLOOKUP(MID(TEXT(A8,n0),9,1)*AND(MID(TEXT(A8,n0),8,1)-1),тыс,2),"")&INDEX(n_4,MID(TEXT(A8,n0),10,1)+1)&INDEX(n0x,MID(TEXT(A8,n0),11,1)+1,MID(TEXT(A8,n0),12,1)+1)),"z"," ")&IF(TRUNC(TEXT(A8,n0)),"","Ноль ")&"рубл"&VLOOKUP(MOD(MAX(MOD(MID(TEXT(A8,n0),11,2)-11,100),9),10),{0,"ь ";1,"я ";4,"ей "},2)&RIGHT(TEXT(A8,n0),2)&" копе"&VLOOKUP(MOD(MAX(MOD(RIGHT(TEXT(A8,n0),2)-11,100),9),10),{0,"йка";1,"йки";4,"ек"},2) -> Восемнадцать тысяч девятьсот семьдесят рублей 00 копеек
B9: =SUBSTITUTE(PROPER(INDEX(n_4,MID(TEXT(A9,n0),1,1)+1)&INDEX(n0x,MID(TEXT(A9,n0),2,1)+1,MID(TEXT(A9,n0),3,1)+1)&IF(-MID(TEXT(A9,n0),1,3),"миллиард"&VLOOKUP(MID(TEXT(A9,n0),3,1)*AND(MID(TEXT(A9,n0),2,1)-1),мил,2),"")&INDEX(n_4,MID(TEXT(A9,n0),4,1)+1)&INDEX(n0x,MID(TEXT(A9,n0),5,1)+1,MID(TEXT(A9,n0),6,1)+1)&IF(-MID(TEXT(A9,n0),4,3),"миллион"&VLOOKUP(MID(TEXT(A9,n0),6,1)*AND(MID(TEXT(A9,n0),5,1)-1),мил,2),"")&INDEX(n_4,MID(TEXT(A9,n0),7,1)+1)&INDEX(n1x,MID(TEXT(A9,n0),8,1)+1,MID(TEXT(A9,n0),9,1)+1)&IF(-MID(TEXT(A9,n0),7,3),VLOOKUP(MID(TEXT(A9,n0),9,1)*AND(MID(TEXT(A9,n0),8,1)-1),тыс,2),"")&INDEX(n_4,MID(TEXT(A9,n0),10,1)+1)&INDEX(n0x,MID(TEXT(A9,n0),11,1)+1,MID(TEXT(A9,n0),12,1)+1)),"z"," ")&IF(TRUNC(TEXT(A9,n0)),"","Ноль ")&"рубл"&VLOOKUP(MOD(MAX(MOD(MID(TEXT(A9,n0),11,2)-11,100),9),10),{0,"ь ";1,"я ";4,"ей "},2)&RIGHT(TEXT(A9,n0),2)&" копе"&VLOOKUP(MOD(MAX(MOD(RIGHT(TEXT(A9,n0),2)-11,100),9),10),{0,"йка";1,"йки";4,"ек"},2) -> Ноль рублей 00 копеек
A10: ='Акт невозврата Вышки'!BO65 -> 6600 | B10: =SUBSTITUTE(PROPER(INDEX(n_4,MID(TEXT(A10,n0),1,1)+1)&INDEX(n0x,MID(TEXT(A10,n0),2,1)+1,MID(TEXT(A10,n0),3,1)+1)&IF(-MID(TEXT(A10,n0),1,3),"миллиард"&VLOOKUP(MID(TEXT(A10,n0),3,1)*AND(MID(TEXT(A10,n0),2,1)-1),мил,2),"")&INDEX(n_4,MID(TEXT(A10,n0),4,1)+1)&INDEX(n0x,MID(TEXT(A10,n0),5,1)+1,MID(TEXT(A10,n0),6,1)+1)&IF(-MID(TEXT(A10,n0),4,3),"миллион"&VLOOKUP(MID(TEXT(A10,n0),6,1)*AND(MID(TEXT(A10,n0),5,1)-1),мил,2),"")&INDEX(n_4,MID(TEXT(A10,n0),7,1)+1)&INDEX(n1x,MID(TEXT(A10,n0),8,1)+1,MID(TEXT(A10,n0),9,1)+1)&IF(-MID(TEXT(A10,n0),7,3),VLOOKUP(MID(TEXT(A10,n0),9,1)*AND(MID(TEXT(A10,n0),8,1)-1),тыс,2),"")&INDEX(n_4,MID(TEXT(A10,n0),10,1)+1)&INDEX(n0x,MID(TEXT(A10,n0),11,1)+1,MID(TEXT(A10,n0),12,1)+1)),"z"," ")&IF(TRUNC(TEXT(A10,n0)),"","Ноль ")&"рубл"&VLOOKUP(MOD(MAX(MOD(MID(TEXT(A10,n0),11,2)-11,100),9),10),{0,"ь ";1,"я ";4,"ей "},2)&RIGHT(TEXT(A10,n0),2)&" копе"&VLOOKUP(MOD(MAX(MOD(RIGHT(TEXT(A10,n0),2)-11,100),9),10),{0,"йка";1,"йки";4,"ек"},2) -> Шесть тысяч шестьсот рублей 00 копеек
A11: ='Акт невозврата Вышки'!BO66 -> 400 | B11: =SUBSTITUTE(PROPER(INDEX(n_4,MID(TEXT(A11,n0),1,1)+1)&INDEX(n0x,MID(TEXT(A11,n0),2,1)+1,MID(TEXT(A11,n0),3,1)+1)&IF(-MID(TEXT(A11,n0),1,3),"миллиард"&VLOOKUP(MID(TEXT(A11,n0),3,1)*AND(MID(TEXT(A11,n0),2,1)-1),мил,2),"")&INDEX(n_4,MID(TEXT(A11,n0),4,1)+1)&INDEX(n0x,MID(TEXT(A11,n0),5,1)+1,MID(TEXT(A11,n0),6,1)+1)&IF(-MID(TEXT(A11,n0),4,3),"миллион"&VLOOKUP(MID(TEXT(A11,n0),6,1)*AND(MID(TEXT(A11,n0),5,1)-1),мил,2),"")&INDEX(n_4,MID(TEXT(A11,n0),7,1)+1)&INDEX(n1x,MID(TEXT(A11,n0),8,1)+1,MID(TEXT(A11,n0),9,1)+1)&IF(-MID(TEXT(A11,n0),7,3),VLOOKUP(MID(TEXT(A11,n0),9,1)*AND(MID(TEXT(A11,n0),8,1)-1),тыс,2),"")&INDEX(n_4,MID(TEXT(A11,n0),10,1)+1)&INDEX(n0x,MID(TEXT(A11,n0),11,1)+1,MID(TEXT(A11,n0),12,1)+1)),"z"," ")&IF(TRUNC(TEXT(A11,n0)),"","Ноль ")&"рубл"&VLOOKUP(MOD(MAX(MOD(MID(TEXT(A11,n0),11,2)-11,100),9),10),{0,"ь ";1,"я ";4,"ей "},2)&RIGHT(TEXT(A11,n0),2)&" копе"&VLOOKUP(MOD(MAX(MOD(RIGHT(TEXT(A11,n0),2)-11,100),9),10),{0,"йка";1,"йки";4,"ек"},2) -> Четыреста рублей 00 копеек
A12: ='Акт невозврата Вышки'!BO67 -> 0 | B12: =SUBSTITUTE(PROPER(INDEX(n_4,MID(TEXT(A12,n0),1,1)+1)&INDEX(n0x,MID(TEXT(A12,n0),2,1)+1,MID(TEXT(A12,n0),3,1)+1)&IF(-MID(TEXT(A12,n0),1,3),"миллиард"&VLOOKUP(MID(TEXT(A12,n0),3,1)*AND(MID(TEXT(A12,n0),2,1)-1),мил,2),"")&INDEX(n_4,MID(TEXT(A12,n0),4,1)+1)&INDEX(n0x,MID(TEXT(A12,n0),5,1)+1,MID(TEXT(A12,n0),6,1)+1)&IF(-MID(TEXT(A12,n0),4,3),"миллион"&VLOOKUP(MID(TEXT(A12,n0),6,1)*AND(MID(TEXT(A12,n0),5,1)-1),мил,2),"")&INDEX(n_4,MID(TEXT(A12,n0),7,1)+1)&INDEX(n1x,MID(TEXT(A12,n0),8,1)+1,MID(TEXT(A12,n0),9,1)+1)&IF(-MID(TEXT(A12,n0),7,3),VLOOKUP(MID(TEXT(A12,n0),9,1)*AND(MID(TEXT(A12,n0),8,1)-1),тыс,2),"")&INDEX(n_4,MID(TEXT(A12,n0),10,1)+1)&INDEX(n0x,MID(TEXT(A12,n0),11,1)+1,MID(TEXT(A12,n0),12,1)+1)),"z"," ")&IF(TRUNC(TEXT(A12,n0)),"","Ноль ")&"рубл"&VLOOKUP(MOD(MAX(MOD(MID(TEXT(A12,n0),11,2)-11,100),9),10),{0,"ь ";1,"я ";4,"ей "},2)&RIGHT(TEXT(A12,n0),2)&" копе"&VLOOKUP(MOD(MAX(MOD(RIGHT(TEXT(A12,n0),2)-11,100),9),10),{0,"йка";1,"йки";4,"ек"},2) -> Ноль рублей 00 копеек
A13: ='Акт невозврата Вышки'!BO72 -> 7000 | B13: =SUBSTITUTE(PROPER(INDEX(n_4,MID(TEXT(A13,n0),1,1)+1)&INDEX(n0x,MID(TEXT(A13,n0),2,1)+1,MID(TEXT(A13,n0),3,1)+1)&IF(-MID(TEXT(A13,n0),1,3),"миллиард"&VLOOKUP(MID(TEXT(A13,n0),3,1)*AND(MID(TEXT(A13,n0),2,1)-1),мил,2),"")&INDEX(n_4,MID(TEXT(A13,n0),4,1)+1)&INDEX(n0x,MID(TEXT(A13,n0),5,1)+1,MID(TEXT(A13,n0),6,1)+1)&IF(-MID(TEXT(A13,n0),4,3),"миллион"&VLOOKUP(MID(TEXT(A13,n0),6,1)*AND(MID(TEXT(A13,n0),5,1)-1),мил,2),"")&INDEX(n_4,MID(TEXT(A13,n0),7,1)+1)&INDEX(n1x,MID(TEXT(A13,n0),8,1)+1,MID(TEXT(A13,n0),9,1)+1)&IF(-MID(TEXT(A13,n0),7,3),VLOOKUP(MID(TEXT(A13,n0),9,1)*AND(MID(TEXT(A13,n0),8,1)-1),тыс,2),"")&INDEX(n_4,MID(TEXT(A13,n0),10,1)+1)&INDEX(n0x,MID(TEXT(A13,n0),11,1)+1,MID(TEXT(A13,n0),12,1)+1)),"z"," ")&IF(TRUNC(TEXT(A13,n0)),"","Ноль ")&"рубл"&VLOOKUP(MOD(MAX(MOD(MID(TEXT(A13,n0),11,2)-11,100),9),10),{0,"ь ";1,"я ";4,"ей "},2)&RIGHT(TEXT(A13,n0),2)&" копе"&VLOOKUP(MOD(MAX(MOD(RIGHT(TEXT(A13,n0),2)-11,100),9),10),{0,"йка";1,"йки";4,"ек"},2) -> Семь тысяч рублей 00 копеек
B14: =SUBSTITUTE(PROPER(INDEX(n_4,MID(TEXT(A14,n0),1,1)+1)&INDEX(n0x,MID(TEXT(A14,n0),2,1)+1,MID(TEXT(A14,n0),3,1)+1)&IF(-MID(TEXT(A14,n0),1,3),"миллиард"&VLOOKUP(MID(TEXT(A14,n0),3,1)*AND(MID(TEXT(A14,n0),2,1)-1),мил,2),"")&INDEX(n_4,MID(TEXT(A14,n0),4,1)+1)&INDEX(n0x,MID(TEXT(A14,n0),5,1)+1,MID(TEXT(A14,n0),6,1)+1)&IF(-MID(TEXT(A14,n0),4,3),"миллион"&VLOOKUP(MID(TEXT(A14,n0),6,1)*AND(MID(TEXT(A14,n0),5,1)-1),мил,2),"")&INDEX(n_4,MID(TEXT(A14,n0),7,1)+1)&INDEX(n1x,MID(TEXT(A14,n0),8,1)+1,MID(TEXT(A14,n0),9,1)+1)&IF(-MID(TEXT(A14,n0),7,3),VLOOKUP(MID(TEXT(A14,n0),9,1)*AND(MID(TEXT(A14,n0),8,1)-1),тыс,2),"")&INDEX(n_4,MID(TEXT(A14,n0),10,1)+1)&INDEX(n0x,MID(TEXT(A14,n0),11,1)+1,MID(TEXT(A14,n0),12,1)+1)),"z"," ")&IF(TRUNC(TEXT(A14,n0)),"","Ноль ")&"рубл"&VLOOKUP(MOD(MAX(MOD(MID(TEXT(A14,n0),11,2)-11,100),9),10),{0,"ь ";1,"я ";4,"ей "},2)&RIGHT(TEXT(A14,n0),2)&" копе"&VLOOKUP(MOD(MAX(MOD(RIGHT(TEXT(A14,n0),2)-11,100),9),10),{0,"йка";1,"йки";4,"ек"},2) -> Ноль рублей 00 копеек
A15: 101.2 | B15: =SUBSTITUTE(PROPER(INDEX(n_4,MID(TEXT(A15,n0),1,1)+1)&INDEX(n0x,MID(TEXT(A15,n0),2,1)+1,MID(TEXT(A15,n0),3,1)+1)&IF(-MID(TEXT(A15,n0),1,3),"миллиард"&VLOOKUP(MID(TEXT(A15,n0),3,1)*AND(MID(TEXT(A15,n0),2,1)-1),мил,2),"")&INDEX(n_4,MID(TEXT(A15,n0),4,1)+1)&INDEX(n0x,MID(TEXT(A15,n0),5,1)+1,MID(TEXT(A15,n0),6,1)+1)&IF(-MID(TEXT(A15,n0),4,3),"миллион"&VLOOKUP(MID(TEXT(A15,n0),6,1)*AND(MID(TEXT(A15,n0),5,1)-1),мил,2),"")&INDEX(n_4,MID(TEXT(A15,n0),7,1)+1)&INDEX(n1x,MID(TEXT(A15,n0),8,1)+1,MID(TEXT(A15,n0),9,1)+1)&IF(-MID(TEXT(A15,n0),7,3),VLOOKUP(MID(TEXT(A15,n0),9,1)*AND(MID(TEXT(A15,n0),8,1)-1),тыс,2),"")&INDEX(n_4,MID(TEXT(A15,n0),10,1)+1)&INDEX(n0x,MID(TEXT(A15,n0),11,1)+1,MID(TEXT(A15,n0),12,1)+1)),"z"," ")&IF(TRUNC(TEXT(A15,n0)),"","Ноль ")&"рубл"&VLOOKUP(MOD(MAX(MOD(MID(TEXT(A15,n0),11,2)-11,100),9),10),{0,"ь ";1,"я ";4,"ей "},2)&RIGHT(TEXT(A15,n0),2)&" копе"&VLOOKUP(MOD(MAX(MOD(RIGHT(TEXT(A15,n0),2)-11,100),9),10),{0,"йка";1,"йки";4,"ек"},2) -> Сто один рубль 20 копеек
A16: 121.22 | B16: =SUBSTITUTE(PROPER(INDEX(n_4,MID(TEXT(A16,n0),1,1)+1)&INDEX(n0x,MID(TEXT(A16,n0),2,1)+1,MID(TEXT(A16,n0),3,1)+1)&IF(-MID(TEXT(A16,n0),1,3),"миллиард"&VLOOKUP(MID(TEXT(A16,n0),3,1)*AND(MID(TEXT(A16,n0),2,1)-1),мил,2),"")&INDEX(n_4,MID(TEXT(A16,n0),4,1)+1)&INDEX(n0x,MID(TEXT(A16,n0),5,1)+1,MID(TEXT(A16,n0),6,1)+1)&IF(-MID(TEXT(A16,n0),4,3),"миллион"&VLOOKUP(MID(TEXT(A16,n0),6,1)*AND(MID(TEXT(A16,n0),5,1)-1),мил,2),"")&INDEX(n_4,MID(TEXT(A16,n0),7,1)+1)&INDEX(n1x,MID(TEXT(A16,n0),8,1)+1,MID(TEXT(A16,n0),9,1)+1)&IF(-MID(TEXT(A16,n0),7,3),VLOOKUP(MID(TEXT(A16,n0),9,1)*AND(MID(TEXT(A16,n0),8,1)-1),тыс,2),"")&INDEX(n_4,MID(TEXT(A16,n0),10,1)+1)&INDEX(n0x,MID(TEXT(A16,n0),11,1)+1,MID(TEXT(A16,n0),12,1)+1)),"z"," ")&IF(TRUNC(TEXT(A16,n0)),"","Ноль ")&"рубл"&VLOOKUP(MOD(MAX(MOD(MID(TEXT(A16,n0),11,2)-11,100),9),10),{0,"ь ";1,"я ";4,"ей "},2)&RIGHT(TEXT(A16,n0),2)&" копе"&VLOOKUP(MOD(MAX(MOD(RIGHT(TEXT(A16,n0),2)-11,100),9),10),{0,"йка";1,"йки";4,"ек"},2) -> Сто двадцать один рубль 22 копейки
A17: 1000.16 | B17: =SUBSTITUTE(PROPER(INDEX(n_4,MID(TEXT(A17,n0),1,1)+1)&INDEX(n0x,MID(TEXT(A17,n0),2,1)+1,MID(TEXT(A17,n0),3,1)+1)&IF(-MID(TEXT(A17,n0),1,3),"миллиард"&VLOOKUP(MID(TEXT(A17,n0),3,1)*AND(MID(TEXT(A17,n0),2,1)-1),мил,2),"")&INDEX(n_4,MID(TEXT(A17,n0),4,1)+1)&INDEX(n0x,MID(TEXT(A17,n0),5,1)+1,MID(TEXT(A17,n0),6,1)+1)&IF(-MID(TEXT(A17,n0),4,3),"миллион"&VLOOKUP(MID(TEXT(A17,n0),6,1)*AND(MID(TEXT(A17,n0),5,1)-1),мил,2),"")&INDEX(n_4,MID(TEXT(A17,n0),7,1)+1)&INDEX(n1x,MID(TEXT(A17,n0),8,1)+1,MID(TEXT(A17,n0),9,1)+1)&IF(-MID(TEXT(A17,n0),7,3),VLOOKUP(MID(TEXT(A17,n0),9,1)*AND(MID(TEXT(A17,n0),8,1)-1),тыс,2),"")&INDEX(n_4,MID(TEXT(A17,n0),10,1)+1)&INDEX(n0x,MID(TEXT(A17,n0),11,1)+1,MID(TEXT(A17,n0),12,1)+1)),"z"," ")&IF(TRUNC(TEXT(A17,n0)),"","Ноль ")&"рубл"&VLOOKUP(MOD(MAX(MOD(MID(TEXT(A17,n0),11,2)-11,100),9),10),{0,"ь ";1,"я ";4,"ей "},2)&RIGHT(TEXT(A17,n0),2)&" копе"&VLOOKUP(MOD(MAX(MOD(RIGHT(TEXT(A17,n0),2)-11,100),9),10),{0,"йка";1,"йки";4,"ек"},2) -> Одна тысяча рублей 16 копеек
A18: 1002.51 | B18: =SUBSTITUTE(PROPER(INDEX(n_4,MID(TEXT(A18,n0),1,1)+1)&INDEX(n0x,MID(TEXT(A18,n0),2,1)+1,MID(TEXT(A18,n0),3,1)+1)&IF(-MID(TEXT(A18,n0),1,3),"миллиард"&VLOOKUP(MID(TEXT(A18,n0),3,1)*AND(MID(TEXT(A18,n0),2,1)-1),мил,2),"")&INDEX(n_4,MID(TEXT(A18,n0),4,1)+1)&INDEX(n0x,MID(TEXT(A18,n0),5,1)+1,MID(TEXT(A18,n0),6,1)+1)&IF(-MID(TEXT(A18,n0),4,3),"миллион"&VLOOKUP(MID(TEXT(A18,n0),6,1)*AND(MID(TEXT(A18,n0),5,1)-1),мил,2),"")&INDEX(n_4,MID(TEXT(A18,n0),7,1)+1)&INDEX(n1x,MID(TEXT(A18,n0),8,1)+1,MID(TEXT(A18,n0),9,1)+1)&IF(-MID(TEXT(A18,n0),7,3),VLOOKUP(MID(TEXT(A18,n0),9,1)*AND(MID(TEXT(A18,n0),8,1)-1),тыс,2),"")&INDEX(n_4,MID(TEXT(A18,n0),10,1)+1)&INDEX(n0x,MID(TEXT(A18,n0),11,1)+1,MID(TEXT(A18,n0),12,1)+1)),"z"," ")&IF(TRUNC(TEXT(A18,n0)),"","Ноль ")&"рубл"&VLOOKUP(MOD(MAX(MOD(MID(TEXT(A18,n0),11,2)-11,100),9),10),{0,"ь ";1,"я ";4,"ей "},2)&RIGHT(TEXT(A18,n0),2)&" копе"&VLOOKUP(MOD(MAX(MOD(RIGHT(TEXT(A18,n0),2)-11,100),9),10),{0,"йка";1,"йки";4,"ек"},2) -> Одна тысяча два рубля 51 копейка
A19: 120101.1 | B19: =SUBSTITUTE(PROPER(INDEX(n_4,MID(TEXT(A19,n0),1,1)+1)&INDEX(n0x,MID(TEXT(A19,n0),2,1)+1,MID(TEXT(A19,n0),3,1)+1)&IF(-MID(TEXT(A19,n0),1,3),"миллиард"&VLOOKUP(MID(TEXT(A19,n0),3,1)*AND(MID(TEXT(A19,n0),2,1)-1),мил,2),"")&INDEX(n_4,MID(TEXT(A19,n0),4,1)+1)&INDEX(n0x,MID(TEXT(A19,n0),5,1)+1,MID(TEXT(A19,n0),6,1)+1)&IF(-MID(TEXT(A19,n0),4,3),"миллион"&VLOOKUP(MID(TEXT(A19,n0),6,1)*AND(MID(TEXT(A19,n0),5,1)-1),мил,2),"")&INDEX(n_4,MID(TEXT(A19,n0),7,1)+1)&INDEX(n1x,MID(TEXT(A19,n0),8,1)+1,MID(TEXT(A19,n0),9,1)+1)&IF(-MID(TEXT(A19,n0),7,3),VLOOKUP(MID(TEXT(A19,n0),9,1)*AND(MID(TEXT(A19,n0),8,1)-1),тыс,2),"")&INDEX(n_4,MID(TEXT(A19,n0),10,1)+1)&INDEX(n0x,MID(TEXT(A19,n0),11,1)+1,MID(TEXT(A19,n0),12,1)+1)),"z"," ")&IF(TRUNC(TEXT(A19,n0)),"","Ноль ")&"рубл"&VLOOKUP(MOD(MAX(MOD(MID(TEXT(A19,n0),11,2)-11,100),9),10),{0,"ь ";1,"я ";4,"ей "},2)&RIGHT(TEXT(A19,n0),2)&" копе"&VLOOKUP(MOD(MAX(MOD(RIGHT(TEXT(A19,n0),2)-11,100),9),10),{0,"йка";1,"йки";4,"ек"},2) -> Сто двадцать тысяч сто один рубль 10 копеек
A20: 2000000 | B20: =SUBSTITUTE(PROPER(INDEX(n_4,MID(TEXT(A20,n0),1,1)+1)&INDEX(n0x,MID(TEXT(A20,n0),2,1)+1,MID(TEXT(A20,n0),3,1)+1)&IF(-MID(TEXT(A20,n0),1,3),"миллиард"&VLOOKUP(MID(TEXT(A20,n0),3,1)*AND(MID(TEXT(A20,n0),2,1)-1),мил,2),"")&INDEX(n_4,MID(TEXT(A20,n0),4,1)+1)&INDEX(n0x,MID(TEXT(A20,n0),5,1)+1,MID(TEXT(A20,n0),6,1)+1)&IF(-MID(TEXT(A20,n0),4,3),"миллион"&VLOOKUP(MID(TEXT(A20,n0),6,1)*AND(MID(TEXT(A20,n0),5,1)-1),мил,2),"")&INDEX(n_4,MID(TEXT(A20,n0),7,1)+1)&INDEX(n1x,MID(TEXT(A20,n0),8,1)+1,MID(TEXT(A20,n0),9,1)+1)&IF(-MID(TEXT(A20,n0),7,3),VLOOKUP(MID(TEXT(A20,n0),9,1)*AND(MID(TEXT(A20,n0),8,1)-1),тыс,2),"")&INDEX(n_4,MID(TEXT(A20,n0),10,1)+1)&INDEX(n0x,MID(TEXT(A20,n0),11,1)+1,MID(TEXT(A20,n0),12,1)+1)),"z"," ")&IF(TRUNC(TEXT(A20,n0)),"","Ноль ")&"рубл"&VLOOKUP(MOD(MAX(MOD(MID(TEXT(A20,n0),11,2)-11,100),9),10),{0,"ь ";1,"я ";4,"ей "},2)&RIGHT(TEXT(A20,n0),2)&" копе"&VLOOKUP(MOD(MAX(MOD(RIGHT(TEXT(A20,n0),2)-11,100),9),10),{0,"йка";1,"йки";4,"ек"},2) -> Два миллиона рублей 00 копеек
A21: 11102345 | B21: =SUBSTITUTE(PROPER(INDEX(n_4,MID(TEXT(A21,n0),1,1)+1)&INDEX(n0x,MID(TEXT(A21,n0),2,1)+1,MID(TEXT(A21,n0),3,1)+1)&IF(-MID(TEXT(A21,n0),1,3),"миллиард"&VLOOKUP(MID(TEXT(A21,n0),3,1)*AND(MID(TEXT(A21,n0),2,1)-1),мил,2),"")&INDEX(n_4,MID(TEXT(A21,n0),4,1)+1)&INDEX(n0x,MID(TEXT(A21,n0),5,1)+1,MID(TEXT(A21,n0),6,1)+1)&IF(-MID(TEXT(A21,n0),4,3),"миллион"&VLOOKUP(MID(TEXT(A21,n0),6,1)*AND(MID(TEXT(A21,n0),5,1)-1),мил,2),"")&INDEX(n_4,MID(TEXT(A21,n0),7,1)+1)&INDEX(n1x,MID(TEXT(A21,n0),8,1)+1,MID(TEXT(A21,n0),9,1)+1)&IF(-MID(TEXT(A21,n0),7,3),VLOOKUP(MID(TEXT(A21,n0),9,1)*AND(MID(TEXT(A21,n0),8,1)-1),тыс,2),"")&INDEX(n_4,MID(TEXT(A21,n0),10,1)+1)&INDEX(n0x,MID(TEXT(A21,n0),11,1)+1,MID(TEXT(A21,n0),12,1)+1)),"z"," ")&IF(TRUNC(TEXT(A21,n0)),"","Ноль ")&"рубл"&VLOOKUP(MOD(MAX(MOD(MID(TEXT(A21,n0),11,2)-11,100),9),10),{0,"ь ";1,"я ";4,"ей "},2)&RIGHT(TEXT(A21,n0),2)&" копе"&VLOOKUP(MOD(MAX(MOD(RIGHT(TEXT(A21,n0),2)-11,100),9),10),{0,"йка";1,"йки";4,"ек"},2) -> Одиннадцать миллионов сто две тысячи триста сорок пять рублей 23 копейки
A22: 1.2345679e+08 | B22: =SUBSTITUTE(PROPER(INDEX(n_4,MID(TEXT(A22,n0),1,1)+1)&INDEX(n0x,MID(TEXT(A22,n0),2,1)+1,MID(TEXT(A22,n0),3,1)+1)&IF(-MID(TEXT(A22,n0),1,3),"миллиард"&VLOOKUP(MID(TEXT(A22,n0),3,1)*AND(MID(TEXT(A22,n0),2,1)-1),мил,2),"")&INDEX(n_4,MID(TEXT(A22,n0),4,1)+1)&INDEX(n0x,MID(TEXT(A22,n0),5,1)+1,MID(TEXT(A22,n0),6,1)+1)&IF(-MID(TEXT(A22,n0),4,3),"миллион"&VLOOKUP(MID(TEXT(A22,n0),6,1)*AND(MID(TEXT(A22,n0),5,1)-1),мил,2),"")&INDEX(n_4,MID(TEXT(A22,n0),7,1)+1)&INDEX(n1x,MID(TEXT(A22,n0),8,1)+1,MID(TEXT(A22,n0),9,1)+1)&IF(-MID(TEXT(A22,n0),7,3),VLOOKUP(MID(TEXT(A22,n0),9,1)*AND(MID(TEXT(A22,n0),8,1)-1),тыс,2),"")&INDEX(n_4,MID(TEXT(A22,n0),10,1)+1)&INDEX(n0x,MID(TEXT(A22,n0),11,1)+1,MID(TEXT(A22,n0),12,1)+1)),"z"," ")&IF(TRUNC(TEXT(A22,n0)),"","Ноль ")&"рубл"&VLOOKUP(MOD(MAX(MOD(MID(TEXT(A22,n0),11,2)-11,100),9),10),{0,"ь ";1,"я ";4,"ей "},2)&RIGHT(TEXT(A22,n0),2)&" копе"&VLOOKUP(MOD(MAX(MOD(RIGHT(TEXT(A22,n0),2)-11,100),9),10),{0,"йка";1,"йки";4,"ек"},2) -> Сто двадцать три миллиона четыреста пятьдесят шесть тысяч семьсот восемьдесят девять рублей 32 копейки
A24: Случайные числа:
A25: =ROUND((RAND()*1000000),2) -> 943103.78 | B25: =SUBSTITUTE(PROPER(INDEX(n_4,MID(TEXT(A25,n0),1,1)+1)&INDEX(n0x,MID(TEXT(A25,n0),2,1)+1,MID(TEXT(A25,n0),3,1)+1)&IF(-MID(TEXT(A25,n0),1,3),"миллиард"&VLOOKUP(MID(TEXT(A25,n0),3,1)*AND(MID(TEXT(A25,n0),2,1)-1),мил,2),"")&INDEX(n_4,MID(TEXT(A25,n0),4,1)+1)&INDEX(n0x,MID(TEXT(A25,n0),5,1)+1,MID(TEXT(A25,n0),6,1)+1)&IF(-MID(TEXT(A25,n0),4,3),"миллион"&VLOOKUP(MID(TEXT(A25,n0),6,1)*AND(MID(TEXT(A25,n0),5,1)-1),мил,2),"")&INDEX(n_4,MID(TEXT(A25,n0),7,1)+1)&INDEX(n1x,MID(TEXT(A25,n0),8,1)+1,MID(TEXT(A25,n0),9,1)+1)&IF(-MID(TEXT(A25,n0),7,3),VLOOKUP(MID(TEXT(A25,n0),9,1)*AND(MID(TEXT(A25,n0),8,1)-1),тыс,2),"")&INDEX(n_4,MID(TEXT(A25,n0),10,1)+1)&INDEX(n0x,MID(TEXT(A25,n0),11,1)+1,MID(TEXT(A25,n0),12,1)+1)),"z"," ")&IF(TRUNC(TEXT(A25,n0)),"","Ноль ")&"рубл"&VLOOKUP(MOD(MAX(MOD(MID(TEXT(A25,n0),11,2)-11,100),9),10),{0,"ь ";1,"я ";4,"ей "},2)&RIGHT(TEXT(A25,n0),2)&" копе"&VLOOKUP(MOD(MAX(MOD(RIGHT(TEXT(A25,n0),2)-11,100),9),10),{0,"йка";1,"йки";4,"ек"},2) -> Девятьсот сорок три тысячи сто три рубля 78 копеек
A26: =ROUND((RAND()*10000000),2) -> 2279588.3 | B26: =SUBSTITUTE(PROPER(INDEX(n_4,MID(TEXT(A26,n0),1,1)+1)&INDEX(n0x,MID(TEXT(A26,n0),2,1)+1,MID(TEXT(A26,n0),3,1)+1)&IF(-MID(TEXT(A26,n0),1,3),"миллиард"&VLOOKUP(MID(TEXT(A26,n0),3,1)*AND(MID(TEXT(A26,n0),2,1)-1),мил,2),"")&INDEX(n_4,MID(TEXT(A26,n0),4,1)+1)&INDEX(n0x,MID(TEXT(A26,n0),5,1)+1,MID(TEXT(A26,n0),6,1)+1)&IF(-MID(TEXT(A26,n0),4,3),"миллион"&VLOOKUP(MID(TEXT(A26,n0),6,1)*AND(MID(TEXT(A26,n0),5,1)-1),мил,2),"")&INDEX(n_4,MID(TEXT(A26,n0),7,1)+1)&INDEX(n1x,MID(TEXT(A26,n0),8,1)+1,MID(TEXT(A26,n0),9,1)+1)&IF(-MID(TEXT(A26,n0),7,3),VLOOKUP(MID(TEXT(A26,n0),9,1)*AND(MID(TEXT(A26,n0),8,1)-1),тыс,2),"")&INDEX(n_4,MID(TEXT(A26,n0),10,1)+1)&INDEX(n0x,MID(TEXT(A26,n0),11,1)+1,MID(TEXT(A26,n0),12,1)+1)),"z"," ")&IF(TRUNC(TEXT(A26,n0)),"","Ноль ")&"рубл"&VLOOKUP(MOD(MAX(MOD(MID(TEXT(A26,n0),11,2)-11,100),9),10),{0,"ь ";1,"я ";4,"ей "},2)&RIGHT(TEXT(A26,n0),2)&" копе"&VLOOKUP(MOD(MAX(MOD(RIGHT(TEXT(A26,n0),2)-11,100),9),10),{0,"йка";1,"йки";4,"ек"},2) -> Два миллиона двести семьдесят девять тысяч пятьсот восемьдесят восемь рублей 29 копеек
A27: =ROUND((RAND()*100000000),2) -> 85104982 | B27: =SUBSTITUTE(PROPER(INDEX(n_4,MID(TEXT(A27,n0),1,1)+1)&INDEX(n0x,MID(TEXT(A27,n0),2,1)+1,MID(TEXT(A27,n0),3,1)+1)&IF(-MID(TEXT(A27,n0),1,3),"миллиард"&VLOOKUP(MID(TEXT(A27,n0),3,1)*AND(MID(TEXT(A27,n0),2,1)-1),мил,2),"")&INDEX(n_4,MID(TEXT(A27,n0),4,1)+1)&INDEX(n0x,MID(TEXT(A27,n0),5,1)+1,MID(TEXT(A27,n0),6,1)+1)&IF(-MID(TEXT(A27,n0),4,3),"миллион"&VLOOKUP(MID(TEXT(A27,n0),6,1)*AND(MID(TEXT(A27,n0),5,1)-1),мил,2),"")&INDEX(n_4,MID(TEXT(A27,n0),7,1)+1)&INDEX(n1x,MID(TEXT(A27,n0),8,1)+1,MID(TEXT(A27,n0),9,1)+1)&IF(-MID(TEXT(A27,n0),7,3),VLOOKUP(MID(TEXT(A27,n0),9,1)*AND(MID(TEXT(A27,n0),8,1)-1),тыс,2),"")&INDEX(n_4,MID(TEXT(A27,n0),10,1)+1)&INDEX(n0x,MID(TEXT(A27,n0),11,1)+1,MID(TEXT(A27,n0),12,1)+1)),"z"," ")&IF(TRUNC(TEXT(A27,n0)),"","Ноль ")&"рубл"&VLOOKUP(MOD(MAX(MOD(MID(TEXT(A27,n0),11,2)-11,100),9),10),{0,"ь ";1,"я ";4,"ей "},2)&RIGHT(TEXT(A27,n0),2)&" копе"&VLOOKUP(MOD(MAX(MOD(RIGHT(TEXT(A27,n0),2)-11,100),9),10),{0,"йка";1,"йки";4,"ек"},2) -> Восемьдесят пять миллионов сто четыре тысячи девятьсот восемьдесят один рубль 64 копейки
A28: =ROUND((RAND()*1000000000),2) -> 9.6478509e+08 | B28: =SUBSTITUTE(PROPER(INDEX(n_4,MID(TEXT(A28,n0),1,1)+1)&INDEX(n0x,MID(TEXT(A28,n0),2,1)+1,MID(TEXT(A28,n0),3,1)+1)&IF(-MID(TEXT(A28,n0),1,3),"миллиард"&VLOOKUP(MID(TEXT(A28,n0),3,1)*AND(MID(TEXT(A28,n0),2,1)-1),мил,2),"")&INDEX(n_4,MID(TEXT(A28,n0),4,1)+1)&INDEX(n0x,MID(TEXT(A28,n0),5,1)+1,MID(TEXT(A28,n0),6,1)+1)&IF(-MID(TEXT(A28,n0),4,3),"миллион"&VLOOKUP(MID(TEXT(A28,n0),6,1)*AND(MID(TEXT(A28,n0),5,1)-1),мил,2),"")&INDEX(n_4,MID(TEXT(A28,n0),7,1)+1)&INDEX(n1x,MID(TEXT(A28,n0),8,1)+1,MID(TEXT(A28,n0),9,1)+1)&IF(-MID(TEXT(A28,n0),7,3),VLOOKUP(MID(TEXT(A28,n0),9,1)*AND(MID(TEXT(A28,n0),8,1)-1),тыс,2),"")&INDEX(n_4,MID(TEXT(A28,n0),10,1)+1)&INDEX(n0x,MID(TEXT(A28,n0),11,1)+1,MID(TEXT(A28,n0),12,1)+1)),"z"," ")&IF(TRUNC(TEXT(A28,n0)),"","Ноль ")&"рубл"&VLOOKUP(MOD(MAX(MOD(MID(TEXT(A28,n0),11,2)-11,100),9),10),{0,"ь ";1,"я ";4,"ей "},2)&RIGHT(TEXT(A28,n0),2)&" копе"&VLOOKUP(MOD(MAX(MOD(RIGHT(TEXT(A28,n0),2)-11,100),9),10),{0,"йка";1,"йки";4,"ек"},2) -> Девятьсот шестьдесят четыре миллиона семьсот восемьдесят пять тысяч девяносто рублей 11 копеек
A29: =ROUND((RAND()*1000000000000),2) -> 3.4054857e+11 | B29: =SUBSTITUTE(PROPER(INDEX(n_4,MID(TEXT(A29,n0),1,1)+1)&INDEX(n0x,MID(TEXT(A29,n0),2,1)+1,MID(TEXT(A29,n0),3,1)+1)&IF(-MID(TEXT(A29,n0),1,3),"миллиард"&VLOOKUP(MID(TEXT(A29,n0),3,1)*AND(MID(TEXT(A29,n0),2,1)-1),мил,2),"")&INDEX(n_4,MID(TEXT(A29,n0),4,1)+1)&INDEX(n0x,MID(TEXT(A29,n0),5,1)+1,MID(TEXT(A29,n0),6,1)+1)&IF(-MID(TEXT(A29,n0),4,3),"миллион"&VLOOKUP(MID(TEXT(A29,n0),6,1)*AND(MID(TEXT(A29,n0),5,1)-1),мил,2),"")&INDEX(n_4,MID(TEXT(A29,n0),7,1)+1)&INDEX(n1x,MID(TEXT(A29,n0),8,1)+1,MID(TEXT(A29,n0),9,1)+1)&IF(-MID(TEXT(A29,n0),7,3),VLOOKUP(MID(TEXT(A29,n0),9,1)*AND(MID(TEXT(A29,n0),8,1)-1),тыс,2),"")&INDEX(n_4,MID(TEXT(A29,n0),10,1)+1)&INDEX(n0x,MID(TEXT(A29,n0),11,1)+1,MID(TEXT(A29,n0),12,1)+1)),"z"," ")&IF(TRUNC(TEXT(A29,n0)),"","Ноль ")&"рубл"&VLOOKUP(MOD(MAX(MOD(MID(TEXT(A29,n0),11,2)-11,100),9),10),{0,"ь ";1,"я ";4,"ей "},2)&RIGHT(TEXT(A29,n0),2)&" копе"&VLOOKUP(MOD(MAX(MOD(RIGHT(TEXT(A29,n0),2)-11,100),9),10),{0,"йка";1,"йки";4,"ек"},2) -> Триста сорок миллиардов пятьсот сорок восемь миллионов пятьсот шестьдесят семь тысяч восемьсот двадцать семь рублей 94 копейки
A31: Формула РУС: | B31: =ПОДСТАВИТЬ(ПРОПНАЧ(ИНДЕКС(n_4;ПСТР(ТЕКСТ(A1;n0);1;1)+1)&ИНДЕКС(n0x;ПСТР(ТЕКСТ(A1;n0);2;1)+1;ПСТР(ТЕКСТ(A1;n0);3;1)+1)&ЕСЛИ(-ПСТР(ТЕКСТ(A1;n0);1;3);"миллиард"&ВПР(ПСТР(ТЕКСТ(A1;n0);3;1)*И(ПСТР(ТЕКСТ(A1;n0);2;1)-1);мил;2);"")&ИНДЕКС(n_4;ПСТР(ТЕКСТ(A1;n0);4;1)+1)&ИНДЕКС(n0x;ПСТР(ТЕКСТ(A1;n0);5;1)+1;ПСТР(ТЕКСТ(A1;n0);6;1)+1)&ЕСЛИ(-ПСТР(ТЕКСТ(A1;n0);4;3);"миллион"&ВПР(ПСТР(ТЕКСТ(A1;n0);6;1)*И(ПСТР(ТЕКСТ(A1;n0);5;1)-1);мил;2);"")&ИНДЕКС(n_4;ПСТР(ТЕКСТ(A1;n0);7;1)+1)&ИНДЕКС(n1x;ПСТР(ТЕКСТ(A1;n0);8;1)+1;ПСТР(ТЕКСТ(A1;n0);9;1)+1)&ЕСЛИ(-ПСТР(ТЕКСТ(A1;n0);7;3);ВПР(ПСТР(ТЕКСТ(A1;n0);9;1)*И(ПСТР(ТЕКСТ(A1;n0);8;1)-1);тыс;2);"")&ИНДЕКС(n_4;ПСТР(ТЕКСТ(A1;n0);10;1)+1)&ИНДЕКС(n0x;ПСТР(ТЕКСТ(A1;n0);11;1)+1;ПСТР(ТЕКСТ(A1;n0);12;1)+1));"z";" ")&ЕСЛИ(ОТБР(ТЕКСТ(A1;n0));"";"Ноль ")&"рубл"&ВПР(ОСТАТ(МАКС(ОСТАТ(ПСТР(ТЕКСТ(A1;n0);11;2)-11;100);9);10);{0;"ь ":1;"я ":4;"ей "};2)&ПРАВСИМВ(ТЕКСТ(A1;n0);2)&" копе"&ВПР(ОСТАТ(МАКС(ОСТАТ(ПРАВСИМВ(ТЕКСТ(A1;n0);2)-11;100);9);10);{0;"йка":1;"йки":4;"ек"};2)
A32: Длина: | B32: =LEN(B31) -> 986
A33: Формула ENG: | B33: =SUBSTITUTE(PROPER(INDEX(n_4,MID(TEXT(A1,n0),1,1)+1)&INDEX(n0x,MID(TEXT(A1,n0),2,1)+1,MID(TEXT(A1,n0),3,1)+1)&IF(-MID(TEXT(A1,n0),1,3),"миллиард"&VLOOKUP(MID(TEXT(A1,n0),3,1)*AND(MID(TEXT(A1,n0),2,1)-1),мил,2),"")&INDEX(n_4,MID(TEXT(A1,n0),4,1)+1)&INDEX(n0x,MID(TEXT(A1,n0),5,1)+1,MID(TEXT(A1,n0),6,1)+1)&IF(-MID(TEXT(A1,n0),4,3),"миллион"&VLOOKUP(MID(TEXT(A1,n0),6,1)*AND(MID(TEXT(A1,n0),5,1)-1),мил,2),"")&INDEX(n_4,MID(TEXT(A1,n0),7,1)+1)&INDEX(n1x,MID(TEXT(A1,n0),8,1)+1,MID(TEXT(A1,n0),9,1)+1)&IF(-MID(TEXT(A1,n0),7,3),VLOOKUP(MID(TEXT(A1,n0),9,1)*AND(MID(TEXT(A1,n0),8,1)-1),тыс,2),"")&INDEX(n_4,MID(TEXT(A1,n0),10,1)+1)&INDEX(n0x,MID(TEXT(A1,n0),11,1)+1,MID(TEXT(A1,n0),12,1)+1)),"z"," ")&IF(TRUNC(TEXT(A1,n0)),"","Ноль ")&"рубл"&VLOOKUP(MOD(MAX(MOD(MID(TEXT(A1,n0),11,2)-11,100),9),10),{0,"ь ";1,"я ";4,"ей "},2)&RIGHT(TEXT(A1,n0),2)&" копе"&VLOOKUP(MOD(MAX(MOD(RIGHT(TEXT(A1,n0),2)-11,100),9),10),{0,"йка";1,"йки";4,"ек"},2)
A34: Длина: | B34: =LEN(B33) -> 933
A36: Имена: | B36: n_1 | C36: ={"";"одинz";"дваz";"триz";"четыреz";"пятьz";"шестьz";"семьz";"восемьz";"девятьz"}
B37: n_2 | C37: ={"десятьz";"одиннадцатьz";"двенадцатьz";"тринадцатьz";"четырнадцатьz";"пятнадцатьz";"шестнадцатьz";"семнадцатьz";"восемнадцатьz";"девятнадцатьz"}
B38: n_3 | C38: ={"":1:"двадцатьz":"тридцатьz":"сорокz":"пятьдесятz":"шестьдесятz":"семьдесятz":"восемьдесятz":"девяностоz"}
B39: n_4 | C39: ={"";"стоz";"двестиz";"тристаz";"четырестаz";"пятьсотz";"шестьсотz";"семьсотz";"восемьсотz";"девятьсотz"}
B40: n_5 | C40: ={"";"однаz";"двеz";"триz";"четыреz";"пятьz";"шестьz";"семьz";"восемьz";"девятьz"}
B41: n0 | C41: ="000000000000"&ПСТР(1/2;2;1)&"00"
B42: n0x | C42: =ЕСЛИ(n_3=1;n_2;n_3&n_1)
B43: n1x | C43: =ЕСЛИ(n_3=1;n_2;n_3&n_5)
B44: мил | C44: ={0;"овz":1;"z":2;"аz":5;"овz"}
B45: тыс | C45: ={0;"тысячz":1;"тысячаz":2;"тысячиz":5;"тысячz"}

Sheet расценки
M2: Испр. От 31.01.2017
B3: Кол-во метров/ срок аренды | C3: До недели | D3: До 2-х недель | E3: До месяца | F3: До 45дн | G3: До 2-х месяцев | H3: Св 2 месяцев | N3: Кол-во метров/ срок аренды | O3: До 3-х дней | P3: До недели | Q3: До 2-х недель | R3: До месяца | S3: До 45дн | T3: До 2-х месяцев | U3: Св 2 месяцев
A4: 1 | B4: До 50м2 | C4: 5 | D4: 3.5 | E4: 3 | F4: 2.5 | G4: 2 | H4: 1.8 | M4: 1 | N4: До 50м2 | O4: 10 | P4: 6 | Q4: 4.5 | R4: 3.2 | S4: 2.5 | T4: 2 | U4: 1.6
A5: 2 | B5: До 100м2 | C5: 4.5 | D5: 3 | E5: 2.5 | F5: 2 | G5: 1.8 | H5: 1.6 | M5: 2 | N5: До 100м2 | O5: 8 | P5: 5 | Q5: 3.7 | R5: 2.7 | S5: 2 | T5: 1.65 | U5: 1.4
A6: 3 | B6: До 300м2 | C6: 3.5 | D6: 2.5 | E6: 2.1 | F6: 1.8 | G6: 1.6 | H6: 1.4 | M6: 3 | N6: До 300м2 | O6: 5 | P6: 4 | Q6: 2.8 | R6: 2.1 | S6: 1.7 | T6: 1.45 | U6: 1.25
A7: 4 | B7: До 500м2 | C7: 3 | D7: 2 | E7: 1.7 | F7: 1.6 | G7: 1.4 | H7: 1.2 | M7: 4 | N7: До 500м2 | P7: 3 | Q7: 2 | R7: 1.65 | S7: 1.5 | T7: 1.3 | U7: 1.1
A8: 5 | B8: До 1000м2 | C8: 2.5 | D8: 1.75 | E8: 1.5 | F8: 1.4 | G8: 1.2 | H8: 1.1 | M8: 5 | N8: До 1000м2 | P8: 2.5 | Q8: 1.7 | R8: 1.4 | S8: 1.25 | T8: 1.1 | U8: 1
A9: 6 | B9: Св 1000м2 | C9: 2.2 | D9: 1.5 | E9: 1.3 | F9: 1.2 | G9: 1.1 | H9: 1 | M9: 6 | N9: Св 1000м2 | P9: 2 | Q9: 1.5 | R9: 1.25 | S9: 1.1 | T9: 1 | U9: 0.9
A11: Подмости | B11: шт (3м*1м) | C11: 25 | D11: 18 | E11: 15 | F11: 13 | G11: 11 | H11: 10 | M11: Подмости | N11: шт (3м*1м) | O11: 40 | P11: 25 | Q11: 18 | R11: 15 | S11: 12.5 | T11: 10 | U11: 8
B13: Кол-во метров/ срок аренды | C13: До 4-х дней | D13: До недели | E13: До 2-х недель | F13: До месяца | G13: До 45дн | H13: До 2-х месяцев | I13: Св 2 месяцев
A14: Вышка-тура | B14: до 6,29м | C14: 500 | D14: 350 | E14: 300 | F14: 250 | G14: 220 | H14: 200 | I14: 190
A15: Вышка-тура | B15: до 9,89м | C15: 550 | D15: 400 | E15: 350 | F15: 290 | G15: 270 | H15: 240 | I15: 220
A16: Вышка-тура | B16: св 9,89м | C16: 650 | D16: 500 | E16: 450 | F16: 390 | G16: 370 | H16: 330 | I16: 300
C17: 3 | D17: 7 | E17: 14 | F17: 30 | G17: 45 | H17: 60 | I17: 60
A19: Залог | B19: 100 руб за 1 м2

Sheet ремонт
B2: Кол-во | E2: Стоимость ремонта
A3: Диагональ | B3: 0 | E3: Диагоналей | G3: =B3*C11 -> 0
A4: Горизонталь | B4: 200 | E4: Горизонталей | G4: =B4*C12 -> 9000
A5: Рам | B5: 0 | E5: Рам | G5: =B5*C13 -> 0
A6: Стоимость смены | B6: 1500 | C6: =B6*1.42 -> 2130 | E6: Сумма | G6: =SUM(G3:G5) -> 9000
A7: Кол-во часов в смене | B7: 7.15
A10: Стоимость ремонта 1 шт
A11: Диагонали | B11: =C6/B15 -> 85.2 | C11: 90 | E11: 30
A12: Горизонтали | B12: =C6/B16 -> 42.6 | C12: 45 | E12: 10
A13: Рам | B13: 0 | C13: 0
A14: Кол-во рем в смену | B14: шт
A15: Диагонали | B15: 25
A16: Горизонтали | B16: 50

Sheet Сдача
A1: Сегодня | B1: =TODAY() -> 45015 | N1: Оплачено | O1: =6900+5600 -> 12500
F2: Рама прох | G2: Рама лестн | H2: Диагональ | I2: Гориз-ль | J2: Щит | K2: Ригель
B3: Начало аренды | E3: цена за 1 шт | F3: ='Договор аренды лесов Юр'!AU141 -> 9.7 | G3: ='Договор аренды лесов Юр'!AU142 -> 11.5 | H3: ='Договор аренды лесов Юр'!AU143 -> 4.3 | I3: ='Договор аренды лесов Юр'!AU144 -> 2.2 | J3: ='Договор аренды лесов Юр'!AU145 -> 3.1 | K3: ='Договор аренды лесов Юр'!AU146 -> 7.7 | M3: цена в сутки
B4: 43062 | E4: Кол-во | F4: ='Расчет лесов'!B8 -> 4 | G4: ='Расчет лесов'!B9 -> 4 | H4: ='Расчет лесов'!B10 -> 4 | I4: ='Расчет лесов'!B11 -> 4 | J4: ='Расчет лесов'!B12 -> 12 | K4: ='Расчет лесов'!B13 -> 8 | M4: =F4*$F$3+G4*$G$3+H4*$H$3+I4*$I$3+J4*$J$3+K4*$K$3+$N$4 -> 209.8 | N4: 0.2
B7: 1я сдача | E7: 43067 | F7: 2 | G7: 0 | H7: 2 | I7: 4 | J7: 5 | K7: 0 | N7: Дней аренды | O7: =E7-B4+1 -> 6 | P7: Сумма | Q7: =O7*M4 -> 1258.8
E8: Остаток | F8: =F4-F7 -> 2 | G8: =G4-G7 -> 4 | H8: =H4-H7 -> 2 | I8: =I4-I7 -> 0 | J8: =J4-J7 -> 7 | K8: =K4-K7 -> 8 | M8: =F8*$F$3+G8*$G$3+H8*$H$3+I8*$I$3+J8*$J$3+K8*$K$3 -> 157.3
B10: 2я сдача | E10: 43070 | F10: 0 | G10: 0 | H10: 0 | I10: 0 | J10: 0 | K10: 0 | N10: Дней аренды | O10: =E10-E7+1 -> 4 | P10: Сумма | Q10: =O10*M8 -> 629.2
E11: Остаток | F11: =F8-F10 -> 2 | G11: =G8-G10 -> 4 | H11: =H8-H10 -> 2 | I11: =I8-I10 -> 0 | J11: =J8-J10 -> 7 | K11: =K8-K10 -> 8 | M11: =F11*$F$3+G11*$G$3+H11*$H$3+I11*$I$3+J11*$J$3+K11*$K$3 -> 157.3
B13: 3я сдача | E13: 43070 | F13: 0 | G13: 0 | H13: 0 | I13: 0 | J13: 0 | K13: 0 | N13: Дней аренды | O13: =E13-E10+1 -> 1 | P13: Сумма | Q13: =O13*M11 -> 157.3
E14: Остаток | F14: =F11-F13 -> 2 | G14: =G11-G13 -> 4 | H14: =H11-H13 -> 2 | I14: =I11-I13 -> 0 | J14: =J11-J13 -> 7 | K14: =K11-K13 -> 8 | M14: =F14*$F$3+G14*$G$3+H14*$H$3+I14*$I$3+J14*$J$3+K14*$K$3 -> 157.3
B16: 4я сдача | E16: 43070 | F16: 0 | G16: 0 | H16: 0 | I16: 0 | J16: 0 | K16: 0 | N16: Дней аренды | O16: =E16-E13+1 -> 1 | P16: Сумма | Q16: =O16*M14 -> 157.3
E17: Остаток | F17: =F14-F16 -> 2 | G17: =G14-G16 -> 4 | H17: =H14-H16 -> 2 | I17: =I14-I16 -> 0 | J17: =J14-J16 -> 7 | K17: =K14-K16 -> 8 | M17: =F17*$F$3+G17*$G$3+H17*$H$3+I17*$I$3+J17*$J$3+K17*$K$3 -> 157.3
B19: 5я сдача | E19: 43070 | F19: 0 | G19: 0 | H19: 0 | I19: 0 | J19: 0 | K19: 0 | N19: Дней аренды | O19: =E19-E16+1 -> 1 | P19: Сумма | Q19: =O19*M17 -> 157.3
E20: Остаток | F20: =F17-F19 -> 2 | G20: =G17-G19 -> 4 | H20: =H17-H19 -> 2 | I20: =I17-I19 -> 0 | J20: =J17-J19 -> 7 | K20: =K17-K19 -> 8 | M20: =F20*$F$3+G20*$G$3+H20*$H$3+I20*$I$3+J20*$J$3+K20*$K$3 -> 157.3
O23: Остаток | Q23: =O1-Q7-Q10-Q13-Q16-Q19 -> 10140.1

Sheet Лист1
G3: 21400
G4: 25140
G5: 28900
G6: 34900
G7: 38500
G8: 42500
G9: 46300
G10: 50000
G11: 53700
G12: 57700
G13: 61000
G14: 65100
... G19: 83900
